Workbook

Sheet 00_GHID
A1: EQUIL GROWTH INTELLIGENCE — v0.2
A2: Pachet de colectare a datelor + motor de KPI, semnale și oportunități. Completează doar celulele galbene.
A4: LA CE FOLOSEȘTE | B4: Transformă datele brute ale unei firme în KPI, semnale de risc și oportunități de creștere prioritizate, plus un raport gata de prezentat.
A5: CUM SE FOLOSEȘTE
A6: Pas 1 — Profil | B6: Completează 01_FIRMA în discuția de kickoff. Durează 20 de minute și îți dă contextul pentru tot restul.
A7: Pas 2 — Oameni | B7: Completează 02_CONTACTE: cine, din firmă, deține fiecare set de date. Fără asta, colectarea se blochează.
A8: Pas 3 — Cerere date | B8: Trimite 03_CHECKLIST_DATE. Fiecare rând spune ce câmp ceri, din ce sistem se scoate, cine îl poate da și ce deblochează. Filtrează pe „Obligatoriu” pentru setul minim viabil.
A9: Pas 4 — Parametri | B9: Setează în 09_PARAMETRI perioada analizată, perioada de comparație și pragurile. Toate calculele se recalculează automat.
A10: Pas 5 — Import date | B10: Lipește datele în 10_CLIENTI, 11_PRODUSE, 12_OAMENI, 13_VANZARI, 14_TINTE, 15_NPS. Coloanele gri au formule — nu le suprascrie.
A11: Pas 6 — Citește | B11: Verifică 20_KPI, apoi 21/22/23 pentru semnale pe clienți, produse și oameni.
A12: Pas 7 — Prioritizează | B12: Preia semnalele în 30_OPORTUNITATI. Scor = Impact × Probabilitate × Ușurință. Prioritatea se calculează din pragurile din 09_PARAMETRI.
A13: Pas 8 — Prezintă | B13: 40_RAPORT este structura pentru clientul final; se completează singur din foile anterioare.
A15: COD DE CULORI
A16: Galben | B16: Celulă de completat (de tine sau de client).
A17: Gri | B17: Celulă calculată automat. Nu se scrie în ea.
A18: Verde-închis | B18: Antet de tabel.
A20: SETUL MINIM VIABIL | B20: Cu doar 3 lucruri se poate produce un prim raport: (1) vânzări pe 24 de luni cu client, produs, venit net și cost; (2) nomenclatorul de clienți; (3) ținta de venit pe perioadă. Restul îmbogățește analiza.
A21: ISTORIC RECOMANDAT | B21: Minim 13 luni (pentru comparație an/an), ideal 24-36 de luni.
A23: REGULI DE IGIENĂ A DATELOR
A24: Un ID = o entitate | B24: Fiecare client și produs are un singur ID, constant în toate foile.
A25: Valori fără TVA | B25: Veniturile și costurile se dau nete, în aceeași monedă.
A26: Stornări | B26: Se trec ca linii separate, cu valori negative.
A27: Fără celule „mixte” | B27: Nu combina text și cifre în aceeași celulă (ex. „12.000 lei” → 12000).
A28: Date personale | B28: Pentru NPS și oameni, folosește inițiale sau ID-uri dacă firma nu a agreat nominalizarea. Semnează NDA înainte de a primi datele.
A30: UN FIȘIER PENTRU FIECARE FIRMĂ
A31: Regula | B31: Nu amesteca două firme în același fișier. Păstrezi acest fișier ca șablon nemodificat și faci o copie pentru fiecare client.
A32: Cod de firmă | B32: Fiecare firmă primește un cod în 01_FIRMA (EQ-0001, EQ-0002…). Codul rămâne același pentru totdeauna, chiar dacă firma își schimbă numele.
A33: Nume fișier | B33: EQUIL_<cod>_<NumeFirma>_<AAAA-LL>.xlsx — ex. EQUIL_EQ-0001_AlfaSRL_2026-06.xlsx. Perioada din nume îți spune din ce rulaj e fișierul.
A34: Refolosire lunară | B34: Pentru luna următoare la aceeași firmă: copiază fișierul, schimbă perioada în 09_PARAMETRI și adaugă noile linii de vânzări. Nu ștergi istoricul.
A35: Șablonul | B35: Ține o copie curată, fără date, într-un folder separat („_SABLON”). Din ea pleacă fiecare firmă nouă.
A37: CÂT DUREAZĂ (estimat, prima rulare)
A38: 01_FIRMA | B38: 20-30 min, în discuția de kickoff, împreună cu clientul.
A39: 02_CONTACTE | B39: 10-15 min, tot la kickoff. Cea mai bună investiție de timp din tot procesul.
A40: 03_CHECKLIST_DATE | B40: 15 min să-l trimiți și să-l explici. Apoi 3-10 zile lucrătoare de așteptare, cu 2-3 follow-up-uri scurte.
A41: Import date | B41: 30-60 min dacă exporturile sunt curate. 2-4 ore dacă trebuie curățate manual (denumiri inconsecvente, valori cu text, ID-uri lipsă).
A42: 09_PARAMETRI | B42: 5 min. Pragurile se ajustează pe industrie.
A43: Citit 20-23 | B43: 30-45 min de citit semnalele și de verificat dacă au sens.
A44: 30_OPORTUNITATI | B44: 45-60 min: transformi semnalele în oportunități, estimezi impactul, pui responsabili.
A45: 40_RAPORT + grafice | B45: 30-45 min: concluziile automate îți dau schița, tu scrii varianta pentru client.
A46: TOTAL munca ta | B46: aprox. 4-6 ore de lucru efectiv, întinse pe 1-2 săptămâni calendaristice (așteptarea datelor domină).
A47: Rulările următoare | B47: 1-1,5 ore pe lună la aceeași firmă: adaugi datele noi, schimbi perioada, reciteşti semnalele.
A49: COMPATIBILITATE | B49: Fără funcții dinamice (UNIQUE/FILTER/LET/IFS). Funcționează în Excel 2016+, Microsoft 365, LibreOffice Calc și Google Sheets. Nu ai nevoie de o versiune mai nouă de Office pentru acest fișier.
A50: LIMITE ACTUALE | B50: Pre-formatat pentru 1000 de linii de vânzări, 200 de clienți, 100 de produse, 60 de persoane, 500 de răspunsuri NPS. Pentru volume mai mari, trage formulele în jos.
A51: URMĂTOAREA VERSIUNE | B51: Benchmark-uri de industrie, previziune de venit, scor de risc de churn, generare automată a naraţiunii din raport.

Sheet 01_FIRMA
A1: 01 — PROFILUL FIRMEI
A2: Se completează la kickoff, împreună cu clientul. Câmpurile galbene sunt de completat.
A4: IDENTIFICARE
A5: Cod client EQUIL | C5: ID-ul intern al firmei în portofoliul tău. Format recomandat: EQ-0001, EQ-0002…
A6: Denumire legală | C6: Exact ca la Registrul Comerțului.
A7: CUI / Cod fiscal
A8: Nr. Registrul Comerțului
A9: Site web
A10: Industrie / CAEN principal | C10: Determină benchmark-urile folosite.
A11: Sub-industrie / nișă
A12: An înființare
A13: Model de business | C13: B2B / B2C / Mix / Marketplace.
A14: Piețe / regiuni acoperite
A15: DIMENSIUNE
A16: Număr total angajați | C16: Total, nu doar vânzări.
A17: Din care în vânzări
A18: Cifra de afaceri — ultimul an încheiat | C18: Fără TVA.
A19: Profit brut — ultimul an încheiat
A20: Număr clienți activi | C20: Clienți cu cel puțin o achiziție în ultimele 12 luni.
A21: Număr produse / SKU active
A22: Sezonalitate | C22: Lunile de vârf și lunile slabe.
A23: SISTEME ȘI DATE
A24: ERP / sistem de facturare | C24: Ex. SAGA, WinMentor, SAP, Oracle NetSuite, Smartbill.
A25: CRM | C25: Ex. HubSpot, Pipedrive, Salesforce, Excel.
A26: Instrument de raportare | C26: Ex. Excel, Power BI, Looker, nimic.
A27: Se pot exporta datele în Excel/CSV? | C27: Da / Nu / Parțial — și cine face exportul.
A28: Istoric disponibil (luni) | C28: Câte luni de date se pot scoate din sisteme.
A29: Se măsoară deja NPS? | C29: Da / Nu. Dacă da, de când și cum.
A30: OBIECTIVE ȘI CONTEXT
A31: Obiectivul principal pe 12 luni | C31: Exprimat în cifre, dacă se poate.
A32: Cele 3 provocări majore
A33: Ce au încercat deja și nu a mers
A34: Cine ia decizia finală | C34: Numele și rolul decidentului.
A35: MANDAT EQUIL
A36: Perioada analizată | C36: Trebuie să coincidă cu 09_PARAMETRI.
A37: Moneda de raportare
A38: Consultant EQUIL responsabil
A39: Data kickoff
A40: Data livrării raportului
A41: NDA semnat | C41: Da / Nu / Data. NDA = acord de confidențialitate; vezi 04_DICTIONAR.
A42: Nume fișier | C42: Convenție: EQUIL_<cod>_<NumeFirma>_<AAAA-LL>.xlsx — ex. EQUIL_EQ-0001_AlfaSRL_2026-06.xlsx

Sheet 02_CONTACTE
A1: 02 — CINE FURNIZEAZĂ DATELE (data owners)
A2: Sfat: nu cere „toate datele”. Cere de la fiecare om exact setul din 03_CHECKLIST_DATE care îi este atribuit, cu un termen concret.
A4: Cod contact Contact_ID | B4: Rol în firmă Rol_in_firma | C4: Nume și prenume Nume | D4: Funcția exactă Functie_exacta | E4: Email Email | F4: Telefon Telefon | G4: Ce date poate furniza Seturi_de_date_detinute | H4: Sisteme la care are acces Sisteme_la_care_are_acces | I4: Poate aproba transmiterea? (Da/Nu) Decident | J4: Canal preferat de contact Canal_preferat | K4: Disponibilitate Disponibilitate | L4: Data solicitării Data_solicitarii | M4: Termen agreat Termen_agreat | N4: Status Status | O4: Observații Observatii
A5: CT01 | B5: CEO / Administrator | G5: Obiective, context strategic, aprobarea transmiterii datelor | H5: — | I5: Da | J5: Întâlnire | N5: Nesolicitat | O5: Decide ce date pot ieși din firmă.
A6: CT02 | B6: CFO / Contabilitate | G6: Venituri, costuri (COGS), balanță, ținte/buget, termene de plată | H6: ERP, contabilitate | I6: Da | J6: Email | N6: Nesolicitat | O6: Sursa principală pentru profit brut și marjă.
A7: CT03 | B7: Director Vânzări | G7: Clienți, segmente, canale, ținte pe oameni, context comercial | H7: CRM | I7: Da | J7: Telefon | N7: Nesolicitat | O7: Validează interpretarea semnalelor.
A8: CT04 | B8: Sales Ops / CRM | G8: Export CRM: clienți, responsabili de cont, pipeline, activitate | H8: CRM | I8: Nu | J8: Email | N8: Nesolicitat | O8: De obicei cel care face efectiv exportul.
A9: CT05 | B9: IT / ERP | G9: Export brut din ERP: facturi, nomenclator produse, clienți | H9: ERP | I9: Nu | J9: Email | N9: Nesolicitat | O9: Cere formatul CSV/XLSX, nu PDF.
A10: CT06 | B10: Marketing | G10: NPS, campanii, lansări de produs, lead-uri | H10: Survey, web | I10: Nu | J10: Email | N10: Nesolicitat | O10: Deține de obicei instrumentul de chestionar.
A11: CT07 | B11: HR / Resurse Umane | G11: Structura echipei, FTE, intrări/ieșiri, cost cu personalul | H11: HR / salarizare | I11: Da | J11: Email | N11: Nesolicitat | O11: Atenție la GDPR: cere agregat sau anonimizat.
A12: CT08 | B12: Customer Service | G12: Reclamații, motive de nemulțumire, follow-up detractori | H12: Ticketing | I12: Nu | J12: Telefon | N12: Nesolicitat | O12: Sursa cea mai bogată de cauze calitative.
A13: CT09 | B13: Operațiuni / Logistică | G13: Livrări, stocuri, termene, capacitate | H13: ERP / WMS | I13: Nu | J13: Email | N13: Nesolicitat | O13: Relevant când NPS scade din cauza livrării.

Sheet 03_CHECKLIST_DATE
A1: 03 — CE DATE CER ȘI DE LA CINE
A2: Lista completă a câmpurilor. Filtrează pe Obligatoriu = „Obligatoriu” pentru setul minim viabil. Coloana „Persoana” se leagă de numele din 02_CONTACTE.
A4: ID | B4: Set de date | C4: Foaie destinație | D4: Câmp (tehnic) | E4: Denumire RO | F4: Ce înseamnă / cum se completează | G4: Obligatoriu | H4: Format / unitate | I4: Exemplu | J4: Sursă tipică | K4: Rol furnizor | L4: Persoana (nume) | M4: Ce deblochează | N4: Status | O4: Data primirii | P4: Observații | R4: PROGRES COLECTARE
A5: D001 | B5: Profil firmă | C5: 01_FIRMA | E5: Profil complet firmă | F5: Se completează în discuția de kickoff: identificare, dimensiune, sisteme, obiective. | G5: Obligatoriu | H5: Text | I5: vezi 01_FIRMA | J5: Interviu / Workshop | K5: CEO / Administrator | M5: Context pentru toate interpretările | N5: Nesolicitat | R5: Total câmpuri cerute | S5: =COUNTA($A$5:$A$70)
A6: D002 | B6: Documente / context | C6: — | E6: NDA semnat | F6: Acord de confidențialitate semnat înainte de transmiterea oricăror date. | G6: Obligatoriu | H6: PDF | I6: NDA_2026.pdf | J6: Interviu / Workshop | K6: CEO / Administrator | M6: Permite transmiterea legală a datelor | N6: Nesolicitat | R6: Din care obligatorii | S6: =COUNTIF($G$5:$G$70,"Obligatoriu")
A7: D003 | B7: Documente / context | C7: — | E7: Organigramă echipă comercială | F7: Structura echipei: cine cui raportează, cine acoperă ce zonă sau segment. | G7: Recomandat | H7: PDF / imagine | I7: organigrama.pdf | J7: HR / State de plată | K7: HR / Resurse Umane | M7: Interpretarea corectă a analizei pe oameni | N7: Nesolicitat | R7: Primite sau validate | S7: =COUNTIF($N$5:$N$70,"Primit")+COUNTIF($N$5:$N$70,"Validat")
A8: D004 | B8: Documente / context | C8: — | E8: Listă de prețuri și politică de discount | F8: Prețurile de listă și regulile de discount pe segment sau volum. | G8: Recomandat | H8: XLSX | I8: pricelist_2026.xlsx | J8: Excel intern | K8: Director Vânzări | M8: Analiza erodării de preț și a marjei | N8: Nesolicitat | R8: Obligatorii încă lipsă | S8: =COUNTIFS($G$5:$G$70,"Obligatoriu",$N$5:$N$70,"<>Primit",$N$5:$N$70,"<>Validat")
A9: D005 | B9: Financiar | C9: — | E9: Balanță / P&L ultimele 24 de luni | F9: Pentru validarea veniturilor și a costurilor față de contabilitate. | G9: Recomandat | H9: XLSX / PDF | I9: balanta_2025.xlsx | J9: Balanță / Contabilitate | K9: CFO / Contabilitate | M9: Verificarea consistenței cifrelor | N9: Nesolicitat | R9: Blocate | S9: =COUNTIF($N$5:$N$70,"Blocat")
A10: D006 | B10: Financiar | C10: — | E10: Cheltuieli fixe lunare (agregat) | F10: Costuri indirecte lunare, agregat. Nu e nevoie de detaliu pe furnizor. | G10: Opțional | H10: Valoare / lună | I10: 180000 | J10: Balanță / Contabilitate | K10: CFO / Contabilitate | M10: Prag de rentabilitate, impact real al oportunităților | N10: Nesolicitat | R10: % completare | S10: =IFERROR((S7)/(S5),0)
A11: D007 | B11: Documente / context | C11: — | E11: Acces la export ERP (recurent) | F11: Cine face exportul lunar și în ce format, pentru actualizări periodice. | G11: Recomandat | H11: Proces | I11: export lunar CSV | J11: ERP / Facturare | K11: IT / ERP | M11: Repetabilitatea raportului, nu doar o dată | N11: Nesolicitat | R11: % completare obligatorii | S11: =IFERROR(1-(S8)/(S6),0)
A12: D008 | B12: Vânzări | C12: 13_VANZARI | D12: Doc_Date | E12: Data document | F12: Data facturii sau a lunii de raportare. O linie = o combinație client × produs × perioadă. | G12: Obligatoriu | H12: yyyy-mm-dd | I12: 2026-01-31 | J12: ERP / Facturare | K12: CFO / Contabilitate | M12: Toate KPI-urile și trendurile | N12: Nesolicitat
A13: D009 | B13: Vânzări | C13: 13_VANZARI | D13: Doc_Type | E13: Tip document | F13: Factură / Storno / Avans. Stornările se trec cu valori negative. | G13: Recomandat | H13: Text | I13: Factură | J13: ERP / Facturare | K13: CFO / Contabilitate | M13: Corectitudinea veniturilor | N13: Nesolicitat
A14: D010 | B14: Vânzări | C14: 13_VANZARI | D14: Customer_ID | E14: ID client | F14: Trebuie să existe în 10_CLIENTI. | G14: Obligatoriu | H14: Text | I14: C001 | J14: ERP / Facturare | K14: IT / ERP | M14: Analiză client, concentrare | N14: Nesolicitat
A15: D011 | B15: Vânzări | C15: 13_VANZARI | D15: Product_ID | E15: ID produs | F15: Trebuie să existe în 11_PRODUSE. | G15: Obligatoriu | H15: Text | I15: P001 | J15: ERP / Facturare | K15: IT / ERP | M15: Analiză produs, cross-sell | N15: Nesolicitat
A16: D012 | B16: Vânzări | C16: 13_VANZARI | D16: Person_ID | E16: ID persoană vânzări | F16: Cine a făcut vânzarea; trebuie să existe în 12_OAMENI. | G16: Recomandat | H16: Text | I16: S001 | J16: CRM | K16: Sales Ops / CRM | M16: Productivitate pe om | N16: Nesolicitat
A17: D013 | B17: Vânzări | C17: 13_VANZARI | D17: Units | E17: Cantitate | F17: Număr de unități / ore / licențe. | G17: Recomandat | H17: #,##0.00 | I17: 100 | J17: ERP / Facturare | K17: IT / ERP | M17: Preț mediu, volum vs. preț | N17: Nesolicitat
A18: D014 | B18: Vânzări | C18: 13_VANZARI | D18: Revenue_Net | E18: Venit net | F18: Venit fără TVA, după discount. | G18: Obligatoriu | H18: #,##0 | I18: 10000 | J18: ERP / Facturare | K18: CFO / Contabilitate | M18: Venit, creștere, țintă | N18: Nesolicitat
A19: D015 | B19: Vânzări | C19: 13_VANZARI | D19: Discount_Value | E19: Valoare discount | F19: Discountul acordat, în valoare absolută. | G19: Opțional | H19: #,##0 | I19: 800 | J19: ERP / Facturare | K19: CFO / Contabilitate | M19: Erodare preț, marjă | N19: Nesolicitat
A20: D016 | B20: Vânzări | C20: 13_VANZARI | D20: COGS | E20: Cost direct (COGS) | F20: Costul direct aferent vânzării. | G20: Obligatoriu | H20: #,##0 | I20: 7500 | J20: Balanță / Contabilitate | K20: CFO / Contabilitate | M20: Profit brut, marjă | N20: Nesolicitat
A21: D017 | B21: Vânzări | C21: 13_VANZARI | D21: Currency | E21: Monedă | F21: Moneda documentului. Ideal toate liniile în aceeași monedă. | G21: Recomandat | H21: Text | I21: RON | J21: ERP / Facturare | K21: CFO / Contabilitate | M21: Consistența raportării | N21: Nesolicitat
A22: D018 | B22: Vânzări | C22: 13_VANZARI | D22: Notes | E22: Observații | F22: Context pe linie, dacă e nevoie. | G22: Opțional | H22: Text | J22: Interviu / Workshop | K22: Director Vânzări | M22: Context | N22: Nesolicitat
A23: D019 | B23: Clienți | C23: 10_CLIENTI | D23: Customer_ID | E23: ID client | F23: Cod unic de client, exact cum apare în ERP/CRM. Se folosește în foaia de vânzări. | G23: Obligatoriu | H23: Text | I23: C001 | J23: ERP / Facturare | K23: IT / ERP | M23: Toate analizele pe client | N23: Nesolicitat
A24: D020 | B24: Clienți | C24: 10_CLIENTI | D24: Customer_Name | E24: Denumire client | F24: Denumirea comercială a clientului. | G24: Obligatoriu | H24: Text | I24: Alfa Distribution SRL | J24: ERP / Facturare | K24: Director Vânzări | M24: Raport client, top clienți | N24: Nesolicitat
A25: D021 | B25: Clienți | C25: 10_CLIENTI | D25: Segment | E25: Segment | F25: Segmentul de client (ex. Key Account, Mid, Small, Online). | G25: Recomandat | H25: Text | I25: Key Account | J25: CRM | K25: Director Vânzări | M25: Analiză pe segmente | N25: Nesolicitat
A26: D022 | B26: Clienți | C26: 10_CLIENTI | D26: Channel | E26: Canal | F26: Canalul prin care se vinde: Retail, Wholesale, Online, Direct, Partener. | G26: Recomandat | H26: Text | I26: Wholesale | J26: CRM | K26: Director Vânzări | M26: Mix de canal, oportunități cross-sell | N26: Nesolicitat
A27: D023 | B27: Clienți | C27: 10_CLIENTI | D27: Region | E27: Regiune / Țară | F27: Regiunea sau țara clientului. | G27: Recomandat | H27: Text | I27: București-Ilfov | J27: ERP / Facturare | K27: Sales Ops / CRM | M27: Analiză geografică | N27: Nesolicitat
A28: D024 | B28: Clienți | C28: 10_CLIENTI | D28: Country | E28: Țară | F28: Cod țară (RO, HU, BG...). | G28: Opțional | H28: Text | I28: RO | J28: ERP / Facturare | K28: Sales Ops / CRM | M28: Export vs. intern | N28: Nesolicitat
A29: D025 | B29: Clienți | C29: 10_CLIENTI | D29: Account_Owner_ID | E29: ID responsabil cont | F29: ID-ul persoanei din 12_OAMENI care răspunde de acest client. | G29: Recomandat | H29: Text | I29: S001 | J29: CRM | K29: Director Vânzări | M29: Analiză pe oameni, plan de acțiune | N29: Nesolicitat
A30: D026 | B30: Clienți | C30: 10_CLIENTI | D30: Customer_Since | E30: Client din data | F30: Data primei relații comerciale. | G30: Recomandat | H30: yyyy-mm-dd | I30: 2021-03-15 | J30: ERP / Facturare | K30: Sales Ops / CRM | M30: Vechime, retenție, clienți noi | N30: Nesolicitat
A31: D027 | B31: Clienți | C31: 10_CLIENTI | D31: Status | E31: Status | F31: Activ / Inactiv / Prospect / Pierdut. | G31: Recomandat | H31: Text | I31: Activ | J31: CRM | K31: Director Vânzări | M31: Reactivare clienți dormanți | N31: Nesolicitat
A32: D028 | B32: Clienți | C32: 10_CLIENTI | D32: Payment_Terms_Days | E32: Termen plată (zile) | F32: Termenul de plată agreat, în zile. | G32: Opțional | H32: #,##0 | I32: 30 | J32: Balanță / Contabilitate | K32: CFO / Contabilitate | M32: Cash-flow, risc | N32: Nesolicitat
A33: D029 | B33: Clienți | C33: 10_CLIENTI | D33: Credit_Limit | E33: Limită credit | F33: Plafonul de credit acordat. | G33: Opțional | H33: #,##0 | I33: 50000 | J33: Balanță / Contabilitate | K33: CFO / Contabilitate | M33: Risc comercial | N33: Nesolicitat
A34: D030 | B34: Clienți | C34: 10_CLIENTI | D34: Notes | E34: Observații | F34: Context util: istoric, relație, riscuri cunoscute. | G34: Opțional | H34: Text | I34: Renegociere contract în T3 | J34: Interviu / Workshop | K34: Director Vânzări | M34: Context pentru recomandări | N34: Nesolicitat
... A67: D063 | B67: Oameni | C67: 12_OAMENI | D67: Start_Date | E67: Data angajării | F67: Data intrării în echipă. | G67: Recomandat | H67: yyyy-mm-dd | I67: 2023-02-01 | J67: HR / State de plată | K67: HR / Resurse Umane | M67: FTE activ pe perioadă | N67: Nesolicitat
A68: D064 | B68: Oameni | C68: 12_OAMENI | D68: Exit_Date | E68: Data plecării | F68: Se lasă gol dacă persoana este activă. | G68: Recomandat | H68: yyyy-mm-dd | J68: HR / State de plată | K68: HR / Resurse Umane | M68: FTE activ, fluctuație | N68: Nesolicitat
A69: D065 | B69: Oameni | C69: 12_OAMENI | D69: Annual_Cost | E69: Cost anual total | F69: Cost total angajator pe an (opțional, se poate da agregat pe echipă). | G69: Opțional | H69: #,##0 | I69: 96000 | J69: HR / State de plată | K69: CFO / Contabilitate | M69: ROI pe om, cost/venit | N69: Nesolicitat
A70: D066 | B70: Oameni | C70: 12_OAMENI | D70: Is_Quota_Carrying | E70: Are țintă (Da/Nu) | F70: Dacă persoana are țintă de vânzări. | G70: Recomandat | H70: Text | I70: Da | J70: Director Vânzări | K70: Director Vânzări | M70: Atingere țintă pe om | N70: Nesolicitat

Sheet 04_DICTIONAR
A1: 04 — DICȚIONAR DE TERMENI
A2: Fiecare termen din fișier, explicat pe scurt, cu formularea pe care o poți folosi direct în discuția cu clientul. Filtrează pe „Categorie” ca să vezi doar ce te interesează.
A4: Termen | B4: Categorie | C4: Ce înseamnă | D4: De ce contează pentru analiză | E4: Cum îl ceri / unde îl găsești
A5: NDA (Non-Disclosure Agreement) | B5: Proces | C5: Acord de confidențialitate. Un contract scurt prin care te obligi să nu divulgi și să nu folosești în alt scop datele primite. | D5: Fără el, majoritatea firmelor serioase nu îți dau cifre reale. Îl semnezi înainte de prima cerere de date. | E5: „Vă propun să semnăm un acord de confidențialitate înainte să îmi trimiteți orice cifră. Aveți un model al dumneavoastră sau folosim al meu?”
A6: Kickoff | B6: Proces | C6: Întâlnirea de start a proiectului, în care stabilești obiectivul, perioada analizată, cine ce dă și până când. | D6: Aici completezi 01_FIRMA și 02_CONTACTE. Un kickoff bun scurtează colectarea cu săptămâni. | E6: „Propun o oră împreună la început, ca să stabilim exact ce ne uităm și cine îmi trimite ce.”
A7: Data kickoff | B7: Proces | C7: Data la care a avut loc întâlnirea de start. Este ziua zero a proiectului. | D7: De la ea numeri termenele. Dacă livrarea întârzie, de aici vezi unde s-a pierdut timpul. | E7: Se completează în 01_FIRMA, secțiunea MANDAT EQUIL.
A8: Data owner | B8: Proces | C8: Persoana din firmă care deține efectiv un set de date și îl poate scoate din sistem. | D8: Nu firma îți dă datele, ci un om anume. Foaia 02_CONTACTE există exact pentru asta. | E8: „Cine, concret, poate scoate din ERP lista de facturi pe ultimele 24 de luni?”
A9: Stakeholder / decident | B9: Proces | C9: Persoana care ia decizia finală și aprobă bugetele. Nu e întotdeauna cine te-a contactat. | D9: Raportul trebuie scris pentru decident. Dacă el nu e în discuție, concluziile rămân pe hârtie. | E9: „Cine semnează la final pentru acțiunile pe care le propunem?”
A10: Scope / mandat | B10: Proces | C10: Ce intră și ce NU intră în proiect: ce perioadă, ce linii de business, ce nu analizăm. | D10: Previne extinderea nelimitată a muncii („dar puteți să vă uitați și la...”). | E10: „Ne uităm la vânzări și clienți pe ultimele 24 de luni. Stocurile și producția nu intră acum.”
A11: Livrabil (deliverable) | B11: Proces | C11: Rezultatul concret pe care îl predai: în cazul nostru, raportul din 40_RAPORT plus planul de acțiuni. | D11: Clientul trebuie să știe din prima ce primește, ca să nu aibă alte așteptări. | E11: „La final primiți un raport cu 5 oportunități prioritizate și un plan pe 30 de zile.”
A12: Follow-up | B12: Proces | C12: Revenirea cu o solicitare sau o acțiune după o discuție. În colectarea de date, reamintirea politicoasă. | D12: Datele întârzie aproape întotdeauna. Două-trei follow-up-uri scurte sunt normale, nu insistență. | E12: „Vă reamintesc de exportul din ERP — de el depinde restul analizei. Puteți până vineri?”
A13: Workshop | B13: Proces | C13: Sesiune de lucru cu mai mulți oameni din firmă, în care validezi concluziile și construiești planul. | D13: Oportunitățile validate împreună cu echipa se execută. Cele trimise pe email, mai rar. | E13: „Propun 90 de minute cu echipa de vânzări, să validăm împreună ce am găsit.”
A14: GDPR | B14: Proces | C14: Regulamentul european de protecție a datelor personale. Numele, emailul sau telefonul unei persoane sunt date personale. | D14: Pentru NPS și pentru echipă, cere date anonimizate (inițiale sau ID-uri) dacă nu ai un temei clar. | E14: „Îmi puteți trimite lista cu inițiale în loc de nume complete? Analiza funcționează la fel.”
A15: ERP | B15: Sisteme | C15: Enterprise Resource Planning — programul central în care firma ține facturi, stocuri, furnizori, uneori contabilitatea. „Sistemul în care se face factura.” | D15: Sursa principală pentru vânzări, clienți, produse și costuri. Fără el, datele vin din Excel-uri paralele, cu erori. | E15: „În ce program emiteți facturile?” Exemple în România: SAGA, WinMentor, Smartbill, Nexus, Charisma, SAP, Oracle NetSuite.
... A70: Formatare condiționată | B70: Excel | C70: Colorarea automată a celulelor în funcție de valoare sau text. | D70: Prioritățile HIGH/MEDIUM/LOW și semnalele se colorează singure. | E70: —

Sheet 09_PARAMETRI
A1: 09 — PARAMETRI (panoul de control)
A2: Aici se setează perioada și pragurile. Tot restul fișierului se recalculează automat.
A4: PERIOADA DE ANALIZĂ
A5: Perioada curentă — de la | B5: 46023 | C5: Prima zi a perioadei analizate.
A6: Perioada curentă — până la | B6: 46203 | C6: Ultima zi a perioadei analizate.
A7: Perioada de comparație — de la | B7: 45658 | C7: De regulă aceeași perioadă din anul anterior.
A8: Perioada de comparație — până la | B8: 45838
A9: Data de referință | B9: =IF($B$6="",TODAY(),$B$6) | C9: Față de ea se numără zilele de inactivitate. Implicit = ultima zi a perioadei analizate, ca să nu apară dormanți artificiali când analizezi o perioadă din trecut. Poți scrie în loc =TODAY() sau o dată fixă.
A10: Moneda de raportare | B10: RON | C10: Toate valorile trebuie să fie în aceeași monedă.
A12: PRAGURI PENTRU SEMNALE
A13: Scădere de venit considerată alertă | B13: -0.15 | C13: Ex. −15%: sub acest nivel, clientul intră în „Scădere venit”.
A14: Creștere considerată oportunitate | B14: 0.2 | C14: Peste acest nivel, produsul/clientul e marcat ca „în creștere”.
A15: Marjă brută de referință | B15: 0.3 | C15: Sub acest nivel se semnalează problemă de marjă.
A16: Zile fără achiziție = client dormant | B16: 90 | C16: Numărul de zile de la ultima achiziție.
A17: Prag NPS acceptabil | B17: 30 | C17: NPS sub acest nivel declanșează plan de recuperare.
A18: Prag de atingere a țintei | B18: 0.9 | C18: Sub acest nivel se semnalează gap față de țintă.
A19: Concentrare: prag pe un singur client | B19: 0.2 | C19: Peste acest procent din venit, clientul e risc de concentrare.
A20: Venit minim pentru a intra în analiză | B20: 0 | C20: Ignoră clienții sub acest venit, ca să nu se aglomereze raportul.
A22: PRAGURI DE PRIORITIZARE A OPORTUNITĂȚILOR
A23: Scor minim pentru prioritate HIGH | B23: 40000 | C23: Scor = Impact × Probabilitate × Ușurință.
A24: Scor minim pentru prioritate MEDIUM | B24: 20000
A26: META
A27: Client analizat | B27: =IF('01_FIRMA'!B5="","[completează 01_FIRMA]",'01_FIRMA'!B5) | C27: Se preia din 01_FIRMA.
A28: Consultant EQUIL
A29: Versiune fișier | B29: v0.2
A30: Data generării raportului

Sheet 10_CLIENTI
A1: 10 — CLIENȚI (NOMENCLATOR)
A2: Galben = se completează. Gri = calculat automat, nu suprascrie.
A4: ID client Customer_ID | B4: Denumire client Customer_Name | C4: Segment Segment | D4: Canal Channel | E4: Regiune / Țară Region | F4: Țară Country | G4: ID responsabil cont Account_Owner_ID | H4: Client din data Customer_Since | I4: Status Status | J4: Termen plată (zile) Payment_Terms_Days | K4: Limită credit Credit_Limit | L4: Observații Notes
A5: C001 | B5: Alfa Distribution SRL | C5: Key Account | D5: Wholesale | E5: București-Ilfov | F5: RO | G5: S001 | H5: 44270 | I5: Activ | J5: 30 | K5: 50000 | L5: Exemplu — șterge înainte de utilizare
A6: C002 | B6: Beta Retail SA | C6: Mid-market | D6: Retail | E6: Cluj | F6: RO | G6: S002 | H6: 45078 | I6: Activ | J6: 15 | K6: 20000 | L6: Exemplu — șterge înainte de utilizare

Sheet 11_PRODUSE
A1: 11 — PRODUSE / SERVICII (NOMENCLATOR)
A2: Galben = se completează. Gri = calculat automat, nu suprascrie.
A4: ID produs Product_ID | B4: Denumire produs Product_Name | C4: Categorie Category | D4: Subcategorie Subcategory | E4: Preț de listă List_Price | F4: Cost standard Standard_Cost | G4: Recurent (Da/Nu) Is_Recurring | H4: Data lansării Launch_Date | I4: Status Status
A5: P001 | B5: Produs X | C5: Categoria A | E5: 120 | F5: 84 | G5: Nu | I5: Activ
A6: P002 | B6: Serviciu Y | C6: Servicii recurente | E6: 1200 | F6: 600 | G6: Da | I6: Activ

Sheet 12_OAMENI
A1: 12 — OAMENI (ECHIPA COMERCIALĂ / OPERAȚIONALĂ)
A2: Galben = se completează. Gri = calculat automat, nu suprascrie.
A4: ID persoană Person_ID | B4: Nume Person_Name | C4: Rol Role | D4: Echipă Team | E4: FTE (normă) FTE | F4: Data angajării Start_Date | G4: Data plecării Exit_Date | H4: Cost anual total Annual_Cost | I4: Are țintă (Da/Nu) Is_Quota_Carrying
A5: S001 | B5: Ana P. | C5: Key Account Manager | D5: Vânzări B2B | E5: 1 | F5: 44958 | H5: 96000 | I5: Da
A6: S002 | B6: Bogdan M. | C6: Sales Representative | D6: Vânzări B2B | E6: 1 | F6: 45536 | H6: 72000 | I6: Da

Sheet 13_VANZARI
A1: 13 — VÂNZĂRI / TRANZACȚII (FAPTIC)
A2: Galben = se completează. Gri = calculat automat, nu suprascrie.
A4: Data document Doc_Date | B4: Perioadă (AAAA-LL) Period | C4: Tip document Doc_Type | D4: ID client Customer_ID | E4: ID produs Product_ID | F4: ID persoană vânzări Person_ID | G4: Cantitate Units | H4: Venit net Revenue_Net | I4: Valoare discount Discount_Value | J4: Cost direct (COGS) COGS | K4: Profit brut Gross_Profit | L4: Marjă % Margin_Pct | M4: Denumire client Customer_Name | N4: Denumire produs Product_Name | O4: Monedă Currency | P4: Observații Notes
A5: 46053 | B5: =IF($A5="","",YEAR($A5)&"-"&RIGHT("0"&MONTH($A5),2)) | C5: Factură | D5: C001 | E5: P001 | F5: S001 | G5: 100 | H5: 10000 | I5: 0 | J5: 7500 | K5: =IF($H5="","",$H5-N($J5)) | L5: =IFERROR($K5/$H5,"") | M5: =IFERROR(INDEX('10_CLIENTI'!$B$5:$B$204,MATCH($D5,'10_CLIENTI'!$A$5:$A$204,0)),"") | N5: =IFERROR(INDEX('11_PRODUSE'!$B$5:$B$104,MATCH($E5,'11_PRODUSE'!$A$5:$A$104,0)),"") | O5: RON | P5: Exemplu — șterge înainte de utilizare
A6: 46053 | B6: =IF($A6="","",YEAR($A6)&"-"&RIGHT("0"&MONTH($A6),2)) | C6: Factură | D6: C002 | E6: P002 | F6: S002 | G6: 10 | H6: 12000 | I6: 500 | J6: 6000 | K6: =IF($H6="","",$H6-N($J6)) | L6: =IFERROR($K6/$H6,"") | M6: =IFERROR(INDEX('10_CLIENTI'!$B$5:$B$204,MATCH($D6,'10_CLIENTI'!$A$5:$A$204,0)),"") | N6: =IFERROR(INDEX('11_PRODUSE'!$B$5:$B$104,MATCH($E6,'11_PRODUSE'!$A$5:$A$104,0)),"") | O6: RON | P6: Exemplu — șterge înainte de utilizare
B7: =IF($A7="","",YEAR($A7)&"-"&RIGHT("0"&MONTH($A7),2)) | K7: =IF($H7="","",$H7-N($J7)) | L7: =IFERROR($K7/$H7,"") | M7: =IFERROR(INDEX('10_CLIENTI'!$B$5:$B$204,MATCH($D7,'10_CLIENTI'!$A$5:$A$204,0)),"") | N7: =IFERROR(INDEX('11_PRODUSE'!$B$5:$B$104,MATCH($E7,'11_PRODUSE'!$A$5:$A$104,0)),"")
B8: =IF($A8="","",YEAR($A8)&"-"&RIGHT("0"&MONTH($A8),2)) | K8: =IF($H8="","",$H8-N($J8)) | L8: =IFERROR($K8/$H8,"") | M8: =IFERROR(INDEX('10_CLIENTI'!$B$5:$B$204,MATCH($D8,'10_CLIENTI'!$A$5:$A$204,0)),"") | N8: =IFERROR(INDEX('11_PRODUSE'!$B$5:$B$104,MATCH($E8,'11_PRODUSE'!$A$5:$A$104,0)),"")
B9: =IF($A9="","",YEAR($A9)&"-"&RIGHT("0"&MONTH($A9),2)) | K9: =IF($H9="","",$H9-N($J9)) | L9: =IFERROR($K9/$H9,"") | M9: =IFERROR(INDEX('10_CLIENTI'!$B$5:$B$204,MATCH($D9,'10_CLIENTI'!$A$5:$A$204,0)),"") | N9: =IFERROR(INDEX('11_PRODUSE'!$B$5:$B$104,MATCH($E9,'11_PRODUSE'!$A$5:$A$104,0)),"")
B10: =IF($A10="","",YEAR($A10)&"-"&RIGHT("0"&MONTH($A10),2)) | K10: =IF($H10="","",$H10-N($J10)) | L10: =IFERROR($K10/$H10,"") | M10: =IFERROR(INDEX('10_CLIENTI'!$B$5:$B$204,MATCH($D10,'10_CLIENTI'!$A$5:$A$204,0)),"") | N10: =IFERROR(INDEX('11_PRODUSE'!$B$5:$B$104,MATCH($E10,'11_PRODUSE'!$A$5:$A$104,0)),"")
B11: =IF($A11="","",YEAR($A11)&"-"&RIGHT("0"&MONTH($A11),2)) | K11: =IF($H11="","",$H11-N($J11)) | L11: =IFERROR($K11/$H11,"") | M11: =IFERROR(INDEX('10_CLIENTI'!$B$5:$B$204,MATCH($D11,'10_CLIENTI'!$A$5:$A$204,0)),"") | N11: =IFERROR(INDEX('11_PRODUSE'!$B$5:$B$104,MATCH($E11,'11_PRODUSE'!$A$5:$A$104,0)),"")
B12: =IF($A12="","",YEAR($A12)&"-"&RIGHT("0"&MONTH($A12),2)) | K12: =IF($H12="","",$H12-N($J12)) | L12: =IFERROR($K12/$H12,"") | M12: =IFERROR(INDEX('10_CLIENTI'!$B$5:$B$204,MATCH($D12,'10_CLIENTI'!$A$5:$A$204,0)),"") | N12: =IFERROR(INDEX('11_PRODUSE'!$B$5:$B$104,MATCH($E12,'11_PRODUSE'!$A$5:$A$104,0)),"")
B13: =IF($A13="","",YEAR($A13)&"-"&RIGHT("0"&MONTH($A13),2)) | K13: =IF($H13="","",$H13-N($J13)) | L13: =IFERROR($K13/$H13,"") | M13: =IFERROR(INDEX('10_CLIENTI'!$B$5:$B$204,MATCH($D13,'10_CLIENTI'!$A$5:$A$204,0)),"") | N13: =IFERROR(INDEX('11_PRODUSE'!$B$5:$B$104,MATCH($E13,'11_PRODUSE'!$A$5:$A$104,0)),"")
B14: =IF($A14="","",YEAR($A14)&"-"&RIGHT("0"&MONTH($A14),2)) | K14: =IF($H14="","",$H14-N($J14)) | L14: =IFERROR($K14/$H14,"") | M14: =IFERROR(INDEX('10_CLIENTI'!$B$5:$B$204,MATCH($D14,'10_CLIENTI'!$A$5:$A$204,0)),"") | N14: =IFERROR(INDEX('11_PRODUSE'!$B$5:$B$104,MATCH($E14,'11_PRODUSE'!$A$5:$A$104,0)),"")
B15: =IF($A15="","",YEAR($A15)&"-"&RIGHT("0"&MONTH($A15),2)) | K15: =IF($H15="","",$H15-N($J15)) | L15: =IFERROR($K15/$H15,"") | M15: =IFERROR(INDEX('10_CLIENTI'!$B$5:$B$204,MATCH($D15,'10_CLIENTI'!$A$5:$A$204,0)),"") | N15: =IFERROR(INDEX('11_PRODUSE'!$B$5:$B$104,MATCH($E15,'11_PRODUSE'!$A$5:$A$104,0)),"")
B16: =IF($A16="","",YEAR($A16)&"-"&RIGHT("0"&MONTH($A16),2)) | K16: =IF($H16="","",$H16-N($J16)) | L16: =IFERROR($K16/$H16,"") | M16: =IFERROR(INDEX('10_CLIENTI'!$B$5:$B$204,MATCH($D16,'10_CLIENTI'!$A$5:$A$204,0)),"") | N16: =IFERROR(INDEX('11_PRODUSE'!$B$5:$B$104,MATCH($E16,'11_PRODUSE'!$A$5:$A$104,0)),"")
B17: =IF($A17="","",YEAR($A17)&"-"&RIGHT("0"&MONTH($A17),2)) | K17: =IF($H17="","",$H17-N($J17)) | L17: =IFERROR($K17/$H17,"") | M17: =IFERROR(INDEX('10_CLIENTI'!$B$5:$B$204,MATCH($D17,'10_CLIENTI'!$A$5:$A$204,0)),"") | N17: =IFERROR(INDEX('11_PRODUSE'!$B$5:$B$104,MATCH($E17,'11_PRODUSE'!$A$5:$A$104,0)),"")
B18: =IF($A18="","",YEAR($A18)&"-"&RIGHT("0"&MONTH($A18),2)) | K18: =IF($H18="","",$H18-N($J18)) | L18: =IFERROR($K18/$H18,"") | M18: =IFERROR(INDEX('10_CLIENTI'!$B$5:$B$204,MATCH($D18,'10_CLIENTI'!$A$5:$A$204,0)),"") | N18: =IFERROR(INDEX('11_PRODUSE'!$B$5:$B$104,MATCH($E18,'11_PRODUSE'!$A$5:$A$104,0)),"")
... B1004: =IF($A1004="","",YEAR($A1004)&"-"&RIGHT("0"&MONTH($A1004),2)) | K1004: =IF($H1004="","",$H1004-N($J1004)) | L1004: =IFERROR($K1004/$H1004,"") | M1004: =IFERROR(INDEX('10_CLIENTI'!$B$5:$B$204,MATCH($D1004,'10_CLIENTI'!$A$5:$A$204,0)),"") | N1004: =IFERROR(INDEX('11_PRODUSE'!$B$5:$B$104,MATCH($E1004,'11_PRODUSE'!$A$5:$A$104,0)),"")

Sheet 14_TINTE
A1: 14 — ȚINTE / BUGET
A2: Galben = se completează. Gri = calculat automat, nu suprascrie.
A4: Perioadă (data) Period_Date | B4: Nivel țintă Scope | C4: ID nivel Scope_ID | D4: Indicator Metric | E4: Valoare țintă Target_Value | F4: Observații Notes
A5: 46053 | B5: Companie | D5: Venit | E5: 120000 | F5: Exemplu — șterge înainte de utilizare

Sheet 15_NPS
A1: 15 — NPS / FEEDBACK CLIENȚI
A2: Galben = se completează. Gri = calculat automat, nu suprascrie.
A4: ID răspuns Response_ID | B4: Data răspunsului Survey_Date | C4: ID client Customer_ID | D4: Nume respondent Respondent_Name | E4: Rol respondent Respondent_Role | F4: Scor NPS (0-10) Score | G4: Categorie NPS_Category | H4: Motivul scorului Reason | I4: Temă Theme | J4: Canal colectare Channel | K4: Val / campanie Survey_Wave | L4: Responsabil follow-up Follow_Up_Owner | M4: Status follow-up Follow_Up_Status
A5: R0001 | B5: 46063 | C5: C001 | D5: Mihai I. | E5: Decident | F5: 9 | G5: =IF($F5="","",IF($F5>=9,"Promotor",IF($F5>=7,"Pasiv","Detractor"))) | H5: Relație bună, livrări la timp | I5: Relație | J5: Email | K5: 2026-T1 | L5: S001 | M5: Neînceput
A6: R0002 | B6: 46065 | C6: C002 | D6: Ioana R. | E6: Utilizator | F6: 5 | G6: =IF($F6="","",IF($F6>=9,"Promotor",IF($F6>=7,"Pasiv","Detractor"))) | H6: Întârzieri repetate la livrare | I6: Livrare | J6: Email | K6: 2026-T1 | L6: S002 | M6: În lucru
G7: =IF($F7="","",IF($F7>=9,"Promotor",IF($F7>=7,"Pasiv","Detractor")))
G8: =IF($F8="","",IF($F8>=9,"Promotor",IF($F8>=7,"Pasiv","Detractor")))
G9: =IF($F9="","",IF($F9>=9,"Promotor",IF($F9>=7,"Pasiv","Detractor")))
G10: =IF($F10="","",IF($F10>=9,"Promotor",IF($F10>=7,"Pasiv","Detractor")))
G11: =IF($F11="","",IF($F11>=9,"Promotor",IF($F11>=7,"Pasiv","Detractor")))
G12: =IF($F12="","",IF($F12>=9,"Promotor",IF($F12>=7,"Pasiv","Detractor")))
G13: =IF($F13="","",IF($F13>=9,"Promotor",IF($F13>=7,"Pasiv","Detractor")))
G14: =IF($F14="","",IF($F14>=9,"Promotor",IF($F14>=7,"Pasiv","Detractor")))
G15: =IF($F15="","",IF($F15>=9,"Promotor",IF($F15>=7,"Pasiv","Detractor")))
G16: =IF($F16="","",IF($F16>=9,"Promotor",IF($F16>=7,"Pasiv","Detractor")))
G17: =IF($F17="","",IF($F17>=9,"Promotor",IF($F17>=7,"Pasiv","Detractor")))
G18: =IF($F18="","",IF($F18>=9,"Promotor",IF($F18>=7,"Pasiv","Detractor")))
... G504: =IF($F504="","",IF($F504>=9,"Promotor",IF($F504>=7,"Pasiv","Detractor")))

Sheet 20_KPI
A1: 20 — KPI (perioada curentă vs. perioada de comparație)
A2: Toate valorile se recalculează din 09_PARAMETRI. Nu se scrie nimic în această foaie.
B3: ='09_PARAMETRI'!$B$5 | C3: ='09_PARAMETRI'!$B$7
A4: KPI | B4: Perioada curentă | C4: Perioada comparativă | D4: Δ | E4: Δ % | F4: Ce înseamnă
A5: VENIT ȘI PROFIT
A6: Venit net | B6: =SUMIFS('13_VANZARI'!$H$5:$H$1004,'13_VANZARI'!$A$5:$A$1004,">="&'09_PARAMETRI'!$B$5,'13_VANZARI'!$A$5:$A$1004,"<="&'09_PARAMETRI'!$B$6) | C6: =SUMIFS('13_VANZARI'!$H$5:$H$1004,'13_VANZARI'!$A$5:$A$1004,">="&'09_PARAMETRI'!$B$7,'13_VANZARI'!$A$5:$A$1004,"<="&'09_PARAMETRI'!$B$8) | D6: =IFERROR(IF(OR(B6="",C6=""),"",B6-C6),"") | E6: =IFERROR(IF(OR(C6=0,C6=""),"",(B6-C6)/ABS(C6)),"") | F6: Venitul total fără TVA din perioada selectată.
A7: Profit brut | B7: =SUMIFS('13_VANZARI'!$K$5:$K$1004,'13_VANZARI'!$A$5:$A$1004,">="&'09_PARAMETRI'!$B$5,'13_VANZARI'!$A$5:$A$1004,"<="&'09_PARAMETRI'!$B$6) | C7: =SUMIFS('13_VANZARI'!$K$5:$K$1004,'13_VANZARI'!$A$5:$A$1004,">="&'09_PARAMETRI'!$B$7,'13_VANZARI'!$A$5:$A$1004,"<="&'09_PARAMETRI'!$B$8) | D7: =IFERROR(IF(OR(B7="",C7=""),"",B7-C7),"") | E7: =IFERROR(IF(OR(C7=0,C7=""),"",(B7-C7)/ABS(C7)),"") | F7: Venit net minus costurile directe.
A8: Marjă brută % | B8: =IFERROR(SUMIFS('13_VANZARI'!$K$5:$K$1004,'13_VANZARI'!$A$5:$A$1004,">="&'09_PARAMETRI'!$B$5,'13_VANZARI'!$A$5:$A$1004,"<="&'09_PARAMETRI'!$B$6)/SUMIFS('13_VANZARI'!$H$5:$H$1004,'13_VANZARI'!$A$5:$A$1004,">="&'09_PARAMETRI'!$B$5,'13_VANZARI'!$A$5:$A$1004,"<="&'09_PARAMETRI'!$B$6),0) | C8: =IFERROR(SUMIFS('13_VANZARI'!$K$5:$K$1004,'13_VANZARI'!$A$5:$A$1004,">="&'09_PARAMETRI'!$B$7,'13_VANZARI'!$A$5:$A$1004,"<="&'09_PARAMETRI'!$B$8)/SUMIFS('13_VANZARI'!$H$5:$H$1004,'13_VANZARI'!$A$5:$A$1004,">="&'09_PARAMETRI'!$B$7,'13_VANZARI'!$A$5:$A$1004,"<="&'09_PARAMETRI'!$B$8),0) | D8: =IFERROR(IF(OR(B8="",C8=""),"",B8-C8),"") | E8: — | F8: Profit brut / venit net. Compară cu pragul din 09_PARAMETRI.
A9: Discount acordat | B9: =SUMIFS('13_VANZARI'!$I$5:$I$1004,'13_VANZARI'!$A$5:$A$1004,">="&'09_PARAMETRI'!$B$5,'13_VANZARI'!$A$5:$A$1004,"<="&'09_PARAMETRI'!$B$6) | C9: =SUMIFS('13_VANZARI'!$I$5:$I$1004,'13_VANZARI'!$A$5:$A$1004,">="&'09_PARAMETRI'!$B$7,'13_VANZARI'!$A$5:$A$1004,"<="&'09_PARAMETRI'!$B$8) | D9: =IFERROR(IF(OR(B9="",C9=""),"",B9-C9),"") | E9: =IFERROR(IF(OR(C9=0,C9=""),"",(B9-C9)/ABS(C9)),"") | F9: Cât s-a lăsat din preț. Creșterea lui erodează marja.
A10: Unități vândute | B10: =SUMIFS('13_VANZARI'!$G$5:$G$1004,'13_VANZARI'!$A$5:$A$1004,">="&'09_PARAMETRI'!$B$5,'13_VANZARI'!$A$5:$A$1004,"<="&'09_PARAMETRI'!$B$6) | C10: =SUMIFS('13_VANZARI'!$G$5:$G$1004,'13_VANZARI'!$A$5:$A$1004,">="&'09_PARAMETRI'!$B$7,'13_VANZARI'!$A$5:$A$1004,"<="&'09_PARAMETRI'!$B$8) | D10: =IFERROR(IF(OR(B10="",C10=""),"",B10-C10),"") | E10: =IFERROR(IF(OR(C10=0,C10=""),"",(B10-C10)/ABS(C10)),"") | F10: Separă creșterea de volum de creșterea de preț.
A11: Preț mediu / unitate | B11: =IFERROR(SUMIFS('13_VANZARI'!$H$5:$H$1004,'13_VANZARI'!$A$5:$A$1004,">="&'09_PARAMETRI'!$B$5,'13_VANZARI'!$A$5:$A$1004,"<="&'09_PARAMETRI'!$B$6)/SUMIFS('13_VANZARI'!$G$5:$G$1004,'13_VANZARI'!$A$5:$A$1004,">="&'09_PARAMETRI'!$B$5,'13_VANZARI'!$A$5:$A$1004,"<="&'09_PARAMETRI'!$B$6),0) | C11: =IFERROR(SUMIFS('13_VANZARI'!$H$5:$H$1004,'13_VANZARI'!$A$5:$A$1004,">="&'09_PARAMETRI'!$B$7,'13_VANZARI'!$A$5:$A$1004,"<="&'09_PARAMETRI'!$B$8)/SUMIFS('13_VANZARI'!$G$5:$G$1004,'13_VANZARI'!$A$5:$A$1004,">="&'09_PARAMETRI'!$B$7,'13_VANZARI'!$A$5:$A$1004,"<="&'09_PARAMETRI'!$B$8),0) | D11: =IFERROR(IF(OR(B11="",C11=""),"",B11-C11),"") | E11: =IFERROR(IF(OR(C11=0,C11=""),"",(B11-C11)/ABS(C11)),"") | F11: Venit net / unități. Arată dacă prețul crește sau se erodează.
A12: CLIENȚI
A13: Clienți activi | B13: =SUMPRODUCT(('10_CLIENTI'!$A$5:$A$204<>"")*(SUMIFS('13_VANZARI'!$H$5:$H$1004,'13_VANZARI'!$D$5:$D$1004,'10_CLIENTI'!$A$5:$A$204,'13_VANZARI'!$A$5:$A$1004,">="&'09_PARAMETRI'!$B$5,'13_VANZARI'!$A$5:$A$1004,"<="&'09_PARAMETRI'!$B$6)<>0)) | C13: =SUMPRODUCT(('10_CLIENTI'!$A$5:$A$204<>"")*(SUMIFS('13_VANZARI'!$H$5:$H$1004,'13_VANZARI'!$D$5:$D$1004,'10_CLIENTI'!$A$5:$A$204,'13_VANZARI'!$A$5:$A$1004,">="&'09_PARAMETRI'!$B$7,'13_VANZARI'!$A$5:$A$1004,"<="&'09_PARAMETRI'!$B$8)<>0)) | D13: =IFERROR(IF(OR(B13="",C13=""),"",B13-C13),"") | E13: =IFERROR(IF(OR(C13=0,C13=""),"",(B13-C13)/ABS(C13)),"") | F13: Clienți cu cel puțin o tranzacție în perioadă.
A14: Clienți noi | B14: =SUMPRODUCT(('10_CLIENTI'!$A$5:$A$204<>"")*(SUMIFS('13_VANZARI'!$H$5:$H$1004,'13_VANZARI'!$D$5:$D$1004,'10_CLIENTI'!$A$5:$A$204,'13_VANZARI'!$A$5:$A$1004,"<"&'09_PARAMETRI'!$B$5)=0)*(SUMIFS('13_VANZARI'!$H$5:$H$1004,'13_VANZARI'!$D$5:$D$1004,'10_CLIENTI'!$A$5:$A$204,'13_VANZARI'!$A$5:$A$1004,">="&'09_PARAMETRI'!$B$5,'13_VANZARI'!$A$5:$A$1004,"<="&'09_PARAMETRI'!$B$6)<>0)) | C14: =SUMPRODUCT(('10_CLIENTI'!$A$5:$A$204<>"")*(SUMIFS('13_VANZARI'!$H$5:$H$1004,'13_VANZARI'!$D$5:$D$1004,'10_CLIENTI'!$A$5:$A$204,'13_VANZARI'!$A$5:$A$1004,"<"&'09_PARAMETRI'!$B$7)=0)*(SUMIFS('13_VANZARI'!$H$5:$H$1004,'13_VANZARI'!$D$5:$D$1004,'10_CLIENTI'!$A$5:$A$204,'13_VANZARI'!$A$5:$A$1004,">="&'09_PARAMETRI'!$B$7,'13_VANZARI'!$A$5:$A$1004,"<="&'09_PARAMETRI'!$B$8)<>0)) | D14: =IFERROR(IF(OR(B14="",C14=""),"",B14-C14),"") | E14: =IFERROR(IF(OR(C14=0,C14=""),"",(B14-C14)/ABS(C14)),"") | F14: Clienți fără nicio achiziție înainte de perioada curentă.
A15: Venit mediu / client | B15: =IFERROR(SUMIFS('13_VANZARI'!$H$5:$H$1004,'13_VANZARI'!$A$5:$A$1004,">="&'09_PARAMETRI'!$B$5,'13_VANZARI'!$A$5:$A$1004,"<="&'09_PARAMETRI'!$B$6)/(SUMPRODUCT(('10_CLIENTI'!$A$5:$A$204<>"")*(SUMIFS('13_VANZARI'!$H$5:$H$1004,'13_VANZARI'!$D$5:$D$1004,'10_CLIENTI'!$A$5:$A$204,'13_VANZARI'!$A$5:$A$1004,">="&'09_PARAMETRI'!$B$5,'13_VANZARI'!$A$5:$A$1004,"<="&'09_PARAMETRI'!$B$6)<>0))),0) | C15: =IFERROR(SUMIFS('13_VANZARI'!$H$5:$H$1004,'13_VANZARI'!$A$5:$A$1004,">="&'09_PARAMETRI'!$B$7,'13_VANZARI'!$A$5:$A$1004,"<="&'09_PARAMETRI'!$B$8)/(SUMPRODUCT(('10_CLIENTI'!$A$5:$A$204<>"")*(SUMIFS('13_VANZARI'!$H$5:$H$1004,'13_VANZARI'!$D$5:$D$1004,'10_CLIENTI'!$A$5:$A$204,'13_VANZARI'!$A$5:$A$1004,">="&'09_PARAMETRI'!$B$7,'13_VANZARI'!$A$5:$A$1004,"<="&'09_PARAMETRI'!$B$8)<>0))),0) | D15: =IFERROR(IF(OR(B15="",C15=""),"",B15-C15),"") | E15: =IFERROR(IF(OR(C15=0,C15=""),"",(B15-C15)/ABS(C15)),"") | F15: Arată dacă creșterea vine din clienți noi sau din adâncirea relației.
A16: Număr de linii / facturi | B16: =SUMPRODUCT(('13_VANZARI'!$A$5:$A$1004>='09_PARAMETRI'!$B$5)*('13_VANZARI'!$A$5:$A$1004<='09_PARAMETRI'!$B$6)*('13_VANZARI'!$H$5:$H$1004<>"")) | C16: =SUMPRODUCT(('13_VANZARI'!$A$5:$A$1004>='09_PARAMETRI'!$B$7)*('13_VANZARI'!$A$5:$A$1004<='09_PARAMETRI'!$B$8)*('13_VANZARI'!$H$5:$H$1004<>"")) | D16: =IFERROR(IF(OR(B16="",C16=""),"",B16-C16),"") | E16: =IFERROR(IF(OR(C16=0,C16=""),"",(B16-C16)/ABS(C16)),"") | F16: Frecvența comenzilor.
A17: Valoare medie per linie | B17: =IFERROR(SUMIFS('13_VANZARI'!$H$5:$H$1004,'13_VANZARI'!$A$5:$A$1004,">="&'09_PARAMETRI'!$B$5,'13_VANZARI'!$A$5:$A$1004,"<="&'09_PARAMETRI'!$B$6)/(SUMPRODUCT(('13_VANZARI'!$A$5:$A$1004>='09_PARAMETRI'!$B$5)*('13_VANZARI'!$A$5:$A$1004<='09_PARAMETRI'!$B$6)*('13_VANZARI'!$H$5:$H$1004<>""))),0) | C17: =IFERROR(SUMIFS('13_VANZARI'!$H$5:$H$1004,'13_VANZARI'!$A$5:$A$1004,">="&'09_PARAMETRI'!$B$7,'13_VANZARI'!$A$5:$A$1004,"<="&'09_PARAMETRI'!$B$8)/(SUMPRODUCT(('13_VANZARI'!$A$5:$A$1004>='09_PARAMETRI'!$B$7)*('13_VANZARI'!$A$5:$A$1004<='09_PARAMETRI'!$B$8)*('13_VANZARI'!$H$5:$H$1004<>""))),0) | D17: =IFERROR(IF(OR(B17="",C17=""),"",B17-C17),"") | E17: =IFERROR(IF(OR(C17=0,C17=""),"",(B17-C17)/ABS(C17)),"") | F17: Venit net / număr de linii.
A18: Concentrare — cel mai mare client | B18: =IFERROR(SUMPRODUCT(MAX(('10_CLIENTI'!$A$5:$A$204<>"")*SUMIFS('13_VANZARI'!$H$5:$H$1004,'13_VANZARI'!$D$5:$D$1004,'10_CLIENTI'!$A$5:$A$204,'13_VANZARI'!$A$5:$A$1004,">="&'09_PARAMETRI'!$B$5,'13_VANZARI'!$A$5:$A$1004,"<="&'09_PARAMETRI'!$B$6)))/SUMIFS('13_VANZARI'!$H$5:$H$1004,'13_VANZARI'!$A$5:$A$1004,">="&'09_PARAMETRI'!$B$5,'13_VANZARI'!$A$5:$A$1004,"<="&'09_PARAMETRI'!$B$6),0) | C18: =IFERROR(SUMPRODUCT(MAX(('10_CLIENTI'!$A$5:$A$204<>"")*SUMIFS('13_VANZARI'!$H$5:$H$1004,'13_VANZARI'!$D$5:$D$1004,'10_CLIENTI'!$A$5:$A$204,'13_VANZARI'!$A$5:$A$1004,">="&'09_PARAMETRI'!$B$7,'13_VANZARI'!$A$5:$A$1004,"<="&'09_PARAMETRI'!$B$8)))/SUMIFS('13_VANZARI'!$H$5:$H$1004,'13_VANZARI'!$A$5:$A$1004,">="&'09_PARAMETRI'!$B$7,'13_VANZARI'!$A$5:$A$1004,"<="&'09_PARAMETRI'!$B$8),0) | D18: =IFERROR(IF(OR(B18="",C18=""),"",B18-C18),"") | E18: — | F18: Ce procent din venit vine de la un singur client. Peste pragul setat = risc.
A19: OAMENI
A20: FTE activ | B20: =SUMPRODUCT(('12_OAMENI'!$A$5:$A$64<>"")*('12_OAMENI'!$F$5:$F$64<='09_PARAMETRI'!$B$6)*(('12_OAMENI'!$G$5:$G$64="")+('12_OAMENI'!$G$5:$G$64>='09_PARAMETRI'!$B$5))*'12_OAMENI'!$E$5:$E$64) | C20: =SUMPRODUCT(('12_OAMENI'!$A$5:$A$64<>"")*('12_OAMENI'!$F$5:$F$64<='09_PARAMETRI'!$B$8)*(('12_OAMENI'!$G$5:$G$64="")+('12_OAMENI'!$G$5:$G$64>='09_PARAMETRI'!$B$7))*'12_OAMENI'!$E$5:$E$64) | D20: =IFERROR(IF(OR(B20="",C20=""),"",B20-C20),"") | E20: =IFERROR(IF(OR(C20=0,C20=""),"",(B20-C20)/ABS(C20)),"") | F20: Normă întreagă echivalentă, activă în perioadă.
A21: Venit / FTE | B21: =IFERROR(SUMIFS('13_VANZARI'!$H$5:$H$1004,'13_VANZARI'!$A$5:$A$1004,">="&'09_PARAMETRI'!$B$5,'13_VANZARI'!$A$5:$A$1004,"<="&'09_PARAMETRI'!$B$6)/(SUMPRODUCT(('12_OAMENI'!$A$5:$A$64<>"")*('12_OAMENI'!$F$5:$F$64<='09_PARAMETRI'!$B$6)*(('12_OAMENI'!$G$5:$G$64="")+('12_OAMENI'!$G$5:$G$64>='09_PARAMETRI'!$B$5))*'12_OAMENI'!$E$5:$E$64)),0) | C21: =IFERROR(SUMIFS('13_VANZARI'!$H$5:$H$1004,'13_VANZARI'!$A$5:$A$1004,">="&'09_PARAMETRI'!$B$7,'13_VANZARI'!$A$5:$A$1004,"<="&'09_PARAMETRI'!$B$8)/(SUMPRODUCT(('12_OAMENI'!$A$5:$A$64<>"")*('12_OAMENI'!$F$5:$F$64<='09_PARAMETRI'!$B$8)*(('12_OAMENI'!$G$5:$G$64="")+('12_OAMENI'!$G$5:$G$64>='09_PARAMETRI'!$B$7))*'12_OAMENI'!$E$5:$E$64)),0) | D21: =IFERROR(IF(OR(B21="",C21=""),"",B21-C21),"") | E21: =IFERROR(IF(OR(C21=0,C21=""),"",(B21-C21)/ABS(C21)),"") | F21: Indicatorul principal de productivitate.
A22: Profit brut / FTE | B22: =IFERROR(SUMIFS('13_VANZARI'!$K$5:$K$1004,'13_VANZARI'!$A$5:$A$1004,">="&'09_PARAMETRI'!$B$5,'13_VANZARI'!$A$5:$A$1004,"<="&'09_PARAMETRI'!$B$6)/(SUMPRODUCT(('12_OAMENI'!$A$5:$A$64<>"")*('12_OAMENI'!$F$5:$F$64<='09_PARAMETRI'!$B$6)*(('12_OAMENI'!$G$5:$G$64="")+('12_OAMENI'!$G$5:$G$64>='09_PARAMETRI'!$B$5))*'12_OAMENI'!$E$5:$E$64)),0) | C22: =IFERROR(SUMIFS('13_VANZARI'!$K$5:$K$1004,'13_VANZARI'!$A$5:$A$1004,">="&'09_PARAMETRI'!$B$7,'13_VANZARI'!$A$5:$A$1004,"<="&'09_PARAMETRI'!$B$8)/(SUMPRODUCT(('12_OAMENI'!$A$5:$A$64<>"")*('12_OAMENI'!$F$5:$F$64<='09_PARAMETRI'!$B$8)*(('12_OAMENI'!$G$5:$G$64="")+('12_OAMENI'!$G$5:$G$64>='09_PARAMETRI'!$B$7))*'12_OAMENI'!$E$5:$E$64)),0) | D22: =IFERROR(IF(OR(B22="",C22=""),"",B22-C22),"") | E22: =IFERROR(IF(OR(C22=0,C22=""),"",(B22-C22)/ABS(C22)),"") | F22: Productivitate ajustată cu marja.
A23: EXPERIENȚA CLIENTULUI
A24: NPS | B24: =IFERROR(((COUNTIFS('15_NPS'!$B$5:$B$504,">="&'09_PARAMETRI'!$B$5,'15_NPS'!$B$5:$B$504,"<="&'09_PARAMETRI'!$B$6,'15_NPS'!$F$5:$F$504,">=9"))-(COUNTIFS('15_NPS'!$B$5:$B$504,">="&'09_PARAMETRI'!$B$5,'15_NPS'!$B$5:$B$504,"<="&'09_PARAMETRI'!$B$6,'15_NPS'!$F$5:$F$504,"<=6")))/(SUMPRODUCT(('15_NPS'!$B$5:$B$504>='09_PARAMETRI'!$B$5)*('15_NPS'!$B$5:$B$504<='09_PARAMETRI'!$B$6)*('15_NPS'!$F$5:$F$504<>"")))*100,"") | C24: =IFERROR(((COUNTIFS('15_NPS'!$B$5:$B$504,">="&'09_PARAMETRI'!$B$7,'15_NPS'!$B$5:$B$504,"<="&'09_PARAMETRI'!$B$8,'15_NPS'!$F$5:$F$504,">=9"))-(COUNTIFS('15_NPS'!$B$5:$B$504,">="&'09_PARAMETRI'!$B$7,'15_NPS'!$B$5:$B$504,"<="&'09_PARAMETRI'!$B$8,'15_NPS'!$F$5:$F$504,"<=6")))/(SUMPRODUCT(('15_NPS'!$B$5:$B$504>='09_PARAMETRI'!$B$7)*('15_NPS'!$B$5:$B$504<='09_PARAMETRI'!$B$8)*('15_NPS'!$F$5:$F$504<>"")))*100,"") | D24: =IFERROR(IF(OR(B24="",C24=""),"",B24-C24),"") | E24: =IFERROR(IF(OR(C24=0,C24=""),"",(B24-C24)/ABS(C24)),"") | F24: (% promotori − % detractori) × 100. Scala: −100 la +100.
A25: Număr răspunsuri NPS | B25: =SUMPRODUCT(('15_NPS'!$B$5:$B$504>='09_PARAMETRI'!$B$5)*('15_NPS'!$B$5:$B$504<='09_PARAMETRI'!$B$6)*('15_NPS'!$F$5:$F$504<>"")) | C25: =SUMPRODUCT(('15_NPS'!$B$5:$B$504>='09_PARAMETRI'!$B$7)*('15_NPS'!$B$5:$B$504<='09_PARAMETRI'!$B$8)*('15_NPS'!$F$5:$F$504<>"")) | D25: =IFERROR(IF(OR(B25="",C25=""),"",B25-C25),"") | E25: =IFERROR(IF(OR(C25=0,C25=""),"",(B25-C25)/ABS(C25)),"") | F25: Sub 20 de răspunsuri, NPS-ul e orientativ, nu concluziv.
A26: % Promotori | B26: =IFERROR((COUNTIFS('15_NPS'!$B$5:$B$504,">="&'09_PARAMETRI'!$B$5,'15_NPS'!$B$5:$B$504,"<="&'09_PARAMETRI'!$B$6,'15_NPS'!$F$5:$F$504,">=9"))/(SUMPRODUCT(('15_NPS'!$B$5:$B$504>='09_PARAMETRI'!$B$5)*('15_NPS'!$B$5:$B$504<='09_PARAMETRI'!$B$6)*('15_NPS'!$F$5:$F$504<>""))),"") | C26: =IFERROR((COUNTIFS('15_NPS'!$B$5:$B$504,">="&'09_PARAMETRI'!$B$7,'15_NPS'!$B$5:$B$504,"<="&'09_PARAMETRI'!$B$8,'15_NPS'!$F$5:$F$504,">=9"))/(SUMPRODUCT(('15_NPS'!$B$5:$B$504>='09_PARAMETRI'!$B$7)*('15_NPS'!$B$5:$B$504<='09_PARAMETRI'!$B$8)*('15_NPS'!$F$5:$F$504<>""))),"") | D26: =IFERROR(IF(OR(B26="",C26=""),"",B26-C26),"") | E26: — | F26: Scor 9-10.
A27: % Detractori | B27: =IFERROR((COUNTIFS('15_NPS'!$B$5:$B$504,">="&'09_PARAMETRI'!$B$5,'15_NPS'!$B$5:$B$504,"<="&'09_PARAMETRI'!$B$6,'15_NPS'!$F$5:$F$504,"<=6"))/(SUMPRODUCT(('15_NPS'!$B$5:$B$504>='09_PARAMETRI'!$B$5)*('15_NPS'!$B$5:$B$504<='09_PARAMETRI'!$B$6)*('15_NPS'!$F$5:$F$504<>""))),"") | C27: =IFERROR((COUNTIFS('15_NPS'!$B$5:$B$504,">="&'09_PARAMETRI'!$B$7,'15_NPS'!$B$5:$B$504,"<="&'09_PARAMETRI'!$B$8,'15_NPS'!$F$5:$F$504,"<=6"))/(SUMPRODUCT(('15_NPS'!$B$5:$B$504>='09_PARAMETRI'!$B$7)*('15_NPS'!$B$5:$B$504<='09_PARAMETRI'!$B$8)*('15_NPS'!$F$5:$F$504<>""))),"") | D27: =IFERROR(IF(OR(B27="",C27=""),"",B27-C27),"") | E27: — | F27: Scor 0-6. Aceștia intră în planul de recuperare.
A28: PLAN
A29: Țintă de venit | B29: =SUMIFS('14_TINTE'!$E$5:$E$304,'14_TINTE'!$A$5:$A$304,">="&'09_PARAMETRI'!$B$5,'14_TINTE'!$A$5:$A$304,"<="&'09_PARAMETRI'!$B$6,'14_TINTE'!$D$5:$D$304,"Venit",'14_TINTE'!$B$5:$B$304,"Companie") | C29: =SUMIFS('14_TINTE'!$E$5:$E$304,'14_TINTE'!$A$5:$A$304,">="&'09_PARAMETRI'!$B$7,'14_TINTE'!$A$5:$A$304,"<="&'09_PARAMETRI'!$B$8,'14_TINTE'!$D$5:$D$304,"Venit",'14_TINTE'!$B$5:$B$304,"Companie") | D29: =IFERROR(IF(OR(B29="",C29=""),"",B29-C29),"") | E29: =IFERROR(IF(OR(C29=0,C29=""),"",(B29-C29)/ABS(C29)),"") | F29: Din 14_TINTE, nivel „Companie”, indicator „Venit”.
A30: Atingere țintă % | B30: =IFERROR(SUMIFS('13_VANZARI'!$H$5:$H$1004,'13_VANZARI'!$A$5:$A$1004,">="&'09_PARAMETRI'!$B$5,'13_VANZARI'!$A$5:$A$1004,"<="&'09_PARAMETRI'!$B$6)/(SUMIFS('14_TINTE'!$E$5:$E$304,'14_TINTE'!$A$5:$A$304,">="&'09_PARAMETRI'!$B$5,'14_TINTE'!$A$5:$A$304,"<="&'09_PARAMETRI'!$B$6,'14_TINTE'!$D$5:$D$304,"Venit",'14_TINTE'!$B$5:$B$304,"Companie")),"") | C30: =IFERROR(SUMIFS('13_VANZARI'!$H$5:$H$1004,'13_VANZARI'!$A$5:$A$1004,">="&'09_PARAMETRI'!$B$7,'13_VANZARI'!$A$5:$A$1004,"<="&'09_PARAMETRI'!$B$8)/(SUMIFS('14_TINTE'!$E$5:$E$304,'14_TINTE'!$A$5:$A$304,">="&'09_PARAMETRI'!$B$7,'14_TINTE'!$A$5:$A$304,"<="&'09_PARAMETRI'!$B$8,'14_TINTE'!$D$5:$D$304,"Venit",'14_TINTE'!$B$5:$B$304,"Companie")),"") | D30: =IFERROR(IF(OR(B30="",C30=""),"",B30-C30),"") | E30: — | F30: Venit realizat / țintă.
A31: Gap față de țintă | B31: =IF((SUMIFS('14_TINTE'!$E$5:$E$304,'14_TINTE'!$A$5:$A$304,">="&'09_PARAMETRI'!$B$5,'14_TINTE'!$A$5:$A$304,"<="&'09_PARAMETRI'!$B$6,'14_TINTE'!$D$5:$D$304,"Venit",'14_TINTE'!$B$5:$B$304,"Companie"))=0,"",(SUMIFS('14_TINTE'!$E$5:$E$304,'14_TINTE'!$A$5:$A$304,">="&'09_PARAMETRI'!$B$5,'14_TINTE'!$A$5:$A$304,"<="&'09_PARAMETRI'!$B$6,'14_TINTE'!$D$5:$D$304,"Venit",'14_TINTE'!$B$5:$B$304,"Companie"))-SUMIFS('13_VANZARI'!$H$5:$H$1004,'13_VANZARI'!$A$5:$A$1004,">="&'09_PARAMETRI'!$B$5,'13_VANZARI'!$A$5:$A$1004,"<="&'09_PARAMETRI'!$B$6)) | C31: =IF((SUMIFS('14_TINTE'!$E$5:$E$304,'14_TINTE'!$A$5:$A$304,">="&'09_PARAMETRI'!$B$7,'14_TINTE'!$A$5:$A$304,"<="&'09_PARAMETRI'!$B$8,'14_TINTE'!$D$5:$D$304,"Venit",'14_TINTE'!$B$5:$B$304,"Companie"))=0,"",(SUMIFS('14_TINTE'!$E$5:$E$304,'14_TINTE'!$A$5:$A$304,">="&'09_PARAMETRI'!$B$7,'14_TINTE'!$A$5:$A$304,"<="&'09_PARAMETRI'!$B$8,'14_TINTE'!$D$5:$D$304,"Venit",'14_TINTE'!$B$5:$B$304,"Companie"))-SUMIFS('13_VANZARI'!$H$5:$H$1004,'13_VANZARI'!$A$5:$A$1004,">="&'09_PARAMETRI'!$B$7,'13_VANZARI'!$A$5:$A$1004,"<="&'09_PARAMETRI'!$B$8)) | D31: =IFERROR(IF(OR(B31="",C31=""),"",B31-C31),"") | E31: =IFERROR(IF(OR(C31=0,C31=""),"",(B31-C31)/ABS(C31)),"") | F31: Cât mai lipsește. Acesta e punctul de plecare al oportunităților.

Sheet 21_ANALIZA_CLIENTI
A1: 21 — ANALIZA CLIENȚILOR
A2: Se completează singură din 10_CLIENTI + 13_VANZARI. Filtrează coloana „Semnal” ca să vezi unde e treabă de făcut.
A4: ID client | B4: Denumire client | C4: Segment | D4: Responsabil cont | E4: Venit — perioada curentă | F4: Venit — comparativ | G4: Δ venit % | H4: Profit brut | I4: Marjă % | J4: % din venit total | K4: Ultima achiziție | L4: Zile de la ultima achiziție | M4: Nr. produse cumpărate | N4: NPS mediu | O4: Semnal | P4: Oportunitate sugerată | Q4: Potențial estimat | R4: Cheie clasament
A5: =IF('10_CLIENTI'!$A5="","",'10_CLIENTI'!$A5) | B5: =IF($A5="","",IFERROR(INDEX('10_CLIENTI'!$B$5:$B$204,MATCH($A5,'10_CLIENTI'!$A$5:$A$204,0)),"")) | C5: =IF($A5="","",IFERROR(INDEX('10_CLIENTI'!$C$5:$C$204,MATCH($A5,'10_CLIENTI'!$A$5:$A$204,0)),"")) | D5: =IF($A5="","",IFERROR(INDEX('10_CLIENTI'!$G$5:$G$204,MATCH($A5,'10_CLIENTI'!$A$5:$A$204,0)),"")) | E5: =IF($A5="","",SUMIFS('13_VANZARI'!$H$5:$H$1004,'13_VANZARI'!$D$5:$D$1004,$A5,'13_VANZARI'!$A$5:$A$1004,">="&'09_PARAMETRI'!$B$5,'13_VANZARI'!$A$5:$A$1004,"<="&'09_PARAMETRI'!$B$6)) | F5: =IF($A5="","",SUMIFS('13_VANZARI'!$H$5:$H$1004,'13_VANZARI'!$D$5:$D$1004,$A5,'13_VANZARI'!$A$5:$A$1004,">="&'09_PARAMETRI'!$B$7,'13_VANZARI'!$A$5:$A$1004,"<="&'09_PARAMETRI'!$B$8)) | G5: =IF($A5="","",IFERROR(IF($F5=0,"",($E5-$F5)/ABS($F5)),"")) | H5: =IF($A5="","",SUMIFS('13_VANZARI'!$K$5:$K$1004,'13_VANZARI'!$D$5:$D$1004,$A5,'13_VANZARI'!$A$5:$A$1004,">="&'09_PARAMETRI'!$B$5,'13_VANZARI'!$A$5:$A$1004,"<="&'09_PARAMETRI'!$B$6)) | I5: =IF($A5="","",IFERROR($H5/$E5,"")) | J5: =IF($A5="","",IFERROR($E5/SUMIFS('13_VANZARI'!$H$5:$H$1004,'13_VANZARI'!$A$5:$A$1004,">="&'09_PARAMETRI'!$B$5,'13_VANZARI'!$A$5:$A$1004,"<="&'09_PARAMETRI'!$B$6),"")) | K5: =IF($A5="","",IFERROR(IF(SUMPRODUCT(MAX(('13_VANZARI'!$D$5:$D$1004=$A5)*('13_VANZARI'!$H$5:$H$1004<>"")*'13_VANZARI'!$A$5:$A$1004))=0,"",SUMPRODUCT(MAX(('13_VANZARI'!$D$5:$D$1004=$A5)*('13_VANZARI'!$H$5:$H$1004<>"")*'13_VANZARI'!$A$5:$A$1004))),"")) | L5: =IF(OR($A5="",$K5=""),"",'09_PARAMETRI'!$B$9-$K5) | M5: =IF($A5="","",SUMPRODUCT(('11_PRODUSE'!$A$5:$A$104<>"")*(SUMIFS('13_VANZARI'!$H$5:$H$1004,'13_VANZARI'!$D$5:$D$1004,$A5,'13_VANZARI'!$E$5:$E$1004,'11_PRODUSE'!$A$5:$A$104,'13_VANZARI'!$A$5:$A$1004,">="&'09_PARAMETRI'!$B$5,'13_VANZARI'!$A$5:$A$1004,"<="&'09_PARAMETRI'!$B$6)<>0))) | N5: =IF($A5="","",IFERROR(AVERAGEIFS('15_NPS'!$F$5:$F$504,'15_NPS'!$C$5:$C$504,$A5,'15_NPS'!$B$5:$B$504,">="&'09_PARAMETRI'!$B$5,'15_NPS'!$B$5:$B$504,"<="&'09_PARAMETRI'!$B$6),"")) | O5: =IF($A5="","",IF(AND($F5>0,$E5=0),"Client pierdut",IF(AND($L5<>"",$L5>'09_PARAMETRI'!$B$16,$F5>0),"Client dormant",IF(AND($G5<>"",$G5<='09_PARAMETRI'!$B$13),"Scădere de venit",IF(AND($N5<>"",$N5<7),"Detractor activ",IF(AND($E5>0,$J5>'09_PARAMETRI'!$B$19),"Risc concentrare",IF(AND($E5>0,$I5<>"",$I5<'09_PARAMETRI'!$B$15),"Marjă sub referință",IF(AND($G5<>"",$G5>='09_PARAMETRI'!$B$14),"În creștere",IF($E5=0,"Fără activitate","Stabil"))))))))) | P5: =IF($A5="","",IF($O5="Risc concentrare","Risc concentrare",IF($O5="Client pierdut","Recuperare client",IF($O5="Client dormant","Reactivare client",IF($O5="Scădere de venit","Recuperare client",IF($O5="Detractor activ","Recuperare NPS",IF($O5="Marjă sub referință","Marjă / preț",IF($O5="În creștere","Up-sell",IF($O5="Fără activitate","Reactivare client","Cross-sell"))))))))) | Q5: =IF($A5="","",IFERROR(IF($O5="Scădere de venit",MAX(0,$F5-$E5),IF(OR($O5="Client pierdut",$O5="Client dormant",$O5="Fără activitate"),$F5,IF($O5="Marjă sub referință",MAX(0,$E5*('09_PARAMETRI'!$B$15-$I5)),$E5*0.15))),"")) | R5: =IF(OR($A5="",$E5="",N($E5)<=0),"",$E5+ROW()/1000000)
A6: =IF('10_CLIENTI'!$A6="","",'10_CLIENTI'!$A6) | B6: =IF($A6="","",IFERROR(INDEX('10_CLIENTI'!$B$5:$B$204,MATCH($A6,'10_CLIENTI'!$A$5:$A$204,0)),"")) | C6: =IF($A6="","",IFERROR(INDEX('10_CLIENTI'!$C$5:$C$204,MATCH($A6,'10_CLIENTI'!$A$5:$A$204,0)),"")) | D6: =IF($A6="","",IFERROR(INDEX('10_CLIENTI'!$G$5:$G$204,MATCH($A6,'10_CLIENTI'!$A$5:$A$204,0)),"")) | E6: =IF($A6="","",SUMIFS('13_VANZARI'!$H$5:$H$1004,'13_VANZARI'!$D$5:$D$1004,$A6,'13_VANZARI'!$A$5:$A$1004,">="&'09_PARAMETRI'!$B$5,'13_VANZARI'!$A$5:$A$1004,"<="&'09_PARAMETRI'!$B$6)) | F6: =IF($A6="","",SUMIFS('13_VANZARI'!$H$5:$H$1004,'13_VANZARI'!$D$5:$D$1004,$A6,'13_VANZARI'!$A$5:$A$1004,">="&'09_PARAMETRI'!$B$7,'13_VANZARI'!$A$5:$A$1004,"<="&'09_PARAMETRI'!$B$8)) | G6: =IF($A6="","",IFERROR(IF($F6=0,"",($E6-$F6)/ABS($F6)),"")) | H6: =IF($A6="","",SUMIFS('13_VANZARI'!$K$5:$K$1004,'13_VANZARI'!$D$5:$D$1004,$A6,'13_VANZARI'!$A$5:$A$1004,">="&'09_PARAMETRI'!$B$5,'13_VANZARI'!$A$5:$A$1004,"<="&'09_PARAMETRI'!$B$6)) | I6: =IF($A6="","",IFERROR($H6/$E6,"")) | J6: =IF($A6="","",IFERROR($E6/SUMIFS('13_VANZARI'!$H$5:$H$1004,'13_VANZARI'!$A$5:$A$1004,">="&'09_PARAMETRI'!$B$5,'13_VANZARI'!$A$5:$A$1004,"<="&'09_PARAMETRI'!$B$6),"")) | K6: =IF($A6="","",IFERROR(IF(SUMPRODUCT(MAX(('13_VANZARI'!$D$5:$D$1004=$A6)*('13_VANZARI'!$H$5:$H$1004<>"")*'13_VANZARI'!$A$5:$A$1004))=0,"",SUMPRODUCT(MAX(('13_VANZARI'!$D$5:$D$1004=$A6)*('13_VANZARI'!$H$5:$H$1004<>"")*'13_VANZARI'!$A$5:$A$1004))),"")) | L6: =IF(OR($A6="",$K6=""),"",'09_PARAMETRI'!$B$9-$K6) | M6: =IF($A6="","",SUMPRODUCT(('11_PRODUSE'!$A$5:$A$104<>"")*(SUMIFS('13_VANZARI'!$H$5:$H$1004,'13_VANZARI'!$D$5:$D$1004,$A6,'13_VANZARI'!$E$5:$E$1004,'11_PRODUSE'!$A$5:$A$104,'13_VANZARI'!$A$5:$A$1004,">="&'09_PARAMETRI'!$B$5,'13_VANZARI'!$A$5:$A$1004,"<="&'09_PARAMETRI'!$B$6)<>0))) | N6: =IF($A6="","",IFERROR(AVERAGEIFS('15_NPS'!$F$5:$F$504,'15_NPS'!$C$5:$C$504,$A6,'15_NPS'!$B$5:$B$504,">="&'09_PARAMETRI'!$B$5,'15_NPS'!$B$5:$B$504,"<="&'09_PARAMETRI'!$B$6),"")) | O6: =IF($A6="","",IF(AND($F6>0,$E6=0),"Client pierdut",IF(AND($L6<>"",$L6>'09_PARAMETRI'!$B$16,$F6>0),"Client dormant",IF(AND($G6<>"",$G6<='09_PARAMETRI'!$B$13),"Scădere de venit",IF(AND($N6<>"",$N6<7),"Detractor activ",IF(AND($E6>0,$J6>'09_PARAMETRI'!$B$19),"Risc concentrare",IF(AND($E6>0,$I6<>"",$I6<'09_PARAMETRI'!$B$15),"Marjă sub referință",IF(AND($G6<>"",$G6>='09_PARAMETRI'!$B$14),"În creștere",IF($E6=0,"Fără activitate","Stabil"))))))))) | P6: =IF($A6="","",IF($O6="Risc concentrare","Risc concentrare",IF($O6="Client pierdut","Recuperare client",IF($O6="Client dormant","Reactivare client",IF($O6="Scădere de venit","Recuperare client",IF($O6="Detractor activ","Recuperare NPS",IF($O6="Marjă sub referință","Marjă / preț",IF($O6="În creștere","Up-sell",IF($O6="Fără activitate","Reactivare client","Cross-sell"))))))))) | Q6: =IF($A6="","",IFERROR(IF($O6="Scădere de venit",MAX(0,$F6-$E6),IF(OR($O6="Client pierdut",$O6="Client dormant",$O6="Fără activitate"),$F6,IF($O6="Marjă sub referință",MAX(0,$E6*('09_PARAMETRI'!$B$15-$I6)),$E6*0.15))),"")) | R6: =IF(OR($A6="",$E6="",N($E6)<=0),"",$E6+ROW()/1000000)
A7: =IF('10_CLIENTI'!$A7="","",'10_CLIENTI'!$A7) | B7: =IF($A7="","",IFERROR(INDEX('10_CLIENTI'!$B$5:$B$204,MATCH($A7,'10_CLIENTI'!$A$5:$A$204,0)),"")) | C7: =IF($A7="","",IFERROR(INDEX('10_CLIENTI'!$C$5:$C$204,MATCH($A7,'10_CLIENTI'!$A$5:$A$204,0)),"")) | D7: =IF($A7="","",IFERROR(INDEX('10_CLIENTI'!$G$5:$G$204,MATCH($A7,'10_CLIENTI'!$A$5:$A$204,0)),"")) | E7: =IF($A7="","",SUMIFS('13_VANZARI'!$H$5:$H$1004,'13_VANZARI'!$D$5:$D$1004,$A7,'13_VANZARI'!$A$5:$A$1004,">="&'09_PARAMETRI'!$B$5,'13_VANZARI'!$A$5:$A$1004,"<="&'09_PARAMETRI'!$B$6)) | F7: =IF($A7="","",SUMIFS('13_VANZARI'!$H$5:$H$1004,'13_VANZARI'!$D$5:$D$1004,$A7,'13_VANZARI'!$A$5:$A$1004,">="&'09_PARAMETRI'!$B$7,'13_VANZARI'!$A$5:$A$1004,"<="&'09_PARAMETRI'!$B$8)) | G7: =IF($A7="","",IFERROR(IF($F7=0,"",($E7-$F7)/ABS($F7)),"")) | H7: =IF($A7="","",SUMIFS('13_VANZARI'!$K$5:$K$1004,'13_VANZARI'!$D$5:$D$1004,$A7,'13_VANZARI'!$A$5:$A$1004,">="&'09_PARAMETRI'!$B$5,'13_VANZARI'!$A$5:$A$1004,"<="&'09_PARAMETRI'!$B$6)) | I7: =IF($A7="","",IFERROR($H7/$E7,"")) | J7: =IF($A7="","",IFERROR($E7/SUMIFS('13_VANZARI'!$H$5:$H$1004,'13_VANZARI'!$A$5:$A$1004,">="&'09_PARAMETRI'!$B$5,'13_VANZARI'!$A$5:$A$1004,"<="&'09_PARAMETRI'!$B$6),"")) | K7: =IF($A7="","",IFERROR(IF(SUMPRODUCT(MAX(('13_VANZARI'!$D$5:$D$1004=$A7)*('13_VANZARI'!$H$5:$H$1004<>"")*'13_VANZARI'!$A$5:$A$1004))=0,"",SUMPRODUCT(MAX(('13_VANZARI'!$D$5:$D$1004=$A7)*('13_VANZARI'!$H$5:$H$1004<>"")*'13_VANZARI'!$A$5:$A$1004))),"")) | L7: =IF(OR($A7="",$K7=""),"",'09_PARAMETRI'!$B$9-$K7) | M7: =IF($A7="","",SUMPRODUCT(('11_PRODUSE'!$A$5:$A$104<>"")*(SUMIFS('13_VANZARI'!$H$5:$H$1004,'13_VANZARI'!$D$5:$D$1004,$A7,'13_VANZARI'!$E$5:$E$1004,'11_PRODUSE'!$A$5:$A$104,'13_VANZARI'!$A$5:$A$1004,">="&'09_PARAMETRI'!$B$5,'13_VANZARI'!$A$5:$A$1004,"<="&'09_PARAMETRI'!$B$6)<>0))) | N7: =IF($A7="","",IFERROR(AVERAGEIFS('15_NPS'!$F$5:$F$504,'15_NPS'!$C$5:$C$504,$A7,'15_NPS'!$B$5:$B$504,">="&'09_PARAMETRI'!$B$5,'15_NPS'!$B$5:$B$504,"<="&'09_PARAMETRI'!$B$6),"")) | O7: =IF($A7="","",IF(AND($F7>0,$E7=0),"Client pierdut",IF(AND($L7<>"",$L7>'09_PARAMETRI'!$B$16,$F7>0),"Client dormant",IF(AND($G7<>"",$G7<='09_PARAMETRI'!$B$13),"Scădere de venit",IF(AND($N7<>"",$N7<7),"Detractor activ",IF(AND($E7>0,$J7>'09_PARAMETRI'!$B$19),"Risc concentrare",IF(AND($E7>0,$I7<>"",$I7<'09_PARAMETRI'!$B$15),"Marjă sub referință",IF(AND($G7<>"",$G7>='09_PARAMETRI'!$B$14),"În creștere",IF($E7=0,"Fără activitate","Stabil"))))))))) | P7: =IF($A7="","",IF($O7="Risc concentrare","Risc concentrare",IF($O7="Client pierdut","Recuperare client",IF($O7="Client dormant","Reactivare client",IF($O7="Scădere de venit","Recuperare client",IF($O7="Detractor activ","Recuperare NPS",IF($O7="Marjă sub referință","Marjă / preț",IF($O7="În creștere","Up-sell",IF($O7="Fără activitate","Reactivare client","Cross-sell"))))))))) | Q7: =IF($A7="","",IFERROR(IF($O7="Scădere de venit",MAX(0,$F7-$E7),IF(OR($O7="Client pierdut",$O7="Client dormant",$O7="Fără activitate"),$F7,IF($O7="Marjă sub referință",MAX(0,$E7*('09_PARAMETRI'!$B$15-$I7)),$E7*0.15))),"")) | R7: =IF(OR($A7="",$E7="",N($E7)<=0),"",$E7+ROW()/1000000)
A8: =IF('10_CLIENTI'!$A8="","",'10_CLIENTI'!$A8) | B8: =IF($A8="","",IFERROR(INDEX('10_CLIENTI'!$B$5:$B$204,MATCH($A8,'10_CLIENTI'!$A$5:$A$204,0)),"")) | C8: =IF($A8="","",IFERROR(INDEX('10_CLIENTI'!$C$5:$C$204,MATCH($A8,'10_CLIENTI'!$A$5:$A$204,0)),"")) | D8: =IF($A8="","",IFERROR(INDEX('10_CLIENTI'!$G$5:$G$204,MATCH($A8,'10_CLIENTI'!$A$5:$A$204,0)),"")) | E8: =IF($A8="","",SUMIFS('13_VANZARI'!$H$5:$H$1004,'13_VANZARI'!$D$5:$D$1004,$A8,'13_VANZARI'!$A$5:$A$1004,">="&'09_PARAMETRI'!$B$5,'13_VANZARI'!$A$5:$A$1004,"<="&'09_PARAMETRI'!$B$6)) | F8: =IF($A8="","",SUMIFS('13_VANZARI'!$H$5:$H$1004,'13_VANZARI'!$D$5:$D$1004,$A8,'13_VANZARI'!$A$5:$A$1004,">="&'09_PARAMETRI'!$B$7,'13_VANZARI'!$A$5:$A$1004,"<="&'09_PARAMETRI'!$B$8)) | G8: =IF($A8="","",IFERROR(IF($F8=0,"",($E8-$F8)/ABS($F8)),"")) | H8: =IF($A8="","",SUMIFS('13_VANZARI'!$K$5:$K$1004,'13_VANZARI'!$D$5:$D$1004,$A8,'13_VANZARI'!$A$5:$A$1004,">="&'09_PARAMETRI'!$B$5,'13_VANZARI'!$A$5:$A$1004,"<="&'09_PARAMETRI'!$B$6)) | I8: =IF($A8="","",IFERROR($H8/$E8,"")) | J8: =IF($A8="","",IFERROR($E8/SUMIFS('13_VANZARI'!$H$5:$H$1004,'13_VANZARI'!$A$5:$A$1004,">="&'09_PARAMETRI'!$B$5,'13_VANZARI'!$A$5:$A$1004,"<="&'09_PARAMETRI'!$B$6),"")) | K8: =IF($A8="","",IFERROR(IF(SUMPRODUCT(MAX(('13_VANZARI'!$D$5:$D$1004=$A8)*('13_VANZARI'!$H$5:$H$1004<>"")*'13_VANZARI'!$A$5:$A$1004))=0,"",SUMPRODUCT(MAX(('13_VANZARI'!$D$5:$D$1004=$A8)*('13_VANZARI'!$H$5:$H$1004<>"")*'13_VANZARI'!$A$5:$A$1004))),"")) | L8: =IF(OR($A8="",$K8=""),"",'09_PARAMETRI'!$B$9-$K8) | M8: =IF($A8="","",SUMPRODUCT(('11_PRODUSE'!$A$5:$A$104<>"")*(SUMIFS('13_VANZARI'!$H$5:$H$1004,'13_VANZARI'!$D$5:$D$1004,$A8,'13_VANZARI'!$E$5:$E$1004,'11_PRODUSE'!$A$5:$A$104,'13_VANZARI'!$A$5:$A$1004,">="&'09_PARAMETRI'!$B$5,'13_VANZARI'!$A$5:$A$1004,"<="&'09_PARAMETRI'!$B$6)<>0))) | N8: =IF($A8="","",IFERROR(AVERAGEIFS('15_NPS'!$F$5:$F$504,'15_NPS'!$C$5:$C$504,$A8,'15_NPS'!$B$5:$B$504,">="&'09_PARAMETRI'!$B$5,'15_NPS'!$B$5:$B$504,"<="&'09_PARAMETRI'!$B$6),"")) | O8: =IF($A8="","",IF(AND($F8>0,$E8=0),"Client pierdut",IF(AND($L8<>"",$L8>'09_PARAMETRI'!$B$16,$F8>0),"Client dormant",IF(AND($G8<>"",$G8<='09_PARAMETRI'!$B$13),"Scădere de venit",IF(AND($N8<>"",$N8<7),"Detractor activ",IF(AND($E8>0,$J8>'09_PARAMETRI'!$B$19),"Risc concentrare",IF(AND($E8>0,$I8<>"",$I8<'09_PARAMETRI'!$B$15),"Marjă sub referință",IF(AND($G8<>"",$G8>='09_PARAMETRI'!$B$14),"În creștere",IF($E8=0,"Fără activitate","Stabil"))))))))) | P8: =IF($A8="","",IF($O8="Risc concentrare","Risc concentrare",IF($O8="Client pierdut","Recuperare client",IF($O8="Client dormant","Reactivare client",IF($O8="Scădere de venit","Recuperare client",IF($O8="Detractor activ","Recuperare NPS",IF($O8="Marjă sub referință","Marjă / preț",IF($O8="În creștere","Up-sell",IF($O8="Fără activitate","Reactivare client","Cross-sell"))))))))) | Q8: =IF($A8="","",IFERROR(IF($O8="Scădere de venit",MAX(0,$F8-$E8),IF(OR($O8="Client pierdut",$O8="Client dormant",$O8="Fără activitate"),$F8,IF($O8="Marjă sub referință",MAX(0,$E8*('09_PARAMETRI'!$B$15-$I8)),$E8*0.15))),"")) | R8: =IF(OR($A8="",$E8="",N($E8)<=0),"",$E8+ROW()/1000000)
A9: =IF('10_CLIENTI'!$A9="","",'10_CLIENTI'!$A9) | B9: =IF($A9="","",IFERROR(INDEX('10_CLIENTI'!$B$5:$B$204,MATCH($A9,'10_CLIENTI'!$A$5:$A$204,0)),"")) | C9: =IF($A9="","",IFERROR(INDEX('10_CLIENTI'!$C$5:$C$204,MATCH($A9,'10_CLIENTI'!$A$5:$A$204,0)),"")) | D9: =IF($A9="","",IFERROR(INDEX('10_CLIENTI'!$G$5:$G$204,MATCH($A9,'10_CLIENTI'!$A$5:$A$204,0)),"")) | E9: =IF($A9="","",SUMIFS('13_VANZARI'!$H$5:$H$1004,'13_VANZARI'!$D$5:$D$1004,$A9,'13_VANZARI'!$A$5:$A$1004,">="&'09_PARAMETRI'!$B$5,'13_VANZARI'!$A$5:$A$1004,"<="&'09_PARAMETRI'!$B$6)) | F9: =IF($A9="","",SUMIFS('13_VANZARI'!$H$5:$H$1004,'13_VANZARI'!$D$5:$D$1004,$A9,'13_VANZARI'!$A$5:$A$1004,">="&'09_PARAMETRI'!$B$7,'13_VANZARI'!$A$5:$A$1004,"<="&'09_PARAMETRI'!$B$8)) | G9: =IF($A9="","",IFERROR(IF($F9=0,"",($E9-$F9)/ABS($F9)),"")) | H9: =IF($A9="","",SUMIFS('13_VANZARI'!$K$5:$K$1004,'13_VANZARI'!$D$5:$D$1004,$A9,'13_VANZARI'!$A$5:$A$1004,">="&'09_PARAMETRI'!$B$5,'13_VANZARI'!$A$5:$A$1004,"<="&'09_PARAMETRI'!$B$6)) | I9: =IF($A9="","",IFERROR($H9/$E9,"")) | J9: =IF($A9="","",IFERROR($E9/SUMIFS('13_VANZARI'!$H$5:$H$1004,'13_VANZARI'!$A$5:$A$1004,">="&'09_PARAMETRI'!$B$5,'13_VANZARI'!$A$5:$A$1004,"<="&'09_PARAMETRI'!$B$6),"")) | K9: =IF($A9="","",IFERROR(IF(SUMPRODUCT(MAX(('13_VANZARI'!$D$5:$D$1004=$A9)*('13_VANZARI'!$H$5:$H$1004<>"")*'13_VANZARI'!$A$5:$A$1004))=0,"",SUMPRODUCT(MAX(('13_VANZARI'!$D$5:$D$1004=$A9)*('13_VANZARI'!$H$5:$H$1004<>"")*'13_VANZARI'!$A$5:$A$1004))),"")) | L9: =IF(OR($A9="",$K9=""),"",'09_PARAMETRI'!$B$9-$K9) | M9: =IF($A9="","",SUMPRODUCT(('11_PRODUSE'!$A$5:$A$104<>"")*(SUMIFS('13_VANZARI'!$H$5:$H$1004,'13_VANZARI'!$D$5:$D$1004,$A9,'13_VANZARI'!$E$5:$E$1004,'11_PRODUSE'!$A$5:$A$104,'13_VANZARI'!$A$5:$A$1004,">="&'09_PARAMETRI'!$B$5,'13_VANZARI'!$A$5:$A$1004,"<="&'09_PARAMETRI'!$B$6)<>0))) | N9: =IF($A9="","",IFERROR(AVERAGEIFS('15_NPS'!$F$5:$F$504,'15_NPS'!$C$5:$C$504,$A9,'15_NPS'!$B$5:$B$504,">="&'09_PARAMETRI'!$B$5,'15_NPS'!$B$5:$B$504,"<="&'09_PARAMETRI'!$B$6),"")) | O9: =IF($A9="","",IF(AND($F9>0,$E9=0),"Client pierdut",IF(AND($L9<>"",$L9>'09_PARAMETRI'!$B$16,$F9>0),"Client dormant",IF(AND($G9<>"",$G9<='09_PARAMETRI'!$B$13),"Scădere de venit",IF(AND($N9<>"",$N9<7),"Detractor activ",IF(AND($E9>0,$J9>'09_PARAMETRI'!$B$19),"Risc concentrare",IF(AND($E9>0,$I9<>"",$I9<'09_PARAMETRI'!$B$15),"Marjă sub referință",IF(AND($G9<>"",$G9>='09_PARAMETRI'!$B$14),"În creștere",IF($E9=0,"Fără activitate","Stabil"))))))))) | P9: =IF($A9="","",IF($O9="Risc concentrare","Risc concentrare",IF($O9="Client pierdut","Recuperare client",IF($O9="Client dormant","Reactivare client",IF($O9="Scădere de venit","Recuperare client",IF($O9="Detractor activ","Recuperare NPS",IF($O9="Marjă sub referință","Marjă / preț",IF($O9="În creștere","Up-sell",IF($O9="Fără activitate","Reactivare client","Cross-sell"))))))))) | Q9: =IF($A9="","",IFERROR(IF($O9="Scădere de venit",MAX(0,$F9-$E9),IF(OR($O9="Client pierdut",$O9="Client dormant",$O9="Fără activitate"),$F9,IF($O9="Marjă sub referință",MAX(0,$E9*('09_PARAMETRI'!$B$15-$I9)),$E9*0.15))),"")) | R9: =IF(OR($A9="",$E9="",N($E9)<=0),"",$E9+ROW()/1000000)
A10: =IF('10_CLIENTI'!$A10="","",'10_CLIENTI'!$A10) | B10: =IF($A10="","",IFERROR(INDEX('10_CLIENTI'!$B$5:$B$204,MATCH($A10,'10_CLIENTI'!$A$5:$A$204,0)),"")) | C10: =IF($A10="","",IFERROR(INDEX('10_CLIENTI'!$C$5:$C$204,MATCH($A10,'10_CLIENTI'!$A$5:$A$204,0)),"")) | D10: =IF($A10="","",IFERROR(INDEX('10_CLIENTI'!$G$5:$G$204,MATCH($A10,'10_CLIENTI'!$A$5:$A$204,0)),"")) | E10: =IF($A10="","",SUMIFS('13_VANZARI'!$H$5:$H$1004,'13_VANZARI'!$D$5:$D$1004,$A10,'13_VANZARI'!$A$5:$A$1004,">="&'09_PARAMETRI'!$B$5,'13_VANZARI'!$A$5:$A$1004,"<="&'09_PARAMETRI'!$B$6)) | F10: =IF($A10="","",SUMIFS('13_VANZARI'!$H$5:$H$1004,'13_VANZARI'!$D$5:$D$1004,$A10,'13_VANZARI'!$A$5:$A$1004,">="&'09_PARAMETRI'!$B$7,'13_VANZARI'!$A$5:$A$1004,"<="&'09_PARAMETRI'!$B$8)) | G10: =IF($A10="","",IFERROR(IF($F10=0,"",($E10-$F10)/ABS($F10)),"")) | H10: =IF($A10="","",SUMIFS('13_VANZARI'!$K$5:$K$1004,'13_VANZARI'!$D$5:$D$1004,$A10,'13_VANZARI'!$A$5:$A$1004,">="&'09_PARAMETRI'!$B$5,'13_VANZARI'!$A$5:$A$1004,"<="&'09_PARAMETRI'!$B$6)) | I10: =IF($A10="","",IFERROR($H10/$E10,"")) | J10: =IF($A10="","",IFERROR($E10/SUMIFS('13_VANZARI'!$H$5:$H$1004,'13_VANZARI'!$A$5:$A$1004,">="&'09_PARAMETRI'!$B$5,'13_VANZARI'!$A$5:$A$1004,"<="&'09_PARAMETRI'!$B$6),"")) | K10: =IF($A10="","",IFERROR(IF(SUMPRODUCT(MAX(('13_VANZARI'!$D$5:$D$1004=$A10)*('13_VANZARI'!$H$5:$H$1004<>"")*'13_VANZARI'!$A$5:$A$1004))=0,"",SUMPRODUCT(MAX(('13_VANZARI'!$D$5:$D$1004=$A10)*('13_VANZARI'!$H$5:$H$1004<>"")*'13_VANZARI'!$A$5:$A$1004))),"")) | L10: =IF(OR($A10="",$K10=""),"",'09_PARAMETRI'!$B$9-$K10) | M10: =IF($A10="","",SUMPRODUCT(('11_PRODUSE'!$A$5:$A$104<>"")*(SUMIFS('13_VANZARI'!$H$5:$H$1004,'13_VANZARI'!$D$5:$D$1004,$A10,'13_VANZARI'!$E$5:$E$1004,'11_PRODUSE'!$A$5:$A$104,'13_VANZARI'!$A$5:$A$1004,">="&'09_PARAMETRI'!$B$5,'13_VANZARI'!$A$5:$A$1004,"<="&'09_PARAMETRI'!$B$6)<>0))) | N10: =IF($A10="","",IFERROR(AVERAGEIFS('15_NPS'!$F$5:$F$504,'15_NPS'!$C$5:$C$504,$A10,'15_NPS'!$B$5:$B$504,">="&'09_PARAMETRI'!$B$5,'15_NPS'!$B$5:$B$504,"<="&'09_PARAMETRI'!$B$6),"")) | O10: =IF($A10="","",IF(AND($F10>0,$E10=0),"Client pierdut",IF(AND($L10<>"",$L10>'09_PARAMETRI'!$B$16,$F10>0),"Client dormant",IF(AND($G10<>"",$G10<='09_PARAMETRI'!$B$13),"Scădere de venit",IF(AND($N10<>"",$N10<7),"Detractor activ",IF(AND($E10>0,$J10>'09_PARAMETRI'!$B$19),"Risc concentrare",IF(AND($E10>0,$I10<>"",$I10<'09_PARAMETRI'!$B$15),"Marjă sub referință",IF(AND($G10<>"",$G10>='09_PARAMETRI'!$B$14),"În creștere",IF($E10=0,"Fără activitate","Stabil"))))))))) | P10: =IF($A10="","",IF($O10="Risc concentrare","Risc concentrare",IF($O10="Client pierdut","Recuperare client",IF($O10="Client dormant","Reactivare client",IF($O10="Scădere de venit","Recuperare client",IF($O10="Detractor activ","Recuperare NPS",IF($O10="Marjă sub referință","Marjă / preț",IF($O10="În creștere","Up-sell",IF($O10="Fără activitate","Reactivare client","Cross-sell"))))))))) | Q10: =IF($A10="","",IFERROR(IF($O10="Scădere de venit",MAX(0,$F10-$E10),IF(OR($O10="Client pierdut",$O10="Client dormant",$O10="Fără activitate"),$F10,IF($O10="Marjă sub referință",MAX(0,$E10*('09_PARAMETRI'!$B$15-$I10)),$E10*0.15))),"")) | R10: =IF(OR($A10="",$E10="",N($E10)<=0),"",$E10+ROW()/1000000)
A11: =IF('10_CLIENTI'!$A11="","",'10_CLIENTI'!$A11) | B11: =IF($A11="","",IFERROR(INDEX('10_CLIENTI'!$B$5:$B$204,MATCH($A11,'10_CLIENTI'!$A$5:$A$204,0)),"")) | C11: =IF($A11="","",IFERROR(INDEX('10_CLIENTI'!$C$5:$C$204,MATCH($A11,'10_CLIENTI'!$A$5:$A$204,0)),"")) | D11: =IF($A11="","",IFERROR(INDEX('10_CLIENTI'!$G$5:$G$204,MATCH($A11,'10_CLIENTI'!$A$5:$A$204,0)),"")) | E11: =IF($A11="","",SUMIFS('13_VANZARI'!$H$5:$H$1004,'13_VANZARI'!$D$5:$D$1004,$A11,'13_VANZARI'!$A$5:$A$1004,">="&'09_PARAMETRI'!$B$5,'13_VANZARI'!$A$5:$A$1004,"<="&'09_PARAMETRI'!$B$6)) | F11: =IF($A11="","",SUMIFS('13_VANZARI'!$H$5:$H$1004,'13_VANZARI'!$D$5:$D$1004,$A11,'13_VANZARI'!$A$5:$A$1004,">="&'09_PARAMETRI'!$B$7,'13_VANZARI'!$A$5:$A$1004,"<="&'09_PARAMETRI'!$B$8)) | G11: =IF($A11="","",IFERROR(IF($F11=0,"",($E11-$F11)/ABS($F11)),"")) | H11: =IF($A11="","",SUMIFS('13_VANZARI'!$K$5:$K$1004,'13_VANZARI'!$D$5:$D$1004,$A11,'13_VANZARI'!$A$5:$A$1004,">="&'09_PARAMETRI'!$B$5,'13_VANZARI'!$A$5:$A$1004,"<="&'09_PARAMETRI'!$B$6)) | I11: =IF($A11="","",IFERROR($H11/$E11,"")) | J11: =IF($A11="","",IFERROR($E11/SUMIFS('13_VANZARI'!$H$5:$H$1004,'13_VANZARI'!$A$5:$A$1004,">="&'09_PARAMETRI'!$B$5,'13_VANZARI'!$A$5:$A$1004,"<="&'09_PARAMETRI'!$B$6),"")) | K11: =IF($A11="","",IFERROR(IF(SUMPRODUCT(MAX(('13_VANZARI'!$D$5:$D$1004=$A11)*('13_VANZARI'!$H$5:$H$1004<>"")*'13_VANZARI'!$A$5:$A$1004))=0,"",SUMPRODUCT(MAX(('13_VANZARI'!$D$5:$D$1004=$A11)*('13_VANZARI'!$H$5:$H$1004<>"")*'13_VANZARI'!$A$5:$A$1004))),"")) | L11: =IF(OR($A11="",$K11=""),"",'09_PARAMETRI'!$B$9-$K11) | M11: =IF($A11="","",SUMPRODUCT(('11_PRODUSE'!$A$5:$A$104<>"")*(SUMIFS('13_VANZARI'!$H$5:$H$1004,'13_VANZARI'!$D$5:$D$1004,$A11,'13_VANZARI'!$E$5:$E$1004,'11_PRODUSE'!$A$5:$A$104,'13_VANZARI'!$A$5:$A$1004,">="&'09_PARAMETRI'!$B$5,'13_VANZARI'!$A$5:$A$1004,"<="&'09_PARAMETRI'!$B$6)<>0))) | N11: =IF($A11="","",IFERROR(AVERAGEIFS('15_NPS'!$F$5:$F$504,'15_NPS'!$C$5:$C$504,$A11,'15_NPS'!$B$5:$B$504,">="&'09_PARAMETRI'!$B$5,'15_NPS'!$B$5:$B$504,"<="&'09_PARAMETRI'!$B$6),"")) | O11: =IF($A11="","",IF(AND($F11>0,$E11=0),"Client pierdut",IF(AND($L11<>"",$L11>'09_PARAMETRI'!$B$16,$F11>0),"Client dormant",IF(AND($G11<>"",$G11<='09_PARAMETRI'!$B$13),"Scădere de venit",IF(AND($N11<>"",$N11<7),"Detractor activ",IF(AND($E11>0,$J11>'09_PARAMETRI'!$B$19),"Risc concentrare",IF(AND($E11>0,$I11<>"",$I11<'09_PARAMETRI'!$B$15),"Marjă sub referință",IF(AND($G11<>"",$G11>='09_PARAMETRI'!$B$14),"În creștere",IF($E11=0,"Fără activitate","Stabil"))))))))) | P11: =IF($A11="","",IF($O11="Risc concentrare","Risc concentrare",IF($O11="Client pierdut","Recuperare client",IF($O11="Client dormant","Reactivare client",IF($O11="Scădere de venit","Recuperare client",IF($O11="Detractor activ","Recuperare NPS",IF($O11="Marjă sub referință","Marjă / preț",IF($O11="În creștere","Up-sell",IF($O11="Fără activitate","Reactivare client","Cross-sell"))))))))) | Q11: =IF($A11="","",IFERROR(IF($O11="Scădere de venit",MAX(0,$F11-$E11),IF(OR($O11="Client pierdut",$O11="Client dormant",$O11="Fără activitate"),$F11,IF($O11="Marjă sub referință",MAX(0,$E11*('09_PARAMETRI'!$B$15-$I11)),$E11*0.15))),"")) | R11: =IF(OR($A11="",$E11="",N($E11)<=0),"",$E11+ROW()/1000000)
A12: =IF('10_CLIENTI'!$A12="","",'10_CLIENTI'!$A12) | B12: =IF($A12="","",IFERROR(INDEX('10_CLIENTI'!$B$5:$B$204,MATCH($A12,'10_CLIENTI'!$A$5:$A$204,0)),"")) | C12: =IF($A12="","",IFERROR(INDEX('10_CLIENTI'!$C$5:$C$204,MATCH($A12,'10_CLIENTI'!$A$5:$A$204,0)),"")) | D12: =IF($A12="","",IFERROR(INDEX('10_CLIENTI'!$G$5:$G$204,MATCH($A12,'10_CLIENTI'!$A$5:$A$204,0)),"")) | E12: =IF($A12="","",SUMIFS('13_VANZARI'!$H$5:$H$1004,'13_VANZARI'!$D$5:$D$1004,$A12,'13_VANZARI'!$A$5:$A$1004,">="&'09_PARAMETRI'!$B$5,'13_VANZARI'!$A$5:$A$1004,"<="&'09_PARAMETRI'!$B$6)) | F12: =IF($A12="","",SUMIFS('13_VANZARI'!$H$5:$H$1004,'13_VANZARI'!$D$5:$D$1004,$A12,'13_VANZARI'!$A$5:$A$1004,">="&'09_PARAMETRI'!$B$7,'13_VANZARI'!$A$5:$A$1004,"<="&'09_PARAMETRI'!$B$8)) | G12: =IF($A12="","",IFERROR(IF($F12=0,"",($E12-$F12)/ABS($F12)),"")) | H12: =IF($A12="","",SUMIFS('13_VANZARI'!$K$5:$K$1004,'13_VANZARI'!$D$5:$D$1004,$A12,'13_VANZARI'!$A$5:$A$1004,">="&'09_PARAMETRI'!$B$5,'13_VANZARI'!$A$5:$A$1004,"<="&'09_PARAMETRI'!$B$6)) | I12: =IF($A12="","",IFERROR($H12/$E12,"")) | J12: =IF($A12="","",IFERROR($E12/SUMIFS('13_VANZARI'!$H$5:$H$1004,'13_VANZARI'!$A$5:$A$1004,">="&'09_PARAMETRI'!$B$5,'13_VANZARI'!$A$5:$A$1004,"<="&'09_PARAMETRI'!$B$6),"")) | K12: =IF($A12="","",IFERROR(IF(SUMPRODUCT(MAX(('13_VANZARI'!$D$5:$D$1004=$A12)*('13_VANZARI'!$H$5:$H$1004<>"")*'13_VANZARI'!$A$5:$A$1004))=0,"",SUMPRODUCT(MAX(('13_VANZARI'!$D$5:$D$1004=$A12)*('13_VANZARI'!$H$5:$H$1004<>"")*'13_VANZARI'!$A$5:$A$1004))),"")) | L12: =IF(OR($A12="",$K12=""),"",'09_PARAMETRI'!$B$9-$K12) | M12: =IF($A12="","",SUMPRODUCT(('11_PRODUSE'!$A$5:$A$104<>"")*(SUMIFS('13_VANZARI'!$H$5:$H$1004,'13_VANZARI'!$D$5:$D$1004,$A12,'13_VANZARI'!$E$5:$E$1004,'11_PRODUSE'!$A$5:$A$104,'13_VANZARI'!$A$5:$A$1004,">="&'09_PARAMETRI'!$B$5,'13_VANZARI'!$A$5:$A$1004,"<="&'09_PARAMETRI'!$B$6)<>0))) | N12: =IF($A12="","",IFERROR(AVERAGEIFS('15_NPS'!$F$5:$F$504,'15_NPS'!$C$5:$C$504,$A12,'15_NPS'!$B$5:$B$504,">="&'09_PARAMETRI'!$B$5,'15_NPS'!$B$5:$B$504,"<="&'09_PARAMETRI'!$B$6),"")) | O12: =IF($A12="","",IF(AND($F12>0,$E12=0),"Client pierdut",IF(AND($L12<>"",$L12>'09_PARAMETRI'!$B$16,$F12>0),"Client dormant",IF(AND($G12<>"",$G12<='09_PARAMETRI'!$B$13),"Scădere de venit",IF(AND($N12<>"",$N12<7),"Detractor activ",IF(AND($E12>0,$J12>'09_PARAMETRI'!$B$19),"Risc concentrare",IF(AND($E12>0,$I12<>"",$I12<'09_PARAMETRI'!$B$15),"Marjă sub referință",IF(AND($G12<>"",$G12>='09_PARAMETRI'!$B$14),"În creștere",IF($E12=0,"Fără activitate","Stabil"))))))))) | P12: =IF($A12="","",IF($O12="Risc concentrare","Risc concentrare",IF($O12="Client pierdut","Recuperare client",IF($O12="Client dormant","Reactivare client",IF($O12="Scădere de venit","Recuperare client",IF($O12="Detractor activ","Recuperare NPS",IF($O12="Marjă sub referință","Marjă / preț",IF($O12="În creștere","Up-sell",IF($O12="Fără activitate","Reactivare client","Cross-sell"))))))))) | Q12: =IF($A12="","",IFERROR(IF($O12="Scădere de venit",MAX(0,$F12-$E12),IF(OR($O12="Client pierdut",$O12="Client dormant",$O12="Fără activitate"),$F12,IF($O12="Marjă sub referință",MAX(0,$E12*('09_PARAMETRI'!$B$15-$I12)),$E12*0.15))),"")) | R12: =IF(OR($A12="",$E12="",N($E12)<=0),"",$E12+ROW()/1000000)
A13: =IF('10_CLIENTI'!$A13="","",'10_CLIENTI'!$A13) | B13: =IF($A13="","",IFERROR(INDEX('10_CLIENTI'!$B$5:$B$204,MATCH($A13,'10_CLIENTI'!$A$5:$A$204,0)),"")) | C13: =IF($A13="","",IFERROR(INDEX('10_CLIENTI'!$C$5:$C$204,MATCH($A13,'10_CLIENTI'!$A$5:$A$204,0)),"")) | D13: =IF($A13="","",IFERROR(INDEX('10_CLIENTI'!$G$5:$G$204,MATCH($A13,'10_CLIENTI'!$A$5:$A$204,0)),"")) | E13: =IF($A13="","",SUMIFS('13_VANZARI'!$H$5:$H$1004,'13_VANZARI'!$D$5:$D$1004,$A13,'13_VANZARI'!$A$5:$A$1004,">="&'09_PARAMETRI'!$B$5,'13_VANZARI'!$A$5:$A$1004,"<="&'09_PARAMETRI'!$B$6)) | F13: =IF($A13="","",SUMIFS('13_VANZARI'!$H$5:$H$1004,'13_VANZARI'!$D$5:$D$1004,$A13,'13_VANZARI'!$A$5:$A$1004,">="&'09_PARAMETRI'!$B$7,'13_VANZARI'!$A$5:$A$1004,"<="&'09_PARAMETRI'!$B$8)) | G13: =IF($A13="","",IFERROR(IF($F13=0,"",($E13-$F13)/ABS($F13)),"")) | H13: =IF($A13="","",SUMIFS('13_VANZARI'!$K$5:$K$1004,'13_VANZARI'!$D$5:$D$1004,$A13,'13_VANZARI'!$A$5:$A$1004,">="&'09_PARAMETRI'!$B$5,'13_VANZARI'!$A$5:$A$1004,"<="&'09_PARAMETRI'!$B$6)) | I13: =IF($A13="","",IFERROR($H13/$E13,"")) | J13: =IF($A13="","",IFERROR($E13/SUMIFS('13_VANZARI'!$H$5:$H$1004,'13_VANZARI'!$A$5:$A$1004,">="&'09_PARAMETRI'!$B$5,'13_VANZARI'!$A$5:$A$1004,"<="&'09_PARAMETRI'!$B$6),"")) | K13: =IF($A13="","",IFERROR(IF(SUMPRODUCT(MAX(('13_VANZARI'!$D$5:$D$1004=$A13)*('13_VANZARI'!$H$5:$H$1004<>"")*'13_VANZARI'!$A$5:$A$1004))=0,"",SUMPRODUCT(MAX(('13_VANZARI'!$D$5:$D$1004=$A13)*('13_VANZARI'!$H$5:$H$1004<>"")*'13_VANZARI'!$A$5:$A$1004))),"")) | L13: =IF(OR($A13="",$K13=""),"",'09_PARAMETRI'!$B$9-$K13) | M13: =IF($A13="","",SUMPRODUCT(('11_PRODUSE'!$A$5:$A$104<>"")*(SUMIFS('13_VANZARI'!$H$5:$H$1004,'13_VANZARI'!$D$5:$D$1004,$A13,'13_VANZARI'!$E$5:$E$1004,'11_PRODUSE'!$A$5:$A$104,'13_VANZARI'!$A$5:$A$1004,">="&'09_PARAMETRI'!$B$5,'13_VANZARI'!$A$5:$A$1004,"<="&'09_PARAMETRI'!$B$6)<>0))) | N13: =IF($A13="","",IFERROR(AVERAGEIFS('15_NPS'!$F$5:$F$504,'15_NPS'!$C$5:$C$504,$A13,'15_NPS'!$B$5:$B$504,">="&'09_PARAMETRI'!$B$5,'15_NPS'!$B$5:$B$504,"<="&'09_PARAMETRI'!$B$6),"")) | O13: =IF($A13="","",IF(AND($F13>0,$E13=0),"Client pierdut",IF(AND($L13<>"",$L13>'09_PARAMETRI'!$B$16,$F13>0),"Client dormant",IF(AND($G13<>"",$G13<='09_PARAMETRI'!$B$13),"Scădere de venit",IF(AND($N13<>"",$N13<7),"Detractor activ",IF(AND($E13>0,$J13>'09_PARAMETRI'!$B$19),"Risc concentrare",IF(AND($E13>0,$I13<>"",$I13<'09_PARAMETRI'!$B$15),"Marjă sub referință",IF(AND($G13<>"",$G13>='09_PARAMETRI'!$B$14),"În creștere",IF($E13=0,"Fără activitate","Stabil"))))))))) | P13: =IF($A13="","",IF($O13="Risc concentrare","Risc concentrare",IF($O13="Client pierdut","Recuperare client",IF($O13="Client dormant","Reactivare client",IF($O13="Scădere de venit","Recuperare client",IF($O13="Detractor activ","Recuperare NPS",IF($O13="Marjă sub referință","Marjă / preț",IF($O13="În creștere","Up-sell",IF($O13="Fără activitate","Reactivare client","Cross-sell"))))))))) | Q13: =IF($A13="","",IFERROR(IF($O13="Scădere de venit",MAX(0,$F13-$E13),IF(OR($O13="Client pierdut",$O13="Client dormant",$O13="Fără activitate"),$F13,IF($O13="Marjă sub referință",MAX(0,$E13*('09_PARAMETRI'!$B$15-$I13)),$E13*0.15))),"")) | R13: =IF(OR($A13="",$E13="",N($E13)<=0),"",$E13+ROW()/1000000)
A14: =IF('10_CLIENTI'!$A14="","",'10_CLIENTI'!$A14) | B14: =IF($A14="","",IFERROR(INDEX('10_CLIENTI'!$B$5:$B$204,MATCH($A14,'10_CLIENTI'!$A$5:$A$204,0)),"")) | C14: =IF($A14="","",IFERROR(INDEX('10_CLIENTI'!$C$5:$C$204,MATCH($A14,'10_CLIENTI'!$A$5:$A$204,0)),"")) | D14: =IF($A14="","",IFERROR(INDEX('10_CLIENTI'!$G$5:$G$204,MATCH($A14,'10_CLIENTI'!$A$5:$A$204,0)),"")) | E14: =IF($A14="","",SUMIFS('13_VANZARI'!$H$5:$H$1004,'13_VANZARI'!$D$5:$D$1004,$A14,'13_VANZARI'!$A$5:$A$1004,">="&'09_PARAMETRI'!$B$5,'13_VANZARI'!$A$5:$A$1004,"<="&'09_PARAMETRI'!$B$6)) | F14: =IF($A14="","",SUMIFS('13_VANZARI'!$H$5:$H$1004,'13_VANZARI'!$D$5:$D$1004,$A14,'13_VANZARI'!$A$5:$A$1004,">="&'09_PARAMETRI'!$B$7,'13_VANZARI'!$A$5:$A$1004,"<="&'09_PARAMETRI'!$B$8)) | G14: =IF($A14="","",IFERROR(IF($F14=0,"",($E14-$F14)/ABS($F14)),"")) | H14: =IF($A14="","",SUMIFS('13_VANZARI'!$K$5:$K$1004,'13_VANZARI'!$D$5:$D$1004,$A14,'13_VANZARI'!$A$5:$A$1004,">="&'09_PARAMETRI'!$B$5,'13_VANZARI'!$A$5:$A$1004,"<="&'09_PARAMETRI'!$B$6)) | I14: =IF($A14="","",IFERROR($H14/$E14,"")) | J14: =IF($A14="","",IFERROR($E14/SUMIFS('13_VANZARI'!$H$5:$H$1004,'13_VANZARI'!$A$5:$A$1004,">="&'09_PARAMETRI'!$B$5,'13_VANZARI'!$A$5:$A$1004,"<="&'09_PARAMETRI'!$B$6),"")) | K14: =IF($A14="","",IFERROR(IF(SUMPRODUCT(MAX(('13_VANZARI'!$D$5:$D$1004=$A14)*('13_VANZARI'!$H$5:$H$1004<>"")*'13_VANZARI'!$A$5:$A$1004))=0,"",SUMPRODUCT(MAX(('13_VANZARI'!$D$5:$D$1004=$A14)*('13_VANZARI'!$H$5:$H$1004<>"")*'13_VANZARI'!$A$5:$A$1004))),"")) | L14: =IF(OR($A14="",$K14=""),"",'09_PARAMETRI'!$B$9-$K14) | M14: =IF($A14="","",SUMPRODUCT(('11_PRODUSE'!$A$5:$A$104<>"")*(SUMIFS('13_VANZARI'!$H$5:$H$1004,'13_VANZARI'!$D$5:$D$1004,$A14,'13_VANZARI'!$E$5:$E$1004,'11_PRODUSE'!$A$5:$A$104,'13_VANZARI'!$A$5:$A$1004,">="&'09_PARAMETRI'!$B$5,'13_VANZARI'!$A$5:$A$1004,"<="&'09_PARAMETRI'!$B$6)<>0))) | N14: =IF($A14="","",IFERROR(AVERAGEIFS('15_NPS'!$F$5:$F$504,'15_NPS'!$C$5:$C$504,$A14,'15_NPS'!$B$5:$B$504,">="&'09_PARAMETRI'!$B$5,'15_NPS'!$B$5:$B$504,"<="&'09_PARAMETRI'!$B$6),"")) | O14: =IF($A14="","",IF(AND($F14>0,$E14=0),"Client pierdut",IF(AND($L14<>"",$L14>'09_PARAMETRI'!$B$16,$F14>0),"Client dormant",IF(AND($G14<>"",$G14<='09_PARAMETRI'!$B$13),"Scădere de venit",IF(AND($N14<>"",$N14<7),"Detractor activ",IF(AND($E14>0,$J14>'09_PARAMETRI'!$B$19),"Risc concentrare",IF(AND($E14>0,$I14<>"",$I14<'09_PARAMETRI'!$B$15),"Marjă sub referință",IF(AND($G14<>"",$G14>='09_PARAMETRI'!$B$14),"În creștere",IF($E14=0,"Fără activitate","Stabil"))))))))) | P14: =IF($A14="","",IF($O14="Risc concentrare","Risc concentrare",IF($O14="Client pierdut","Recuperare client",IF($O14="Client dormant","Reactivare client",IF($O14="Scădere de venit","Recuperare client",IF($O14="Detractor activ","Recuperare NPS",IF($O14="Marjă sub referință","Marjă / preț",IF($O14="În creștere","Up-sell",IF($O14="Fără activitate","Reactivare client","Cross-sell"))))))))) | Q14: =IF($A14="","",IFERROR(IF($O14="Scădere de venit",MAX(0,$F14-$E14),IF(OR($O14="Client pierdut",$O14="Client dormant",$O14="Fără activitate"),$F14,IF($O14="Marjă sub referință",MAX(0,$E14*('09_PARAMETRI'!$B$15-$I14)),$E14*0.15))),"")) | R14: =IF(OR($A14="",$E14="",N($E14)<=0),"",$E14+ROW()/1000000)
A15: =IF('10_CLIENTI'!$A15="","",'10_CLIENTI'!$A15) | B15: =IF($A15="","",IFERROR(INDEX('10_CLIENTI'!$B$5:$B$204,MATCH($A15,'10_CLIENTI'!$A$5:$A$204,0)),"")) | C15: =IF($A15="","",IFERROR(INDEX('10_CLIENTI'!$C$5:$C$204,MATCH($A15,'10_CLIENTI'!$A$5:$A$204,0)),"")) | D15: =IF($A15="","",IFERROR(INDEX('10_CLIENTI'!$G$5:$G$204,MATCH($A15,'10_CLIENTI'!$A$5:$A$204,0)),"")) | E15: =IF($A15="","",SUMIFS('13_VANZARI'!$H$5:$H$1004,'13_VANZARI'!$D$5:$D$1004,$A15,'13_VANZARI'!$A$5:$A$1004,">="&'09_PARAMETRI'!$B$5,'13_VANZARI'!$A$5:$A$1004,"<="&'09_PARAMETRI'!$B$6)) | F15: =IF($A15="","",SUMIFS('13_VANZARI'!$H$5:$H$1004,'13_VANZARI'!$D$5:$D$1004,$A15,'13_VANZARI'!$A$5:$A$1004,">="&'09_PARAMETRI'!$B$7,'13_VANZARI'!$A$5:$A$1004,"<="&'09_PARAMETRI'!$B$8)) | G15: =IF($A15="","",IFERROR(IF($F15=0,"",($E15-$F15)/ABS($F15)),"")) | H15: =IF($A15="","",SUMIFS('13_VANZARI'!$K$5:$K$1004,'13_VANZARI'!$D$5:$D$1004,$A15,'13_VANZARI'!$A$5:$A$1004,">="&'09_PARAMETRI'!$B$5,'13_VANZARI'!$A$5:$A$1004,"<="&'09_PARAMETRI'!$B$6)) | I15: =IF($A15="","",IFERROR($H15/$E15,"")) | J15: =IF($A15="","",IFERROR($E15/SUMIFS('13_VANZARI'!$H$5:$H$1004,'13_VANZARI'!$A$5:$A$1004,">="&'09_PARAMETRI'!$B$5,'13_VANZARI'!$A$5:$A$1004,"<="&'09_PARAMETRI'!$B$6),"")) | K15: =IF($A15="","",IFERROR(IF(SUMPRODUCT(MAX(('13_VANZARI'!$D$5:$D$1004=$A15)*('13_VANZARI'!$H$5:$H$1004<>"")*'13_VANZARI'!$A$5:$A$1004))=0,"",SUMPRODUCT(MAX(('13_VANZARI'!$D$5:$D$1004=$A15)*('13_VANZARI'!$H$5:$H$1004<>"")*'13_VANZARI'!$A$5:$A$1004))),"")) | L15: =IF(OR($A15="",$K15=""),"",'09_PARAMETRI'!$B$9-$K15) | M15: =IF($A15="","",SUMPRODUCT(('11_PRODUSE'!$A$5:$A$104<>"")*(SUMIFS('13_VANZARI'!$H$5:$H$1004,'13_VANZARI'!$D$5:$D$1004,$A15,'13_VANZARI'!$E$5:$E$1004,'11_PRODUSE'!$A$5:$A$104,'13_VANZARI'!$A$5:$A$1004,">="&'09_PARAMETRI'!$B$5,'13_VANZARI'!$A$5:$A$1004,"<="&'09_PARAMETRI'!$B$6)<>0))) | N15: =IF($A15="","",IFERROR(AVERAGEIFS('15_NPS'!$F$5:$F$504,'15_NPS'!$C$5:$C$504,$A15,'15_NPS'!$B$5:$B$504,">="&'09_PARAMETRI'!$B$5,'15_NPS'!$B$5:$B$504,"<="&'09_PARAMETRI'!$B$6),"")) | O15: =IF($A15="","",IF(AND($F15>0,$E15=0),"Client pierdut",IF(AND($L15<>"",$L15>'09_PARAMETRI'!$B$16,$F15>0),"Client dormant",IF(AND($G15<>"",$G15<='09_PARAMETRI'!$B$13),"Scădere de venit",IF(AND($N15<>"",$N15<7),"Detractor activ",IF(AND($E15>0,$J15>'09_PARAMETRI'!$B$19),"Risc concentrare",IF(AND($E15>0,$I15<>"",$I15<'09_PARAMETRI'!$B$15),"Marjă sub referință",IF(AND($G15<>"",$G15>='09_PARAMETRI'!$B$14),"În creștere",IF($E15=0,"Fără activitate","Stabil"))))))))) | P15: =IF($A15="","",IF($O15="Risc concentrare","Risc concentrare",IF($O15="Client pierdut","Recuperare client",IF($O15="Client dormant","Reactivare client",IF($O15="Scădere de venit","Recuperare client",IF($O15="Detractor activ","Recuperare NPS",IF($O15="Marjă sub referință","Marjă / preț",IF($O15="În creștere","Up-sell",IF($O15="Fără activitate","Reactivare client","Cross-sell"))))))))) | Q15: =IF($A15="","",IFERROR(IF($O15="Scădere de venit",MAX(0,$F15-$E15),IF(OR($O15="Client pierdut",$O15="Client dormant",$O15="Fără activitate"),$F15,IF($O15="Marjă sub referință",MAX(0,$E15*('09_PARAMETRI'!$B$15-$I15)),$E15*0.15))),"")) | R15: =IF(OR($A15="",$E15="",N($E15)<=0),"",$E15+ROW()/1000000)
A16: =IF('10_CLIENTI'!$A16="","",'10_CLIENTI'!$A16) | B16: =IF($A16="","",IFERROR(INDEX('10_CLIENTI'!$B$5:$B$204,MATCH($A16,'10_CLIENTI'!$A$5:$A$204,0)),"")) | C16: =IF($A16="","",IFERROR(INDEX('10_CLIENTI'!$C$5:$C$204,MATCH($A16,'10_CLIENTI'!$A$5:$A$204,0)),"")) | D16: =IF($A16="","",IFERROR(INDEX('10_CLIENTI'!$G$5:$G$204,MATCH($A16,'10_CLIENTI'!$A$5:$A$204,0)),"")) | E16: =IF($A16="","",SUMIFS('13_VANZARI'!$H$5:$H$1004,'13_VANZARI'!$D$5:$D$1004,$A16,'13_VANZARI'!$A$5:$A$1004,">="&'09_PARAMETRI'!$B$5,'13_VANZARI'!$A$5:$A$1004,"<="&'09_PARAMETRI'!$B$6)) | F16: =IF($A16="","",SUMIFS('13_VANZARI'!$H$5:$H$1004,'13_VANZARI'!$D$5:$D$1004,$A16,'13_VANZARI'!$A$5:$A$1004,">="&'09_PARAMETRI'!$B$7,'13_VANZARI'!$A$5:$A$1004,"<="&'09_PARAMETRI'!$B$8)) | G16: =IF($A16="","",IFERROR(IF($F16=0,"",($E16-$F16)/ABS($F16)),"")) | H16: =IF($A16="","",SUMIFS('13_VANZARI'!$K$5:$K$1004,'13_VANZARI'!$D$5:$D$1004,$A16,'13_VANZARI'!$A$5:$A$1004,">="&'09_PARAMETRI'!$B$5,'13_VANZARI'!$A$5:$A$1004,"<="&'09_PARAMETRI'!$B$6)) | I16: =IF($A16="","",IFERROR($H16/$E16,"")) | J16: =IF($A16="","",IFERROR($E16/SUMIFS('13_VANZARI'!$H$5:$H$1004,'13_VANZARI'!$A$5:$A$1004,">="&'09_PARAMETRI'!$B$5,'13_VANZARI'!$A$5:$A$1004,"<="&'09_PARAMETRI'!$B$6),"")) | K16: =IF($A16="","",IFERROR(IF(SUMPRODUCT(MAX(('13_VANZARI'!$D$5:$D$1004=$A16)*('13_VANZARI'!$H$5:$H$1004<>"")*'13_VANZARI'!$A$5:$A$1004))=0,"",SUMPRODUCT(MAX(('13_VANZARI'!$D$5:$D$1004=$A16)*('13_VANZARI'!$H$5:$H$1004<>"")*'13_VANZARI'!$A$5:$A$1004))),"")) | L16: =IF(OR($A16="",$K16=""),"",'09_PARAMETRI'!$B$9-$K16) | M16: =IF($A16="","",SUMPRODUCT(('11_PRODUSE'!$A$5:$A$104<>"")*(SUMIFS('13_VANZARI'!$H$5:$H$1004,'13_VANZARI'!$D$5:$D$1004,$A16,'13_VANZARI'!$E$5:$E$1004,'11_PRODUSE'!$A$5:$A$104,'13_VANZARI'!$A$5:$A$1004,">="&'09_PARAMETRI'!$B$5,'13_VANZARI'!$A$5:$A$1004,"<="&'09_PARAMETRI'!$B$6)<>0))) | N16: =IF($A16="","",IFERROR(AVERAGEIFS('15_NPS'!$F$5:$F$504,'15_NPS'!$C$5:$C$504,$A16,'15_NPS'!$B$5:$B$504,">="&'09_PARAMETRI'!$B$5,'15_NPS'!$B$5:$B$504,"<="&'09_PARAMETRI'!$B$6),"")) | O16: =IF($A16="","",IF(AND($F16>0,$E16=0),"Client pierdut",IF(AND($L16<>"",$L16>'09_PARAMETRI'!$B$16,$F16>0),"Client dormant",IF(AND($G16<>"",$G16<='09_PARAMETRI'!$B$13),"Scădere de venit",IF(AND($N16<>"",$N16<7),"Detractor activ",IF(AND($E16>0,$J16>'09_PARAMETRI'!$B$19),"Risc concentrare",IF(AND($E16>0,$I16<>"",$I16<'09_PARAMETRI'!$B$15),"Marjă sub referință",IF(AND($G16<>"",$G16>='09_PARAMETRI'!$B$14),"În creștere",IF($E16=0,"Fără activitate","Stabil"))))))))) | P16: =IF($A16="","",IF($O16="Risc concentrare","Risc concentrare",IF($O16="Client pierdut","Recuperare client",IF($O16="Client dormant","Reactivare client",IF($O16="Scădere de venit","Recuperare client",IF($O16="Detractor activ","Recuperare NPS",IF($O16="Marjă sub referință","Marjă / preț",IF($O16="În creștere","Up-sell",IF($O16="Fără activitate","Reactivare client","Cross-sell"))))))))) | Q16: =IF($A16="","",IFERROR(IF($O16="Scădere de venit",MAX(0,$F16-$E16),IF(OR($O16="Client pierdut",$O16="Client dormant",$O16="Fără activitate"),$F16,IF($O16="Marjă sub referință",MAX(0,$E16*('09_PARAMETRI'!$B$15-$I16)),$E16*0.15))),"")) | R16: =IF(OR($A16="",$E16="",N($E16)<=0),"",$E16+ROW()/1000000)
... A204: =IF('10_CLIENTI'!$A204="","",'10_CLIENTI'!$A204) | B204: =IF($A204="","",IFERROR(INDEX('10_CLIENTI'!$B$5:$B$204,MATCH($A204,'10_CLIENTI'!$A$5:$A$204,0)),"")) | C204: =IF($A204="","",IFERROR(INDEX('10_CLIENTI'!$C$5:$C$204,MATCH($A204,'10_CLIENTI'!$A$5:$A$204,0)),"")) | D204: =IF($A204="","",IFERROR(INDEX('10_CLIENTI'!$G$5:$G$204,MATCH($A204,'10_CLIENTI'!$A$5:$A$204,0)),"")) | E204: =IF($A204="","",SUMIFS('13_VANZARI'!$H$5:$H$1004,'13_VANZARI'!$D$5:$D$1004,$A204,'13_VANZARI'!$A$5:$A$1004,">="&'09_PARAMETRI'!$B$5,'13_VANZARI'!$A$5:$A$1004,"<="&'09_PARAMETRI'!$B$6)) | F204: =IF($A204="","",SUMIFS('13_VANZARI'!$H$5:$H$1004,'13_VANZARI'!$D$5:$D$1004,$A204,'13_VANZARI'!$A$5:$A$1004,">="&'09_PARAMETRI'!$B$7,'13_VANZARI'!$A$5:$A$1004,"<="&'09_PARAMETRI'!$B$8)) | G204: =IF($A204="","",IFERROR(IF($F204=0,"",($E204-$F204)/ABS($F204)),"")) | H204: =IF($A204="","",SUMIFS('13_VANZARI'!$K$5:$K$1004,'13_VANZARI'!$D$5:$D$1004,$A204,'13_VANZARI'!$A$5:$A$1004,">="&'09_PARAMETRI'!$B$5,'13_VANZARI'!$A$5:$A$1004,"<="&'09_PARAMETRI'!$B$6)) | I204: =IF($A204="","",IFERROR($H204/$E204,"")) | J204: =IF($A204="","",IFERROR($E204/SUMIFS('13_VANZARI'!$H$5:$H$1004,'13_VANZARI'!$A$5:$A$1004,">="&'09_PARAMETRI'!$B$5,'13_VANZARI'!$A$5:$A$1004,"<="&'09_PARAMETRI'!$B$6),"")) | K204: =IF($A204="","",IFERROR(IF(SUMPRODUCT(MAX(('13_VANZARI'!$D$5:$D$1004=$A204)*('13_VANZARI'!$H$5:$H$1004<>"")*'13_VANZARI'!$A$5:$A$1004))=0,"",SUMPRODUCT(MAX(('13_VANZARI'!$D$5:$D$1004=$A204)*('13_VANZARI'!$H$5:$H$1004<>"")*'13_VANZARI'!$A$5:$A$1004))),"")) | L204: =IF(OR($A204="",$K204=""),"",'09_PARAMETRI'!$B$9-$K204) | M204: =IF($A204="","",SUMPRODUCT(('11_PRODUSE'!$A$5:$A$104<>"")*(SUMIFS('13_VANZARI'!$H$5:$H$1004,'13_VANZARI'!$D$5:$D$1004,$A204,'13_VANZARI'!$E$5:$E$1004,'11_PRODUSE'!$A$5:$A$104,'13_VANZARI'!$A$5:$A$1004,">="&'09_PARAMETRI'!$B$5,'13_VANZARI'!$A$5:$A$1004,"<="&'09_PARAMETRI'!$B$6)<>0))) | N204: =IF($A204="","",IFERROR(AVERAGEIFS('15_NPS'!$F$5:$F$504,'15_NPS'!$C$5:$C$504,$A204,'15_NPS'!$B$5:$B$504,">="&'09_PARAMETRI'!$B$5,'15_NPS'!$B$5:$B$504,"<="&'09_PARAMETRI'!$B$6),"")) | O204: =IF($A204="","",IF(AND($F204>0,$E204=0),"Client pierdut",IF(AND($L204<>"",$L204>'09_PARAMETRI'!$B$16,$F204>0),"Client dormant",IF(AND($G204<>"",$G204<='09_PARAMETRI'!$B$13),"Scădere de venit",IF(AND($N204<>"",$N204<7),"Detractor activ",IF(AND($E204>0,$J204>'09_PARAMETRI'!$B$19),"Risc concentrare",IF(AND($E204>0,$I204<>"",$I204<'09_PARAMETRI'!$B$15),"Marjă sub referință",IF(AND($G204<>"",$G204>='09_PARAMETRI'!$B$14),"În creștere",IF($E204=0,"Fără activitate","Stabil"))))))))) | P204: =IF($A204="","",IF($O204="Risc concentrare","Risc concentrare",IF($O204="Client pierdut","Recuperare client",IF($O204="Client dormant","Reactivare client",IF($O204="Scădere de venit","Recuperare client",IF($O204="Detractor activ","Recuperare NPS",IF($O204="Marjă sub referință","Marjă / preț",IF($O204="În creștere","Up-sell",IF($O204="Fără activitate","Reactivare client","Cross-sell"))))))))) | Q204: =IF($A204="","",IFERROR(IF($O204="Scădere de venit",MAX(0,$F204-$E204),IF(OR($O204="Client pierdut",$O204="Client dormant",$O204="Fără activitate"),$F204,IF($O204="Marjă sub referință",MAX(0,$E204*('09_PARAMETRI'!$B$15-$I204)),$E204*0.15))),"")) | R204: =IF(OR($A204="",$E204="",N($E204)<=0),"",$E204+ROW()/1000000)

Sheet 22_ANALIZA_PRODUSE
A1: 22 — ANALIZA PRODUSELOR
A2: Arată unde e marjă de recuperat și ce produse merg bine, dar ajung la prea puțini clienți.
A4: ID produs | B4: Denumire produs | C4: Categorie | D4: Venit — curent | E4: Venit — comparativ | F4: Δ venit % | G4: Profit brut | H4: Marjă % | I4: Unități | J4: Preț mediu | K4: Nr. clienți care cumpără | L4: Penetrare în baza de clienți | M4: Semnal | N4: Oportunitate sugerată | O4: Potențial estimat | P4: Cheie clasament
A5: =IF('11_PRODUSE'!$A5="","",'11_PRODUSE'!$A5) | B5: =IF($A5="","",IFERROR(INDEX('11_PRODUSE'!$B$5:$B$104,MATCH($A5,'11_PRODUSE'!$A$5:$A$104,0)),"")) | C5: =IF($A5="","",IFERROR(INDEX('11_PRODUSE'!$C$5:$C$104,MATCH($A5,'11_PRODUSE'!$A$5:$A$104,0)),"")) | D5: =IF($A5="","",SUMIFS('13_VANZARI'!$H$5:$H$1004,'13_VANZARI'!$E$5:$E$1004,$A5,'13_VANZARI'!$A$5:$A$1004,">="&'09_PARAMETRI'!$B$5,'13_VANZARI'!$A$5:$A$1004,"<="&'09_PARAMETRI'!$B$6)) | E5: =IF($A5="","",SUMIFS('13_VANZARI'!$H$5:$H$1004,'13_VANZARI'!$E$5:$E$1004,$A5,'13_VANZARI'!$A$5:$A$1004,">="&'09_PARAMETRI'!$B$7,'13_VANZARI'!$A$5:$A$1004,"<="&'09_PARAMETRI'!$B$8)) | F5: =IF($A5="","",IFERROR(IF($E5=0,"",($D5-$E5)/ABS($E5)),"")) | G5: =IF($A5="","",SUMIFS('13_VANZARI'!$K$5:$K$1004,'13_VANZARI'!$E$5:$E$1004,$A5,'13_VANZARI'!$A$5:$A$1004,">="&'09_PARAMETRI'!$B$5,'13_VANZARI'!$A$5:$A$1004,"<="&'09_PARAMETRI'!$B$6)) | H5: =IF($A5="","",IFERROR($G5/$D5,"")) | I5: =IF($A5="","",SUMIFS('13_VANZARI'!$G$5:$G$1004,'13_VANZARI'!$E$5:$E$1004,$A5,'13_VANZARI'!$A$5:$A$1004,">="&'09_PARAMETRI'!$B$5,'13_VANZARI'!$A$5:$A$1004,"<="&'09_PARAMETRI'!$B$6)) | J5: =IF($A5="","",IFERROR($D5/$I5,"")) | K5: =IF($A5="","",SUMPRODUCT(('10_CLIENTI'!$A$5:$A$204<>"")*(SUMIFS('13_VANZARI'!$H$5:$H$1004,'13_VANZARI'!$E$5:$E$1004,$A5,'13_VANZARI'!$D$5:$D$1004,'10_CLIENTI'!$A$5:$A$204,'13_VANZARI'!$A$5:$A$1004,">="&'09_PARAMETRI'!$B$5,'13_VANZARI'!$A$5:$A$1004,"<="&'09_PARAMETRI'!$B$6)<>0))) | L5: =IF($A5="","",IFERROR($K5/(SUMPRODUCT(('10_CLIENTI'!$A$5:$A$204<>"")*(SUMIFS('13_VANZARI'!$H$5:$H$1004,'13_VANZARI'!$D$5:$D$1004,'10_CLIENTI'!$A$5:$A$204,'13_VANZARI'!$A$5:$A$1004,">="&'09_PARAMETRI'!$B$5,'13_VANZARI'!$A$5:$A$1004,"<="&'09_PARAMETRI'!$B$6)<>0))),"")) | M5: =IF($A5="","",IF(AND($D5>0,$H5<>"",$H5<'09_PARAMETRI'!$B$15),"Marjă sub referință",IF(AND($F5<>"",$F5>='09_PARAMETRI'!$B$14,$L5<0.3),"Creștere + penetrare mică",IF(AND($F5<>"",$F5<='09_PARAMETRI'!$B$13),"Produs în scădere",IF($D5=0,"Fără vânzări","Stabil"))))) | N5: =IF($A5="","",IF($M5="Marjă sub referință","Marjă / preț",IF($M5="Creștere + penetrare mică","Creștere produs",IF($M5="Produs în scădere","Cross-sell",IF($M5="Fără vânzări","Proces / operațional","Cross-sell"))))) | O5: =IF($A5="","",IFERROR(IF($M5="Marjă sub referință",MAX(0,$D5*('09_PARAMETRI'!$B$15-$H5)),IF($M5="Creștere + penetrare mică",$D5*0.5,IF($M5="Produs în scădere",MAX(0,$E5-$D5),$D5*0.1))),"")) | P5: =IF(OR($A5="",$D5="",N($D5)<=0),"",$D5+ROW()/1000000)
A6: =IF('11_PRODUSE'!$A6="","",'11_PRODUSE'!$A6) | B6: =IF($A6="","",IFERROR(INDEX('11_PRODUSE'!$B$5:$B$104,MATCH($A6,'11_PRODUSE'!$A$5:$A$104,0)),"")) | C6: =IF($A6="","",IFERROR(INDEX('11_PRODUSE'!$C$5:$C$104,MATCH($A6,'11_PRODUSE'!$A$5:$A$104,0)),"")) | D6: =IF($A6="","",SUMIFS('13_VANZARI'!$H$5:$H$1004,'13_VANZARI'!$E$5:$E$1004,$A6,'13_VANZARI'!$A$5:$A$1004,">="&'09_PARAMETRI'!$B$5,'13_VANZARI'!$A$5:$A$1004,"<="&'09_PARAMETRI'!$B$6)) | E6: =IF($A6="","",SUMIFS('13_VANZARI'!$H$5:$H$1004,'13_VANZARI'!$E$5:$E$1004,$A6,'13_VANZARI'!$A$5:$A$1004,">="&'09_PARAMETRI'!$B$7,'13_VANZARI'!$A$5:$A$1004,"<="&'09_PARAMETRI'!$B$8)) | F6: =IF($A6="","",IFERROR(IF($E6=0,"",($D6-$E6)/ABS($E6)),"")) | G6: =IF($A6="","",SUMIFS('13_VANZARI'!$K$5:$K$1004,'13_VANZARI'!$E$5:$E$1004,$A6,'13_VANZARI'!$A$5:$A$1004,">="&'09_PARAMETRI'!$B$5,'13_VANZARI'!$A$5:$A$1004,"<="&'09_PARAMETRI'!$B$6)) | H6: =IF($A6="","",IFERROR($G6/$D6,"")) | I6: =IF($A6="","",SUMIFS('13_VANZARI'!$G$5:$G$1004,'13_VANZARI'!$E$5:$E$1004,$A6,'13_VANZARI'!$A$5:$A$1004,">="&'09_PARAMETRI'!$B$5,'13_VANZARI'!$A$5:$A$1004,"<="&'09_PARAMETRI'!$B$6)) | J6: =IF($A6="","",IFERROR($D6/$I6,"")) | K6: =IF($A6="","",SUMPRODUCT(('10_CLIENTI'!$A$5:$A$204<>"")*(SUMIFS('13_VANZARI'!$H$5:$H$1004,'13_VANZARI'!$E$5:$E$1004,$A6,'13_VANZARI'!$D$5:$D$1004,'10_CLIENTI'!$A$5:$A$204,'13_VANZARI'!$A$5:$A$1004,">="&'09_PARAMETRI'!$B$5,'13_VANZARI'!$A$5:$A$1004,"<="&'09_PARAMETRI'!$B$6)<>0))) | L6: =IF($A6="","",IFERROR($K6/(SUMPRODUCT(('10_CLIENTI'!$A$5:$A$204<>"")*(SUMIFS('13_VANZARI'!$H$5:$H$1004,'13_VANZARI'!$D$5:$D$1004,'10_CLIENTI'!$A$5:$A$204,'13_VANZARI'!$A$5:$A$1004,">="&'09_PARAMETRI'!$B$5,'13_VANZARI'!$A$5:$A$1004,"<="&'09_PARAMETRI'!$B$6)<>0))),"")) | M6: =IF($A6="","",IF(AND($D6>0,$H6<>"",$H6<'09_PARAMETRI'!$B$15),"Marjă sub referință",IF(AND($F6<>"",$F6>='09_PARAMETRI'!$B$14,$L6<0.3),"Creștere + penetrare mică",IF(AND($F6<>"",$F6<='09_PARAMETRI'!$B$13),"Produs în scădere",IF($D6=0,"Fără vânzări","Stabil"))))) | N6: =IF($A6="","",IF($M6="Marjă sub referință","Marjă / preț",IF($M6="Creștere + penetrare mică","Creștere produs",IF($M6="Produs în scădere","Cross-sell",IF($M6="Fără vânzări","Proces / operațional","Cross-sell"))))) | O6: =IF($A6="","",IFERROR(IF($M6="Marjă sub referință",MAX(0,$D6*('09_PARAMETRI'!$B$15-$H6)),IF($M6="Creștere + penetrare mică",$D6*0.5,IF($M6="Produs în scădere",MAX(0,$E6-$D6),$D6*0.1))),"")) | P6: =IF(OR($A6="",$D6="",N($D6)<=0),"",$D6+ROW()/1000000)
A7: =IF('11_PRODUSE'!$A7="","",'11_PRODUSE'!$A7) | B7: =IF($A7="","",IFERROR(INDEX('11_PRODUSE'!$B$5:$B$104,MATCH($A7,'11_PRODUSE'!$A$5:$A$104,0)),"")) | C7: =IF($A7="","",IFERROR(INDEX('11_PRODUSE'!$C$5:$C$104,MATCH($A7,'11_PRODUSE'!$A$5:$A$104,0)),"")) | D7: =IF($A7="","",SUMIFS('13_VANZARI'!$H$5:$H$1004,'13_VANZARI'!$E$5:$E$1004,$A7,'13_VANZARI'!$A$5:$A$1004,">="&'09_PARAMETRI'!$B$5,'13_VANZARI'!$A$5:$A$1004,"<="&'09_PARAMETRI'!$B$6)) | E7: =IF($A7="","",SUMIFS('13_VANZARI'!$H$5:$H$1004,'13_VANZARI'!$E$5:$E$1004,$A7,'13_VANZARI'!$A$5:$A$1004,">="&'09_PARAMETRI'!$B$7,'13_VANZARI'!$A$5:$A$1004,"<="&'09_PARAMETRI'!$B$8)) | F7: =IF($A7="","",IFERROR(IF($E7=0,"",($D7-$E7)/ABS($E7)),"")) | G7: =IF($A7="","",SUMIFS('13_VANZARI'!$K$5:$K$1004,'13_VANZARI'!$E$5:$E$1004,$A7,'13_VANZARI'!$A$5:$A$1004,">="&'09_PARAMETRI'!$B$5,'13_VANZARI'!$A$5:$A$1004,"<="&'09_PARAMETRI'!$B$6)) | H7: =IF($A7="","",IFERROR($G7/$D7,"")) | I7: =IF($A7="","",SUMIFS('13_VANZARI'!$G$5:$G$1004,'13_VANZARI'!$E$5:$E$1004,$A7,'13_VANZARI'!$A$5:$A$1004,">="&'09_PARAMETRI'!$B$5,'13_VANZARI'!$A$5:$A$1004,"<="&'09_PARAMETRI'!$B$6)) | J7: =IF($A7="","",IFERROR($D7/$I7,"")) | K7: =IF($A7="","",SUMPRODUCT(('10_CLIENTI'!$A$5:$A$204<>"")*(SUMIFS('13_VANZARI'!$H$5:$H$1004,'13_VANZARI'!$E$5:$E$1004,$A7,'13_VANZARI'!$D$5:$D$1004,'10_CLIENTI'!$A$5:$A$204,'13_VANZARI'!$A$5:$A$1004,">="&'09_PARAMETRI'!$B$5,'13_VANZARI'!$A$5:$A$1004,"<="&'09_PARAMETRI'!$B$6)<>0))) | L7: =IF($A7="","",IFERROR($K7/(SUMPRODUCT(('10_CLIENTI'!$A$5:$A$204<>"")*(SUMIFS('13_VANZARI'!$H$5:$H$1004,'13_VANZARI'!$D$5:$D$1004,'10_CLIENTI'!$A$5:$A$204,'13_VANZARI'!$A$5:$A$1004,">="&'09_PARAMETRI'!$B$5,'13_VANZARI'!$A$5:$A$1004,"<="&'09_PARAMETRI'!$B$6)<>0))),"")) | M7: =IF($A7="","",IF(AND($D7>0,$H7<>"",$H7<'09_PARAMETRI'!$B$15),"Marjă sub referință",IF(AND($F7<>"",$F7>='09_PARAMETRI'!$B$14,$L7<0.3),"Creștere + penetrare mică",IF(AND($F7<>"",$F7<='09_PARAMETRI'!$B$13),"Produs în scădere",IF($D7=0,"Fără vânzări","Stabil"))))) | N7: =IF($A7="","",IF($M7="Marjă sub referință","Marjă / preț",IF($M7="Creștere + penetrare mică","Creștere produs",IF($M7="Produs în scădere","Cross-sell",IF($M7="Fără vânzări","Proces / operațional","Cross-sell"))))) | O7: =IF($A7="","",IFERROR(IF($M7="Marjă sub referință",MAX(0,$D7*('09_PARAMETRI'!$B$15-$H7)),IF($M7="Creștere + penetrare mică",$D7*0.5,IF($M7="Produs în scădere",MAX(0,$E7-$D7),$D7*0.1))),"")) | P7: =IF(OR($A7="",$D7="",N($D7)<=0),"",$D7+ROW()/1000000)
A8: =IF('11_PRODUSE'!$A8="","",'11_PRODUSE'!$A8) | B8: =IF($A8="","",IFERROR(INDEX('11_PRODUSE'!$B$5:$B$104,MATCH($A8,'11_PRODUSE'!$A$5:$A$104,0)),"")) | C8: =IF($A8="","",IFERROR(INDEX('11_PRODUSE'!$C$5:$C$104,MATCH($A8,'11_PRODUSE'!$A$5:$A$104,0)),"")) | D8: =IF($A8="","",SUMIFS('13_VANZARI'!$H$5:$H$1004,'13_VANZARI'!$E$5:$E$1004,$A8,'13_VANZARI'!$A$5:$A$1004,">="&'09_PARAMETRI'!$B$5,'13_VANZARI'!$A$5:$A$1004,"<="&'09_PARAMETRI'!$B$6)) | E8: =IF($A8="","",SUMIFS('13_VANZARI'!$H$5:$H$1004,'13_VANZARI'!$E$5:$E$1004,$A8,'13_VANZARI'!$A$5:$A$1004,">="&'09_PARAMETRI'!$B$7,'13_VANZARI'!$A$5:$A$1004,"<="&'09_PARAMETRI'!$B$8)) | F8: =IF($A8="","",IFERROR(IF($E8=0,"",($D8-$E8)/ABS($E8)),"")) | G8: =IF($A8="","",SUMIFS('13_VANZARI'!$K$5:$K$1004,'13_VANZARI'!$E$5:$E$1004,$A8,'13_VANZARI'!$A$5:$A$1004,">="&'09_PARAMETRI'!$B$5,'13_VANZARI'!$A$5:$A$1004,"<="&'09_PARAMETRI'!$B$6)) | H8: =IF($A8="","",IFERROR($G8/$D8,"")) | I8: =IF($A8="","",SUMIFS('13_VANZARI'!$G$5:$G$1004,'13_VANZARI'!$E$5:$E$1004,$A8,'13_VANZARI'!$A$5:$A$1004,">="&'09_PARAMETRI'!$B$5,'13_VANZARI'!$A$5:$A$1004,"<="&'09_PARAMETRI'!$B$6)) | J8: =IF($A8="","",IFERROR($D8/$I8,"")) | K8: =IF($A8="","",SUMPRODUCT(('10_CLIENTI'!$A$5:$A$204<>"")*(SUMIFS('13_VANZARI'!$H$5:$H$1004,'13_VANZARI'!$E$5:$E$1004,$A8,'13_VANZARI'!$D$5:$D$1004,'10_CLIENTI'!$A$5:$A$204,'13_VANZARI'!$A$5:$A$1004,">="&'09_PARAMETRI'!$B$5,'13_VANZARI'!$A$5:$A$1004,"<="&'09_PARAMETRI'!$B$6)<>0))) | L8: =IF($A8="","",IFERROR($K8/(SUMPRODUCT(('10_CLIENTI'!$A$5:$A$204<>"")*(SUMIFS('13_VANZARI'!$H$5:$H$1004,'13_VANZARI'!$D$5:$D$1004,'10_CLIENTI'!$A$5:$A$204,'13_VANZARI'!$A$5:$A$1004,">="&'09_PARAMETRI'!$B$5,'13_VANZARI'!$A$5:$A$1004,"<="&'09_PARAMETRI'!$B$6)<>0))),"")) | M8: =IF($A8="","",IF(AND($D8>0,$H8<>"",$H8<'09_PARAMETRI'!$B$15),"Marjă sub referință",IF(AND($F8<>"",$F8>='09_PARAMETRI'!$B$14,$L8<0.3),"Creștere + penetrare mică",IF(AND($F8<>"",$F8<='09_PARAMETRI'!$B$13),"Produs în scădere",IF($D8=0,"Fără vânzări","Stabil"))))) | N8: =IF($A8="","",IF($M8="Marjă sub referință","Marjă / preț",IF($M8="Creștere + penetrare mică","Creștere produs",IF($M8="Produs în scădere","Cross-sell",IF($M8="Fără vânzări","Proces / operațional","Cross-sell"))))) | O8: =IF($A8="","",IFERROR(IF($M8="Marjă sub referință",MAX(0,$D8*('09_PARAMETRI'!$B$15-$H8)),IF($M8="Creștere + penetrare mică",$D8*0.5,IF($M8="Produs în scădere",MAX(0,$E8-$D8),$D8*0.1))),"")) | P8: =IF(OR($A8="",$D8="",N($D8)<=0),"",$D8+ROW()/1000000)
A9: =IF('11_PRODUSE'!$A9="","",'11_PRODUSE'!$A9) | B9: =IF($A9="","",IFERROR(INDEX('11_PRODUSE'!$B$5:$B$104,MATCH($A9,'11_PRODUSE'!$A$5:$A$104,0)),"")) | C9: =IF($A9="","",IFERROR(INDEX('11_PRODUSE'!$C$5:$C$104,MATCH($A9,'11_PRODUSE'!$A$5:$A$104,0)),"")) | D9: =IF($A9="","",SUMIFS('13_VANZARI'!$H$5:$H$1004,'13_VANZARI'!$E$5:$E$1004,$A9,'13_VANZARI'!$A$5:$A$1004,">="&'09_PARAMETRI'!$B$5,'13_VANZARI'!$A$5:$A$1004,"<="&'09_PARAMETRI'!$B$6)) | E9: =IF($A9="","",SUMIFS('13_VANZARI'!$H$5:$H$1004,'13_VANZARI'!$E$5:$E$1004,$A9,'13_VANZARI'!$A$5:$A$1004,">="&'09_PARAMETRI'!$B$7,'13_VANZARI'!$A$5:$A$1004,"<="&'09_PARAMETRI'!$B$8)) | F9: =IF($A9="","",IFERROR(IF($E9=0,"",($D9-$E9)/ABS($E9)),"")) | G9: =IF($A9="","",SUMIFS('13_VANZARI'!$K$5:$K$1004,'13_VANZARI'!$E$5:$E$1004,$A9,'13_VANZARI'!$A$5:$A$1004,">="&'09_PARAMETRI'!$B$5,'13_VANZARI'!$A$5:$A$1004,"<="&'09_PARAMETRI'!$B$6)) | H9: =IF($A9="","",IFERROR($G9/$D9,"")) | I9: =IF($A9="","",SUMIFS('13_VANZARI'!$G$5:$G$1004,'13_VANZARI'!$E$5:$E$1004,$A9,'13_VANZARI'!$A$5:$A$1004,">="&'09_PARAMETRI'!$B$5,'13_VANZARI'!$A$5:$A$1004,"<="&'09_PARAMETRI'!$B$6)) | J9: =IF($A9="","",IFERROR($D9/$I9,"")) | K9: =IF($A9="","",SUMPRODUCT(('10_CLIENTI'!$A$5:$A$204<>"")*(SUMIFS('13_VANZARI'!$H$5:$H$1004,'13_VANZARI'!$E$5:$E$1004,$A9,'13_VANZARI'!$D$5:$D$1004,'10_CLIENTI'!$A$5:$A$204,'13_VANZARI'!$A$5:$A$1004,">="&'09_PARAMETRI'!$B$5,'13_VANZARI'!$A$5:$A$1004,"<="&'09_PARAMETRI'!$B$6)<>0))) | L9: =IF($A9="","",IFERROR($K9/(SUMPRODUCT(('10_CLIENTI'!$A$5:$A$204<>"")*(SUMIFS('13_VANZARI'!$H$5:$H$1004,'13_VANZARI'!$D$5:$D$1004,'10_CLIENTI'!$A$5:$A$204,'13_VANZARI'!$A$5:$A$1004,">="&'09_PARAMETRI'!$B$5,'13_VANZARI'!$A$5:$A$1004,"<="&'09_PARAMETRI'!$B$6)<>0))),"")) | M9: =IF($A9="","",IF(AND($D9>0,$H9<>"",$H9<'09_PARAMETRI'!$B$15),"Marjă sub referință",IF(AND($F9<>"",$F9>='09_PARAMETRI'!$B$14,$L9<0.3),"Creștere + penetrare mică",IF(AND($F9<>"",$F9<='09_PARAMETRI'!$B$13),"Produs în scădere",IF($D9=0,"Fără vânzări","Stabil"))))) | N9: =IF($A9="","",IF($M9="Marjă sub referință","Marjă / preț",IF($M9="Creștere + penetrare mică","Creștere produs",IF($M9="Produs în scădere","Cross-sell",IF($M9="Fără vânzări","Proces / operațional","Cross-sell"))))) | O9: =IF($A9="","",IFERROR(IF($M9="Marjă sub referință",MAX(0,$D9*('09_PARAMETRI'!$B$15-$H9)),IF($M9="Creștere + penetrare mică",$D9*0.5,IF($M9="Produs în scădere",MAX(0,$E9-$D9),$D9*0.1))),"")) | P9: =IF(OR($A9="",$D9="",N($D9)<=0),"",$D9+ROW()/1000000)
A10: =IF('11_PRODUSE'!$A10="","",'11_PRODUSE'!$A10) | B10: =IF($A10="","",IFERROR(INDEX('11_PRODUSE'!$B$5:$B$104,MATCH($A10,'11_PRODUSE'!$A$5:$A$104,0)),"")) | C10: =IF($A10="","",IFERROR(INDEX('11_PRODUSE'!$C$5:$C$104,MATCH($A10,'11_PRODUSE'!$A$5:$A$104,0)),"")) | D10: =IF($A10="","",SUMIFS('13_VANZARI'!$H$5:$H$1004,'13_VANZARI'!$E$5:$E$1004,$A10,'13_VANZARI'!$A$5:$A$1004,">="&'09_PARAMETRI'!$B$5,'13_VANZARI'!$A$5:$A$1004,"<="&'09_PARAMETRI'!$B$6)) | E10: =IF($A10="","",SUMIFS('13_VANZARI'!$H$5:$H$1004,'13_VANZARI'!$E$5:$E$1004,$A10,'13_VANZARI'!$A$5:$A$1004,">="&'09_PARAMETRI'!$B$7,'13_VANZARI'!$A$5:$A$1004,"<="&'09_PARAMETRI'!$B$8)) | F10: =IF($A10="","",IFERROR(IF($E10=0,"",($D10-$E10)/ABS($E10)),"")) | G10: =IF($A10="","",SUMIFS('13_VANZARI'!$K$5:$K$1004,'13_VANZARI'!$E$5:$E$1004,$A10,'13_VANZARI'!$A$5:$A$1004,">="&'09_PARAMETRI'!$B$5,'13_VANZARI'!$A$5:$A$1004,"<="&'09_PARAMETRI'!$B$6)) | H10: =IF($A10="","",IFERROR($G10/$D10,"")) | I10: =IF($A10="","",SUMIFS('13_VANZARI'!$G$5:$G$1004,'13_VANZARI'!$E$5:$E$1004,$A10,'13_VANZARI'!$A$5:$A$1004,">="&'09_PARAMETRI'!$B$5,'13_VANZARI'!$A$5:$A$1004,"<="&'09_PARAMETRI'!$B$6)) | J10: =IF($A10="","",IFERROR($D10/$I10,"")) | K10: =IF($A10="","",SUMPRODUCT(('10_CLIENTI'!$A$5:$A$204<>"")*(SUMIFS('13_VANZARI'!$H$5:$H$1004,'13_VANZARI'!$E$5:$E$1004,$A10,'13_VANZARI'!$D$5:$D$1004,'10_CLIENTI'!$A$5:$A$204,'13_VANZARI'!$A$5:$A$1004,">="&'09_PARAMETRI'!$B$5,'13_VANZARI'!$A$5:$A$1004,"<="&'09_PARAMETRI'!$B$6)<>0))) | L10: =IF($A10="","",IFERROR($K10/(SUMPRODUCT(('10_CLIENTI'!$A$5:$A$204<>"")*(SUMIFS('13_VANZARI'!$H$5:$H$1004,'13_VANZARI'!$D$5:$D$1004,'10_CLIENTI'!$A$5:$A$204,'13_VANZARI'!$A$5:$A$1004,">="&'09_PARAMETRI'!$B$5,'13_VANZARI'!$A$5:$A$1004,"<="&'09_PARAMETRI'!$B$6)<>0))),"")) | M10: =IF($A10="","",IF(AND($D10>0,$H10<>"",$H10<'09_PARAMETRI'!$B$15),"Marjă sub referință",IF(AND($F10<>"",$F10>='09_PARAMETRI'!$B$14,$L10<0.3),"Creștere + penetrare mică",IF(AND($F10<>"",$F10<='09_PARAMETRI'!$B$13),"Produs în scădere",IF($D10=0,"Fără vânzări","Stabil"))))) | N10: =IF($A10="","",IF($M10="Marjă sub referință","Marjă / preț",IF($M10="Creștere + penetrare mică","Creștere produs",IF($M10="Produs în scădere","Cross-sell",IF($M10="Fără vânzări","Proces / operațional","Cross-sell"))))) | O10: =IF($A10="","",IFERROR(IF($M10="Marjă sub referință",MAX(0,$D10*('09_PARAMETRI'!$B$15-$H10)),IF($M10="Creștere + penetrare mică",$D10*0.5,IF($M10="Produs în scădere",MAX(0,$E10-$D10),$D10*0.1))),"")) | P10: =IF(OR($A10="",$D10="",N($D10)<=0),"",$D10+ROW()/1000000)
A11: =IF('11_PRODUSE'!$A11="","",'11_PRODUSE'!$A11) | B11: =IF($A11="","",IFERROR(INDEX('11_PRODUSE'!$B$5:$B$104,MATCH($A11,'11_PRODUSE'!$A$5:$A$104,0)),"")) | C11: =IF($A11="","",IFERROR(INDEX('11_PRODUSE'!$C$5:$C$104,MATCH($A11,'11_PRODUSE'!$A$5:$A$104,0)),"")) | D11: =IF($A11="","",SUMIFS('13_VANZARI'!$H$5:$H$1004,'13_VANZARI'!$E$5:$E$1004,$A11,'13_VANZARI'!$A$5:$A$1004,">="&'09_PARAMETRI'!$B$5,'13_VANZARI'!$A$5:$A$1004,"<="&'09_PARAMETRI'!$B$6)) | E11: =IF($A11="","",SUMIFS('13_VANZARI'!$H$5:$H$1004,'13_VANZARI'!$E$5:$E$1004,$A11,'13_VANZARI'!$A$5:$A$1004,">="&'09_PARAMETRI'!$B$7,'13_VANZARI'!$A$5:$A$1004,"<="&'09_PARAMETRI'!$B$8)) | F11: =IF($A11="","",IFERROR(IF($E11=0,"",($D11-$E11)/ABS($E11)),"")) | G11: =IF($A11="","",SUMIFS('13_VANZARI'!$K$5:$K$1004,'13_VANZARI'!$E$5:$E$1004,$A11,'13_VANZARI'!$A$5:$A$1004,">="&'09_PARAMETRI'!$B$5,'13_VANZARI'!$A$5:$A$1004,"<="&'09_PARAMETRI'!$B$6)) | H11: =IF($A11="","",IFERROR($G11/$D11,"")) | I11: =IF($A11="","",SUMIFS('13_VANZARI'!$G$5:$G$1004,'13_VANZARI'!$E$5:$E$1004,$A11,'13_VANZARI'!$A$5:$A$1004,">="&'09_PARAMETRI'!$B$5,'13_VANZARI'!$A$5:$A$1004,"<="&'09_PARAMETRI'!$B$6)) | J11: =IF($A11="","",IFERROR($D11/$I11,"")) | K11: =IF($A11="","",SUMPRODUCT(('10_CLIENTI'!$A$5:$A$204<>"")*(SUMIFS('13_VANZARI'!$H$5:$H$1004,'13_VANZARI'!$E$5:$E$1004,$A11,'13_VANZARI'!$D$5:$D$1004,'10_CLIENTI'!$A$5:$A$204,'13_VANZARI'!$A$5:$A$1004,">="&'09_PARAMETRI'!$B$5,'13_VANZARI'!$A$5:$A$1004,"<="&'09_PARAMETRI'!$B$6)<>0))) | L11: =IF($A11="","",IFERROR($K11/(SUMPRODUCT(('10_CLIENTI'!$A$5:$A$204<>"")*(SUMIFS('13_VANZARI'!$H$5:$H$1004,'13_VANZARI'!$D$5:$D$1004,'10_CLIENTI'!$A$5:$A$204,'13_VANZARI'!$A$5:$A$1004,">="&'09_PARAMETRI'!$B$5,'13_VANZARI'!$A$5:$A$1004,"<="&'09_PARAMETRI'!$B$6)<>0))),"")) | M11: =IF($A11="","",IF(AND($D11>0,$H11<>"",$H11<'09_PARAMETRI'!$B$15),"Marjă sub referință",IF(AND($F11<>"",$F11>='09_PARAMETRI'!$B$14,$L11<0.3),"Creștere + penetrare mică",IF(AND($F11<>"",$F11<='09_PARAMETRI'!$B$13),"Produs în scădere",IF($D11=0,"Fără vânzări","Stabil"))))) | N11: =IF($A11="","",IF($M11="Marjă sub referință","Marjă / preț",IF($M11="Creștere + penetrare mică","Creștere produs",IF($M11="Produs în scădere","Cross-sell",IF($M11="Fără vânzări","Proces / operațional","Cross-sell"))))) | O11: =IF($A11="","",IFERROR(IF($M11="Marjă sub referință",MAX(0,$D11*('09_PARAMETRI'!$B$15-$H11)),IF($M11="Creștere + penetrare mică",$D11*0.5,IF($M11="Produs în scădere",MAX(0,$E11-$D11),$D11*0.1))),"")) | P11: =IF(OR($A11="",$D11="",N($D11)<=0),"",$D11+ROW()/1000000)
A12: =IF('11_PRODUSE'!$A12="","",'11_PRODUSE'!$A12) | B12: =IF($A12="","",IFERROR(INDEX('11_PRODUSE'!$B$5:$B$104,MATCH($A12,'11_PRODUSE'!$A$5:$A$104,0)),"")) | C12: =IF($A12="","",IFERROR(INDEX('11_PRODUSE'!$C$5:$C$104,MATCH($A12,'11_PRODUSE'!$A$5:$A$104,0)),"")) | D12: =IF($A12="","",SUMIFS('13_VANZARI'!$H$5:$H$1004,'13_VANZARI'!$E$5:$E$1004,$A12,'13_VANZARI'!$A$5:$A$1004,">="&'09_PARAMETRI'!$B$5,'13_VANZARI'!$A$5:$A$1004,"<="&'09_PARAMETRI'!$B$6)) | E12: =IF($A12="","",SUMIFS('13_VANZARI'!$H$5:$H$1004,'13_VANZARI'!$E$5:$E$1004,$A12,'13_VANZARI'!$A$5:$A$1004,">="&'09_PARAMETRI'!$B$7,'13_VANZARI'!$A$5:$A$1004,"<="&'09_PARAMETRI'!$B$8)) | F12: =IF($A12="","",IFERROR(IF($E12=0,"",($D12-$E12)/ABS($E12)),"")) | G12: =IF($A12="","",SUMIFS('13_VANZARI'!$K$5:$K$1004,'13_VANZARI'!$E$5:$E$1004,$A12,'13_VANZARI'!$A$5:$A$1004,">="&'09_PARAMETRI'!$B$5,'13_VANZARI'!$A$5:$A$1004,"<="&'09_PARAMETRI'!$B$6)) | H12: =IF($A12="","",IFERROR($G12/$D12,"")) | I12: =IF($A12="","",SUMIFS('13_VANZARI'!$G$5:$G$1004,'13_VANZARI'!$E$5:$E$1004,$A12,'13_VANZARI'!$A$5:$A$1004,">="&'09_PARAMETRI'!$B$5,'13_VANZARI'!$A$5:$A$1004,"<="&'09_PARAMETRI'!$B$6)) | J12: =IF($A12="","",IFERROR($D12/$I12,"")) | K12: =IF($A12="","",SUMPRODUCT(('10_CLIENTI'!$A$5:$A$204<>"")*(SUMIFS('13_VANZARI'!$H$5:$H$1004,'13_VANZARI'!$E$5:$E$1004,$A12,'13_VANZARI'!$D$5:$D$1004,'10_CLIENTI'!$A$5:$A$204,'13_VANZARI'!$A$5:$A$1004,">="&'09_PARAMETRI'!$B$5,'13_VANZARI'!$A$5:$A$1004,"<="&'09_PARAMETRI'!$B$6)<>0))) | L12: =IF($A12="","",IFERROR($K12/(SUMPRODUCT(('10_CLIENTI'!$A$5:$A$204<>"")*(SUMIFS('13_VANZARI'!$H$5:$H$1004,'13_VANZARI'!$D$5:$D$1004,'10_CLIENTI'!$A$5:$A$204,'13_VANZARI'!$A$5:$A$1004,">="&'09_PARAMETRI'!$B$5,'13_VANZARI'!$A$5:$A$1004,"<="&'09_PARAMETRI'!$B$6)<>0))),"")) | M12: =IF($A12="","",IF(AND($D12>0,$H12<>"",$H12<'09_PARAMETRI'!$B$15),"Marjă sub referință",IF(AND($F12<>"",$F12>='09_PARAMETRI'!$B$14,$L12<0.3),"Creștere + penetrare mică",IF(AND($F12<>"",$F12<='09_PARAMETRI'!$B$13),"Produs în scădere",IF($D12=0,"Fără vânzări","Stabil"))))) | N12: =IF($A12="","",IF($M12="Marjă sub referință","Marjă / preț",IF($M12="Creștere + penetrare mică","Creștere produs",IF($M12="Produs în scădere","Cross-sell",IF($M12="Fără vânzări","Proces / operațional","Cross-sell"))))) | O12: =IF($A12="","",IFERROR(IF($M12="Marjă sub referință",MAX(0,$D12*('09_PARAMETRI'!$B$15-$H12)),IF($M12="Creștere + penetrare mică",$D12*0.5,IF($M12="Produs în scădere",MAX(0,$E12-$D12),$D12*0.1))),"")) | P12: =IF(OR($A12="",$D12="",N($D12)<=0),"",$D12+ROW()/1000000)
A13: =IF('11_PRODUSE'!$A13="","",'11_PRODUSE'!$A13) | B13: =IF($A13="","",IFERROR(INDEX('11_PRODUSE'!$B$5:$B$104,MATCH($A13,'11_PRODUSE'!$A$5:$A$104,0)),"")) | C13: =IF($A13="","",IFERROR(INDEX('11_PRODUSE'!$C$5:$C$104,MATCH($A13,'11_PRODUSE'!$A$5:$A$104,0)),"")) | D13: =IF($A13="","",SUMIFS('13_VANZARI'!$H$5:$H$1004,'13_VANZARI'!$E$5:$E$1004,$A13,'13_VANZARI'!$A$5:$A$1004,">="&'09_PARAMETRI'!$B$5,'13_VANZARI'!$A$5:$A$1004,"<="&'09_PARAMETRI'!$B$6)) | E13: =IF($A13="","",SUMIFS('13_VANZARI'!$H$5:$H$1004,'13_VANZARI'!$E$5:$E$1004,$A13,'13_VANZARI'!$A$5:$A$1004,">="&'09_PARAMETRI'!$B$7,'13_VANZARI'!$A$5:$A$1004,"<="&'09_PARAMETRI'!$B$8)) | F13: =IF($A13="","",IFERROR(IF($E13=0,"",($D13-$E13)/ABS($E13)),"")) | G13: =IF($A13="","",SUMIFS('13_VANZARI'!$K$5:$K$1004,'13_VANZARI'!$E$5:$E$1004,$A13,'13_VANZARI'!$A$5:$A$1004,">="&'09_PARAMETRI'!$B$5,'13_VANZARI'!$A$5:$A$1004,"<="&'09_PARAMETRI'!$B$6)) | H13: =IF($A13="","",IFERROR($G13/$D13,"")) | I13: =IF($A13="","",SUMIFS('13_VANZARI'!$G$5:$G$1004,'13_VANZARI'!$E$5:$E$1004,$A13,'13_VANZARI'!$A$5:$A$1004,">="&'09_PARAMETRI'!$B$5,'13_VANZARI'!$A$5:$A$1004,"<="&'09_PARAMETRI'!$B$6)) | J13: =IF($A13="","",IFERROR($D13/$I13,"")) | K13: =IF($A13="","",SUMPRODUCT(('10_CLIENTI'!$A$5:$A$204<>"")*(SUMIFS('13_VANZARI'!$H$5:$H$1004,'13_VANZARI'!$E$5:$E$1004,$A13,'13_VANZARI'!$D$5:$D$1004,'10_CLIENTI'!$A$5:$A$204,'13_VANZARI'!$A$5:$A$1004,">="&'09_PARAMETRI'!$B$5,'13_VANZARI'!$A$5:$A$1004,"<="&'09_PARAMETRI'!$B$6)<>0))) | L13: =IF($A13="","",IFERROR($K13/(SUMPRODUCT(('10_CLIENTI'!$A$5:$A$204<>"")*(SUMIFS('13_VANZARI'!$H$5:$H$1004,'13_VANZARI'!$D$5:$D$1004,'10_CLIENTI'!$A$5:$A$204,'13_VANZARI'!$A$5:$A$1004,">="&'09_PARAMETRI'!$B$5,'13_VANZARI'!$A$5:$A$1004,"<="&'09_PARAMETRI'!$B$6)<>0))),"")) | M13: =IF($A13="","",IF(AND($D13>0,$H13<>"",$H13<'09_PARAMETRI'!$B$15),"Marjă sub referință",IF(AND($F13<>"",$F13>='09_PARAMETRI'!$B$14,$L13<0.3),"Creștere + penetrare mică",IF(AND($F13<>"",$F13<='09_PARAMETRI'!$B$13),"Produs în scădere",IF($D13=0,"Fără vânzări","Stabil"))))) | N13: =IF($A13="","",IF($M13="Marjă sub referință","Marjă / preț",IF($M13="Creștere + penetrare mică","Creștere produs",IF($M13="Produs în scădere","Cross-sell",IF($M13="Fără vânzări","Proces / operațional","Cross-sell"))))) | O13: =IF($A13="","",IFERROR(IF($M13="Marjă sub referință",MAX(0,$D13*('09_PARAMETRI'!$B$15-$H13)),IF($M13="Creștere + penetrare mică",$D13*0.5,IF($M13="Produs în scădere",MAX(0,$E13-$D13),$D13*0.1))),"")) | P13: =IF(OR($A13="",$D13="",N($D13)<=0),"",$D13+ROW()/1000000)
A14: =IF('11_PRODUSE'!$A14="","",'11_PRODUSE'!$A14) | B14: =IF($A14="","",IFERROR(INDEX('11_PRODUSE'!$B$5:$B$104,MATCH($A14,'11_PRODUSE'!$A$5:$A$104,0)),"")) | C14: =IF($A14="","",IFERROR(INDEX('11_PRODUSE'!$C$5:$C$104,MATCH($A14,'11_PRODUSE'!$A$5:$A$104,0)),"")) | D14: =IF($A14="","",SUMIFS('13_VANZARI'!$H$5:$H$1004,'13_VANZARI'!$E$5:$E$1004,$A14,'13_VANZARI'!$A$5:$A$1004,">="&'09_PARAMETRI'!$B$5,'13_VANZARI'!$A$5:$A$1004,"<="&'09_PARAMETRI'!$B$6)) | E14: =IF($A14="","",SUMIFS('13_VANZARI'!$H$5:$H$1004,'13_VANZARI'!$E$5:$E$1004,$A14,'13_VANZARI'!$A$5:$A$1004,">="&'09_PARAMETRI'!$B$7,'13_VANZARI'!$A$5:$A$1004,"<="&'09_PARAMETRI'!$B$8)) | F14: =IF($A14="","",IFERROR(IF($E14=0,"",($D14-$E14)/ABS($E14)),"")) | G14: =IF($A14="","",SUMIFS('13_VANZARI'!$K$5:$K$1004,'13_VANZARI'!$E$5:$E$1004,$A14,'13_VANZARI'!$A$5:$A$1004,">="&'09_PARAMETRI'!$B$5,'13_VANZARI'!$A$5:$A$1004,"<="&'09_PARAMETRI'!$B$6)) | H14: =IF($A14="","",IFERROR($G14/$D14,"")) | I14: =IF($A14="","",SUMIFS('13_VANZARI'!$G$5:$G$1004,'13_VANZARI'!$E$5:$E$1004,$A14,'13_VANZARI'!$A$5:$A$1004,">="&'09_PARAMETRI'!$B$5,'13_VANZARI'!$A$5:$A$1004,"<="&'09_PARAMETRI'!$B$6)) | J14: =IF($A14="","",IFERROR($D14/$I14,"")) | K14: =IF($A14="","",SUMPRODUCT(('10_CLIENTI'!$A$5:$A$204<>"")*(SUMIFS('13_VANZARI'!$H$5:$H$1004,'13_VANZARI'!$E$5:$E$1004,$A14,'13_VANZARI'!$D$5:$D$1004,'10_CLIENTI'!$A$5:$A$204,'13_VANZARI'!$A$5:$A$1004,">="&'09_PARAMETRI'!$B$5,'13_VANZARI'!$A$5:$A$1004,"<="&'09_PARAMETRI'!$B$6)<>0))) | L14: =IF($A14="","",IFERROR($K14/(SUMPRODUCT(('10_CLIENTI'!$A$5:$A$204<>"")*(SUMIFS('13_VANZARI'!$H$5:$H$1004,'13_VANZARI'!$D$5:$D$1004,'10_CLIENTI'!$A$5:$A$204,'13_VANZARI'!$A$5:$A$1004,">="&'09_PARAMETRI'!$B$5,'13_VANZARI'!$A$5:$A$1004,"<="&'09_PARAMETRI'!$B$6)<>0))),"")) | M14: =IF($A14="","",IF(AND($D14>0,$H14<>"",$H14<'09_PARAMETRI'!$B$15),"Marjă sub referință",IF(AND($F14<>"",$F14>='09_PARAMETRI'!$B$14,$L14<0.3),"Creștere + penetrare mică",IF(AND($F14<>"",$F14<='09_PARAMETRI'!$B$13),"Produs în scădere",IF($D14=0,"Fără vânzări","Stabil"))))) | N14: =IF($A14="","",IF($M14="Marjă sub referință","Marjă / preț",IF($M14="Creștere + penetrare mică","Creștere produs",IF($M14="Produs în scădere","Cross-sell",IF($M14="Fără vânzări","Proces / operațional","Cross-sell"))))) | O14: =IF($A14="","",IFERROR(IF($M14="Marjă sub referință",MAX(0,$D14*('09_PARAMETRI'!$B$15-$H14)),IF($M14="Creștere + penetrare mică",$D14*0.5,IF($M14="Produs în scădere",MAX(0,$E14-$D14),$D14*0.1))),"")) | P14: =IF(OR($A14="",$D14="",N($D14)<=0),"",$D14+ROW()/1000000)
A15: =IF('11_PRODUSE'!$A15="","",'11_PRODUSE'!$A15) | B15: =IF($A15="","",IFERROR(INDEX('11_PRODUSE'!$B$5:$B$104,MATCH($A15,'11_PRODUSE'!$A$5:$A$104,0)),"")) | C15: =IF($A15="","",IFERROR(INDEX('11_PRODUSE'!$C$5:$C$104,MATCH($A15,'11_PRODUSE'!$A$5:$A$104,0)),"")) | D15: =IF($A15="","",SUMIFS('13_VANZARI'!$H$5:$H$1004,'13_VANZARI'!$E$5:$E$1004,$A15,'13_VANZARI'!$A$5:$A$1004,">="&'09_PARAMETRI'!$B$5,'13_VANZARI'!$A$5:$A$1004,"<="&'09_PARAMETRI'!$B$6)) | E15: =IF($A15="","",SUMIFS('13_VANZARI'!$H$5:$H$1004,'13_VANZARI'!$E$5:$E$1004,$A15,'13_VANZARI'!$A$5:$A$1004,">="&'09_PARAMETRI'!$B$7,'13_VANZARI'!$A$5:$A$1004,"<="&'09_PARAMETRI'!$B$8)) | F15: =IF($A15="","",IFERROR(IF($E15=0,"",($D15-$E15)/ABS($E15)),"")) | G15: =IF($A15="","",SUMIFS('13_VANZARI'!$K$5:$K$1004,'13_VANZARI'!$E$5:$E$1004,$A15,'13_VANZARI'!$A$5:$A$1004,">="&'09_PARAMETRI'!$B$5,'13_VANZARI'!$A$5:$A$1004,"<="&'09_PARAMETRI'!$B$6)) | H15: =IF($A15="","",IFERROR($G15/$D15,"")) | I15: =IF($A15="","",SUMIFS('13_VANZARI'!$G$5:$G$1004,'13_VANZARI'!$E$5:$E$1004,$A15,'13_VANZARI'!$A$5:$A$1004,">="&'09_PARAMETRI'!$B$5,'13_VANZARI'!$A$5:$A$1004,"<="&'09_PARAMETRI'!$B$6)) | J15: =IF($A15="","",IFERROR($D15/$I15,"")) | K15: =IF($A15="","",SUMPRODUCT(('10_CLIENTI'!$A$5:$A$204<>"")*(SUMIFS('13_VANZARI'!$H$5:$H$1004,'13_VANZARI'!$E$5:$E$1004,$A15,'13_VANZARI'!$D$5:$D$1004,'10_CLIENTI'!$A$5:$A$204,'13_VANZARI'!$A$5:$A$1004,">="&'09_PARAMETRI'!$B$5,'13_VANZARI'!$A$5:$A$1004,"<="&'09_PARAMETRI'!$B$6)<>0))) | L15: =IF($A15="","",IFERROR($K15/(SUMPRODUCT(('10_CLIENTI'!$A$5:$A$204<>"")*(SUMIFS('13_VANZARI'!$H$5:$H$1004,'13_VANZARI'!$D$5:$D$1004,'10_CLIENTI'!$A$5:$A$204,'13_VANZARI'!$A$5:$A$1004,">="&'09_PARAMETRI'!$B$5,'13_VANZARI'!$A$5:$A$1004,"<="&'09_PARAMETRI'!$B$6)<>0))),"")) | M15: =IF($A15="","",IF(AND($D15>0,$H15<>"",$H15<'09_PARAMETRI'!$B$15),"Marjă sub referință",IF(AND($F15<>"",$F15>='09_PARAMETRI'!$B$14,$L15<0.3),"Creștere + penetrare mică",IF(AND($F15<>"",$F15<='09_PARAMETRI'!$B$13),"Produs în scădere",IF($D15=0,"Fără vânzări","Stabil"))))) | N15: =IF($A15="","",IF($M15="Marjă sub referință","Marjă / preț",IF($M15="Creștere + penetrare mică","Creștere produs",IF($M15="Produs în scădere","Cross-sell",IF($M15="Fără vânzări","Proces / operațional","Cross-sell"))))) | O15: =IF($A15="","",IFERROR(IF($M15="Marjă sub referință",MAX(0,$D15*('09_PARAMETRI'!$B$15-$H15)),IF($M15="Creștere + penetrare mică",$D15*0.5,IF($M15="Produs în scădere",MAX(0,$E15-$D15),$D15*0.1))),"")) | P15: =IF(OR($A15="",$D15="",N($D15)<=0),"",$D15+ROW()/1000000)
A16: =IF('11_PRODUSE'!$A16="","",'11_PRODUSE'!$A16) | B16: =IF($A16="","",IFERROR(INDEX('11_PRODUSE'!$B$5:$B$104,MATCH($A16,'11_PRODUSE'!$A$5:$A$104,0)),"")) | C16: =IF($A16="","",IFERROR(INDEX('11_PRODUSE'!$C$5:$C$104,MATCH($A16,'11_PRODUSE'!$A$5:$A$104,0)),"")) | D16: =IF($A16="","",SUMIFS('13_VANZARI'!$H$5:$H$1004,'13_VANZARI'!$E$5:$E$1004,$A16,'13_VANZARI'!$A$5:$A$1004,">="&'09_PARAMETRI'!$B$5,'13_VANZARI'!$A$5:$A$1004,"<="&'09_PARAMETRI'!$B$6)) | E16: =IF($A16="","",SUMIFS('13_VANZARI'!$H$5:$H$1004,'13_VANZARI'!$E$5:$E$1004,$A16,'13_VANZARI'!$A$5:$A$1004,">="&'09_PARAMETRI'!$B$7,'13_VANZARI'!$A$5:$A$1004,"<="&'09_PARAMETRI'!$B$8)) | F16: =IF($A16="","",IFERROR(IF($E16=0,"",($D16-$E16)/ABS($E16)),"")) | G16: =IF($A16="","",SUMIFS('13_VANZARI'!$K$5:$K$1004,'13_VANZARI'!$E$5:$E$1004,$A16,'13_VANZARI'!$A$5:$A$1004,">="&'09_PARAMETRI'!$B$5,'13_VANZARI'!$A$5:$A$1004,"<="&'09_PARAMETRI'!$B$6)) | H16: =IF($A16="","",IFERROR($G16/$D16,"")) | I16: =IF($A16="","",SUMIFS('13_VANZARI'!$G$5:$G$1004,'13_VANZARI'!$E$5:$E$1004,$A16,'13_VANZARI'!$A$5:$A$1004,">="&'09_PARAMETRI'!$B$5,'13_VANZARI'!$A$5:$A$1004,"<="&'09_PARAMETRI'!$B$6)) | J16: =IF($A16="","",IFERROR($D16/$I16,"")) | K16: =IF($A16="","",SUMPRODUCT(('10_CLIENTI'!$A$5:$A$204<>"")*(SUMIFS('13_VANZARI'!$H$5:$H$1004,'13_VANZARI'!$E$5:$E$1004,$A16,'13_VANZARI'!$D$5:$D$1004,'10_CLIENTI'!$A$5:$A$204,'13_VANZARI'!$A$5:$A$1004,">="&'09_PARAMETRI'!$B$5,'13_VANZARI'!$A$5:$A$1004,"<="&'09_PARAMETRI'!$B$6)<>0))) | L16: =IF($A16="","",IFERROR($K16/(SUMPRODUCT(('10_CLIENTI'!$A$5:$A$204<>"")*(SUMIFS('13_VANZARI'!$H$5:$H$1004,'13_VANZARI'!$D$5:$D$1004,'10_CLIENTI'!$A$5:$A$204,'13_VANZARI'!$A$5:$A$1004,">="&'09_PARAMETRI'!$B$5,'13_VANZARI'!$A$5:$A$1004,"<="&'09_PARAMETRI'!$B$6)<>0))),"")) | M16: =IF($A16="","",IF(AND($D16>0,$H16<>"",$H16<'09_PARAMETRI'!$B$15),"Marjă sub referință",IF(AND($F16<>"",$F16>='09_PARAMETRI'!$B$14,$L16<0.3),"Creștere + penetrare mică",IF(AND($F16<>"",$F16<='09_PARAMETRI'!$B$13),"Produs în scădere",IF($D16=0,"Fără vânzări","Stabil"))))) | N16: =IF($A16="","",IF($M16="Marjă sub referință","Marjă / preț",IF($M16="Creștere + penetrare mică","Creștere produs",IF($M16="Produs în scădere","Cross-sell",IF($M16="Fără vânzări","Proces / operațional","Cross-sell"))))) | O16: =IF($A16="","",IFERROR(IF($M16="Marjă sub referință",MAX(0,$D16*('09_PARAMETRI'!$B$15-$H16)),IF($M16="Creștere + penetrare mică",$D16*0.5,IF($M16="Produs în scădere",MAX(0,$E16-$D16),$D16*0.1))),"")) | P16: =IF(OR($A16="",$D16="",N($D16)<=0),"",$D16+ROW()/1000000)
... A104: =IF('11_PRODUSE'!$A104="","",'11_PRODUSE'!$A104) | B104: =IF($A104="","",IFERROR(INDEX('11_PRODUSE'!$B$5:$B$104,MATCH($A104,'11_PRODUSE'!$A$5:$A$104,0)),"")) | C104: =IF($A104="","",IFERROR(INDEX('11_PRODUSE'!$C$5:$C$104,MATCH($A104,'11_PRODUSE'!$A$5:$A$104,0)),"")) | D104: =IF($A104="","",SUMIFS('13_VANZARI'!$H$5:$H$1004,'13_VANZARI'!$E$5:$E$1004,$A104,'13_VANZARI'!$A$5:$A$1004,">="&'09_PARAMETRI'!$B$5,'13_VANZARI'!$A$5:$A$1004,"<="&'09_PARAMETRI'!$B$6)) | E104: =IF($A104="","",SUMIFS('13_VANZARI'!$H$5:$H$1004,'13_VANZARI'!$E$5:$E$1004,$A104,'13_VANZARI'!$A$5:$A$1004,">="&'09_PARAMETRI'!$B$7,'13_VANZARI'!$A$5:$A$1004,"<="&'09_PARAMETRI'!$B$8)) | F104: =IF($A104="","",IFERROR(IF($E104=0,"",($D104-$E104)/ABS($E104)),"")) | G104: =IF($A104="","",SUMIFS('13_VANZARI'!$K$5:$K$1004,'13_VANZARI'!$E$5:$E$1004,$A104,'13_VANZARI'!$A$5:$A$1004,">="&'09_PARAMETRI'!$B$5,'13_VANZARI'!$A$5:$A$1004,"<="&'09_PARAMETRI'!$B$6)) | H104: =IF($A104="","",IFERROR($G104/$D104,"")) | I104: =IF($A104="","",SUMIFS('13_VANZARI'!$G$5:$G$1004,'13_VANZARI'!$E$5:$E$1004,$A104,'13_VANZARI'!$A$5:$A$1004,">="&'09_PARAMETRI'!$B$5,'13_VANZARI'!$A$5:$A$1004,"<="&'09_PARAMETRI'!$B$6)) | J104: =IF($A104="","",IFERROR($D104/$I104,"")) | K104: =IF($A104="","",SUMPRODUCT(('10_CLIENTI'!$A$5:$A$204<>"")*(SUMIFS('13_VANZARI'!$H$5:$H$1004,'13_VANZARI'!$E$5:$E$1004,$A104,'13_VANZARI'!$D$5:$D$1004,'10_CLIENTI'!$A$5:$A$204,'13_VANZARI'!$A$5:$A$1004,">="&'09_PARAMETRI'!$B$5,'13_VANZARI'!$A$5:$A$1004,"<="&'09_PARAMETRI'!$B$6)<>0))) | L104: =IF($A104="","",IFERROR($K104/(SUMPRODUCT(('10_CLIENTI'!$A$5:$A$204<>"")*(SUMIFS('13_VANZARI'!$H$5:$H$1004,'13_VANZARI'!$D$5:$D$1004,'10_CLIENTI'!$A$5:$A$204,'13_VANZARI'!$A$5:$A$1004,">="&'09_PARAMETRI'!$B$5,'13_VANZARI'!$A$5:$A$1004,"<="&'09_PARAMETRI'!$B$6)<>0))),"")) | M104: =IF($A104="","",IF(AND($D104>0,$H104<>"",$H104<'09_PARAMETRI'!$B$15),"Marjă sub referință",IF(AND($F104<>"",$F104>='09_PARAMETRI'!$B$14,$L104<0.3),"Creștere + penetrare mică",IF(AND($F104<>"",$F104<='09_PARAMETRI'!$B$13),"Produs în scădere",IF($D104=0,"Fără vânzări","Stabil"))))) | N104: =IF($A104="","",IF($M104="Marjă sub referință","Marjă / preț",IF($M104="Creștere + penetrare mică","Creștere produs",IF($M104="Produs în scădere","Cross-sell",IF($M104="Fără vânzări","Proces / operațional","Cross-sell"))))) | O104: =IF($A104="","",IFERROR(IF($M104="Marjă sub referință",MAX(0,$D104*('09_PARAMETRI'!$B$15-$H104)),IF($M104="Creștere + penetrare mică",$D104*0.5,IF($M104="Produs în scădere",MAX(0,$E104-$D104),$D104*0.1))),"")) | P104: =IF(OR($A104="",$D104="",N($D104)<=0),"",$D104+ROW()/1000000)

Sheet 23_ANALIZA_OAMENI
A1: 23 — ANALIZA ECHIPEI
A2: Productivitate și atingere de țintă pe om. Nu este un instrument de evaluare a performanței individuale, ci de identificat unde ajută coachingul.
A4: ID persoană | B4: Nume | C4: Rol | D4: Echipă | E4: FTE | F4: Venit — curent | G4: Venit — comparativ | H4: Δ venit % | I4: Profit brut | J4: Marjă % | K4: Clienți activi | L4: Venit / FTE | M4: Țintă | N4: Atingere țintă % | O4: Semnal | P4: Oportunitate sugerată | Q4: Potențial estimat
A5: =IF('12_OAMENI'!$A5="","",'12_OAMENI'!$A5) | B5: =IF($A5="","",IFERROR(INDEX('12_OAMENI'!$B$5:$B$64,MATCH($A5,'12_OAMENI'!$A$5:$A$64,0)),"")) | C5: =IF($A5="","",IFERROR(INDEX('12_OAMENI'!$C$5:$C$64,MATCH($A5,'12_OAMENI'!$A$5:$A$64,0)),"")) | D5: =IF($A5="","",IFERROR(INDEX('12_OAMENI'!$D$5:$D$64,MATCH($A5,'12_OAMENI'!$A$5:$A$64,0)),"")) | E5: =IF($A5="","",IFERROR(INDEX('12_OAMENI'!$E$5:$E$64,MATCH($A5,'12_OAMENI'!$A$5:$A$64,0)),"")) | F5: =IF($A5="","",SUMIFS('13_VANZARI'!$H$5:$H$1004,'13_VANZARI'!$F$5:$F$1004,$A5,'13_VANZARI'!$A$5:$A$1004,">="&'09_PARAMETRI'!$B$5,'13_VANZARI'!$A$5:$A$1004,"<="&'09_PARAMETRI'!$B$6)) | G5: =IF($A5="","",SUMIFS('13_VANZARI'!$H$5:$H$1004,'13_VANZARI'!$F$5:$F$1004,$A5,'13_VANZARI'!$A$5:$A$1004,">="&'09_PARAMETRI'!$B$7,'13_VANZARI'!$A$5:$A$1004,"<="&'09_PARAMETRI'!$B$8)) | H5: =IF($A5="","",IFERROR(IF($G5=0,"",($F5-$G5)/ABS($G5)),"")) | I5: =IF($A5="","",SUMIFS('13_VANZARI'!$K$5:$K$1004,'13_VANZARI'!$F$5:$F$1004,$A5,'13_VANZARI'!$A$5:$A$1004,">="&'09_PARAMETRI'!$B$5,'13_VANZARI'!$A$5:$A$1004,"<="&'09_PARAMETRI'!$B$6)) | J5: =IF($A5="","",IFERROR($I5/$F5,"")) | K5: =IF($A5="","",SUMPRODUCT(('10_CLIENTI'!$A$5:$A$204<>"")*(SUMIFS('13_VANZARI'!$H$5:$H$1004,'13_VANZARI'!$F$5:$F$1004,$A5,'13_VANZARI'!$D$5:$D$1004,'10_CLIENTI'!$A$5:$A$204,'13_VANZARI'!$A$5:$A$1004,">="&'09_PARAMETRI'!$B$5,'13_VANZARI'!$A$5:$A$1004,"<="&'09_PARAMETRI'!$B$6)<>0))) | L5: =IF($A5="","",IFERROR($F5/$E5,"")) | M5: =IF($A5="","",SUMIFS('14_TINTE'!$E$5:$E$304,'14_TINTE'!$A$5:$A$304,">="&'09_PARAMETRI'!$B$5,'14_TINTE'!$A$5:$A$304,"<="&'09_PARAMETRI'!$B$6,'14_TINTE'!$D$5:$D$304,"Venit",'14_TINTE'!$B$5:$B$304,"Persoană",'14_TINTE'!$C$5:$C$304,$A5)) | N5: =IF($A5="","",IFERROR(IF($M5=0,"",$F5/$M5),"")) | O5: =IF($A5="","",IF(AND($N5<>"",$N5<'09_PARAMETRI'!$B$18,$M5>0),"Sub țintă",IF(AND($H5<>"",$H5<='09_PARAMETRI'!$B$13),"Portofoliu în scădere",IF(AND($F5>0,$L5<>"",$L5<IFERROR(AVERAGE($L$5:$L$64),0)*0.7),"Productivitate sub medie",IF($F5=0,"Fără vânzări înregistrate","În parametri"))))) | P5: =IF($A5="","",IF($O5="Sub țintă","Gap față de țintă",IF($O5="Portofoliu în scădere","Productivitate vânzări",IF($O5="Productivitate sub medie","Dezvoltare oameni",IF($O5="Fără vânzări înregistrate","Proces / operațional","Productivitate vânzări"))))) | Q5: =IF($A5="","",IFERROR(IF($O5="Sub țintă",MAX(0,$M5-$F5),IF($O5="Portofoliu în scădere",MAX(0,$G5-$F5),$F5*0.15)),""))
A6: =IF('12_OAMENI'!$A6="","",'12_OAMENI'!$A6) | B6: =IF($A6="","",IFERROR(INDEX('12_OAMENI'!$B$5:$B$64,MATCH($A6,'12_OAMENI'!$A$5:$A$64,0)),"")) | C6: =IF($A6="","",IFERROR(INDEX('12_OAMENI'!$C$5:$C$64,MATCH($A6,'12_OAMENI'!$A$5:$A$64,0)),"")) | D6: =IF($A6="","",IFERROR(INDEX('12_OAMENI'!$D$5:$D$64,MATCH($A6,'12_OAMENI'!$A$5:$A$64,0)),"")) | E6: =IF($A6="","",IFERROR(INDEX('12_OAMENI'!$E$5:$E$64,MATCH($A6,'12_OAMENI'!$A$5:$A$64,0)),"")) | F6: =IF($A6="","",SUMIFS('13_VANZARI'!$H$5:$H$1004,'13_VANZARI'!$F$5:$F$1004,$A6,'13_VANZARI'!$A$5:$A$1004,">="&'09_PARAMETRI'!$B$5,'13_VANZARI'!$A$5:$A$1004,"<="&'09_PARAMETRI'!$B$6)) | G6: =IF($A6="","",SUMIFS('13_VANZARI'!$H$5:$H$1004,'13_VANZARI'!$F$5:$F$1004,$A6,'13_VANZARI'!$A$5:$A$1004,">="&'09_PARAMETRI'!$B$7,'13_VANZARI'!$A$5:$A$1004,"<="&'09_PARAMETRI'!$B$8)) | H6: =IF($A6="","",IFERROR(IF($G6=0,"",($F6-$G6)/ABS($G6)),"")) | I6: =IF($A6="","",SUMIFS('13_VANZARI'!$K$5:$K$1004,'13_VANZARI'!$F$5:$F$1004,$A6,'13_VANZARI'!$A$5:$A$1004,">="&'09_PARAMETRI'!$B$5,'13_VANZARI'!$A$5:$A$1004,"<="&'09_PARAMETRI'!$B$6)) | J6: =IF($A6="","",IFERROR($I6/$F6,"")) | K6: =IF($A6="","",SUMPRODUCT(('10_CLIENTI'!$A$5:$A$204<>"")*(SUMIFS('13_VANZARI'!$H$5:$H$1004,'13_VANZARI'!$F$5:$F$1004,$A6,'13_VANZARI'!$D$5:$D$1004,'10_CLIENTI'!$A$5:$A$204,'13_VANZARI'!$A$5:$A$1004,">="&'09_PARAMETRI'!$B$5,'13_VANZARI'!$A$5:$A$1004,"<="&'09_PARAMETRI'!$B$6)<>0))) | L6: =IF($A6="","",IFERROR($F6/$E6,"")) | M6: =IF($A6="","",SUMIFS('14_TINTE'!$E$5:$E$304,'14_TINTE'!$A$5:$A$304,">="&'09_PARAMETRI'!$B$5,'14_TINTE'!$A$5:$A$304,"<="&'09_PARAMETRI'!$B$6,'14_TINTE'!$D$5:$D$304,"Venit",'14_TINTE'!$B$5:$B$304,"Persoană",'14_TINTE'!$C$5:$C$304,$A6)) | N6: =IF($A6="","",IFERROR(IF($M6=0,"",$F6/$M6),"")) | O6: =IF($A6="","",IF(AND($N6<>"",$N6<'09_PARAMETRI'!$B$18,$M6>0),"Sub țintă",IF(AND($H6<>"",$H6<='09_PARAMETRI'!$B$13),"Portofoliu în scădere",IF(AND($F6>0,$L6<>"",$L6<IFERROR(AVERAGE($L$5:$L$64),0)*0.7),"Productivitate sub medie",IF($F6=0,"Fără vânzări înregistrate","În parametri"))))) | P6: =IF($A6="","",IF($O6="Sub țintă","Gap față de țintă",IF($O6="Portofoliu în scădere","Productivitate vânzări",IF($O6="Productivitate sub medie","Dezvoltare oameni",IF($O6="Fără vânzări înregistrate","Proces / operațional","Productivitate vânzări"))))) | Q6: =IF($A6="","",IFERROR(IF($O6="Sub țintă",MAX(0,$M6-$F6),IF($O6="Portofoliu în scădere",MAX(0,$G6-$F6),$F6*0.15)),""))
A7: =IF('12_OAMENI'!$A7="","",'12_OAMENI'!$A7) | B7: =IF($A7="","",IFERROR(INDEX('12_OAMENI'!$B$5:$B$64,MATCH($A7,'12_OAMENI'!$A$5:$A$64,0)),"")) | C7: =IF($A7="","",IFERROR(INDEX('12_OAMENI'!$C$5:$C$64,MATCH($A7,'12_OAMENI'!$A$5:$A$64,0)),"")) | D7: =IF($A7="","",IFERROR(INDEX('12_OAMENI'!$D$5:$D$64,MATCH($A7,'12_OAMENI'!$A$5:$A$64,0)),"")) | E7: =IF($A7="","",IFERROR(INDEX('12_OAMENI'!$E$5:$E$64,MATCH($A7,'12_OAMENI'!$A$5:$A$64,0)),"")) | F7: =IF($A7="","",SUMIFS('13_VANZARI'!$H$5:$H$1004,'13_VANZARI'!$F$5:$F$1004,$A7,'13_VANZARI'!$A$5:$A$1004,">="&'09_PARAMETRI'!$B$5,'13_VANZARI'!$A$5:$A$1004,"<="&'09_PARAMETRI'!$B$6)) | G7: =IF($A7="","",SUMIFS('13_VANZARI'!$H$5:$H$1004,'13_VANZARI'!$F$5:$F$1004,$A7,'13_VANZARI'!$A$5:$A$1004,">="&'09_PARAMETRI'!$B$7,'13_VANZARI'!$A$5:$A$1004,"<="&'09_PARAMETRI'!$B$8)) | H7: =IF($A7="","",IFERROR(IF($G7=0,"",($F7-$G7)/ABS($G7)),"")) | I7: =IF($A7="","",SUMIFS('13_VANZARI'!$K$5:$K$1004,'13_VANZARI'!$F$5:$F$1004,$A7,'13_VANZARI'!$A$5:$A$1004,">="&'09_PARAMETRI'!$B$5,'13_VANZARI'!$A$5:$A$1004,"<="&'09_PARAMETRI'!$B$6)) | J7: =IF($A7="","",IFERROR($I7/$F7,"")) | K7: =IF($A7="","",SUMPRODUCT(('10_CLIENTI'!$A$5:$A$204<>"")*(SUMIFS('13_VANZARI'!$H$5:$H$1004,'13_VANZARI'!$F$5:$F$1004,$A7,'13_VANZARI'!$D$5:$D$1004,'10_CLIENTI'!$A$5:$A$204,'13_VANZARI'!$A$5:$A$1004,">="&'09_PARAMETRI'!$B$5,'13_VANZARI'!$A$5:$A$1004,"<="&'09_PARAMETRI'!$B$6)<>0))) | L7: =IF($A7="","",IFERROR($F7/$E7,"")) | M7: =IF($A7="","",SUMIFS('14_TINTE'!$E$5:$E$304,'14_TINTE'!$A$5:$A$304,">="&'09_PARAMETRI'!$B$5,'14_TINTE'!$A$5:$A$304,"<="&'09_PARAMETRI'!$B$6,'14_TINTE'!$D$5:$D$304,"Venit",'14_TINTE'!$B$5:$B$304,"Persoană",'14_TINTE'!$C$5:$C$304,$A7)) | N7: =IF($A7="","",IFERROR(IF($M7=0,"",$F7/$M7),"")) | O7: =IF($A7="","",IF(AND($N7<>"",$N7<'09_PARAMETRI'!$B$18,$M7>0),"Sub țintă",IF(AND($H7<>"",$H7<='09_PARAMETRI'!$B$13),"Portofoliu în scădere",IF(AND($F7>0,$L7<>"",$L7<IFERROR(AVERAGE($L$5:$L$64),0)*0.7),"Productivitate sub medie",IF($F7=0,"Fără vânzări înregistrate","În parametri"))))) | P7: =IF($A7="","",IF($O7="Sub țintă","Gap față de țintă",IF($O7="Portofoliu în scădere","Productivitate vânzări",IF($O7="Productivitate sub medie","Dezvoltare oameni",IF($O7="Fără vânzări înregistrate","Proces / operațional","Productivitate vânzări"))))) | Q7: =IF($A7="","",IFERROR(IF($O7="Sub țintă",MAX(0,$M7-$F7),IF($O7="Portofoliu în scădere",MAX(0,$G7-$F7),$F7*0.15)),""))
A8: =IF('12_OAMENI'!$A8="","",'12_OAMENI'!$A8) | B8: =IF($A8="","",IFERROR(INDEX('12_OAMENI'!$B$5:$B$64,MATCH($A8,'12_OAMENI'!$A$5:$A$64,0)),"")) | C8: =IF($A8="","",IFERROR(INDEX('12_OAMENI'!$C$5:$C$64,MATCH($A8,'12_OAMENI'!$A$5:$A$64,0)),"")) | D8: =IF($A8="","",IFERROR(INDEX('12_OAMENI'!$D$5:$D$64,MATCH($A8,'12_OAMENI'!$A$5:$A$64,0)),"")) | E8: =IF($A8="","",IFERROR(INDEX('12_OAMENI'!$E$5:$E$64,MATCH($A8,'12_OAMENI'!$A$5:$A$64,0)),"")) | F8: =IF($A8="","",SUMIFS('13_VANZARI'!$H$5:$H$1004,'13_VANZARI'!$F$5:$F$1004,$A8,'13_VANZARI'!$A$5:$A$1004,">="&'09_PARAMETRI'!$B$5,'13_VANZARI'!$A$5:$A$1004,"<="&'09_PARAMETRI'!$B$6)) | G8: =IF($A8="","",SUMIFS('13_VANZARI'!$H$5:$H$1004,'13_VANZARI'!$F$5:$F$1004,$A8,'13_VANZARI'!$A$5:$A$1004,">="&'09_PARAMETRI'!$B$7,'13_VANZARI'!$A$5:$A$1004,"<="&'09_PARAMETRI'!$B$8)) | H8: =IF($A8="","",IFERROR(IF($G8=0,"",($F8-$G8)/ABS($G8)),"")) | I8: =IF($A8="","",SUMIFS('13_VANZARI'!$K$5:$K$1004,'13_VANZARI'!$F$5:$F$1004,$A8,'13_VANZARI'!$A$5:$A$1004,">="&'09_PARAMETRI'!$B$5,'13_VANZARI'!$A$5:$A$1004,"<="&'09_PARAMETRI'!$B$6)) | J8: =IF($A8="","",IFERROR($I8/$F8,"")) | K8: =IF($A8="","",SUMPRODUCT(('10_CLIENTI'!$A$5:$A$204<>"")*(SUMIFS('13_VANZARI'!$H$5:$H$1004,'13_VANZARI'!$F$5:$F$1004,$A8,'13_VANZARI'!$D$5:$D$1004,'10_CLIENTI'!$A$5:$A$204,'13_VANZARI'!$A$5:$A$1004,">="&'09_PARAMETRI'!$B$5,'13_VANZARI'!$A$5:$A$1004,"<="&'09_PARAMETRI'!$B$6)<>0))) | L8: =IF($A8="","",IFERROR($F8/$E8,"")) | M8: =IF($A8="","",SUMIFS('14_TINTE'!$E$5:$E$304,'14_TINTE'!$A$5:$A$304,">="&'09_PARAMETRI'!$B$5,'14_TINTE'!$A$5:$A$304,"<="&'09_PARAMETRI'!$B$6,'14_TINTE'!$D$5:$D$304,"Venit",'14_TINTE'!$B$5:$B$304,"Persoană",'14_TINTE'!$C$5:$C$304,$A8)) | N8: =IF($A8="","",IFERROR(IF($M8=0,"",$F8/$M8),"")) | O8: =IF($A8="","",IF(AND($N8<>"",$N8<'09_PARAMETRI'!$B$18,$M8>0),"Sub țintă",IF(AND($H8<>"",$H8<='09_PARAMETRI'!$B$13),"Portofoliu în scădere",IF(AND($F8>0,$L8<>"",$L8<IFERROR(AVERAGE($L$5:$L$64),0)*0.7),"Productivitate sub medie",IF($F8=0,"Fără vânzări înregistrate","În parametri"))))) | P8: =IF($A8="","",IF($O8="Sub țintă","Gap față de țintă",IF($O8="Portofoliu în scădere","Productivitate vânzări",IF($O8="Productivitate sub medie","Dezvoltare oameni",IF($O8="Fără vânzări înregistrate","Proces / operațional","Productivitate vânzări"))))) | Q8: =IF($A8="","",IFERROR(IF($O8="Sub țintă",MAX(0,$M8-$F8),IF($O8="Portofoliu în scădere",MAX(0,$G8-$F8),$F8*0.15)),""))
A9: =IF('12_OAMENI'!$A9="","",'12_OAMENI'!$A9) | B9: =IF($A9="","",IFERROR(INDEX('12_OAMENI'!$B$5:$B$64,MATCH($A9,'12_OAMENI'!$A$5:$A$64,0)),"")) | C9: =IF($A9="","",IFERROR(INDEX('12_OAMENI'!$C$5:$C$64,MATCH($A9,'12_OAMENI'!$A$5:$A$64,0)),"")) | D9: =IF($A9="","",IFERROR(INDEX('12_OAMENI'!$D$5:$D$64,MATCH($A9,'12_OAMENI'!$A$5:$A$64,0)),"")) | E9: =IF($A9="","",IFERROR(INDEX('12_OAMENI'!$E$5:$E$64,MATCH($A9,'12_OAMENI'!$A$5:$A$64,0)),"")) | F9: =IF($A9="","",SUMIFS('13_VANZARI'!$H$5:$H$1004,'13_VANZARI'!$F$5:$F$1004,$A9,'13_VANZARI'!$A$5:$A$1004,">="&'09_PARAMETRI'!$B$5,'13_VANZARI'!$A$5:$A$1004,"<="&'09_PARAMETRI'!$B$6)) | G9: =IF($A9="","",SUMIFS('13_VANZARI'!$H$5:$H$1004,'13_VANZARI'!$F$5:$F$1004,$A9,'13_VANZARI'!$A$5:$A$1004,">="&'09_PARAMETRI'!$B$7,'13_VANZARI'!$A$5:$A$1004,"<="&'09_PARAMETRI'!$B$8)) | H9: =IF($A9="","",IFERROR(IF($G9=0,"",($F9-$G9)/ABS($G9)),"")) | I9: =IF($A9="","",SUMIFS('13_VANZARI'!$K$5:$K$1004,'13_VANZARI'!$F$5:$F$1004,$A9,'13_VANZARI'!$A$5:$A$1004,">="&'09_PARAMETRI'!$B$5,'13_VANZARI'!$A$5:$A$1004,"<="&'09_PARAMETRI'!$B$6)) | J9: =IF($A9="","",IFERROR($I9/$F9,"")) | K9: =IF($A9="","",SUMPRODUCT(('10_CLIENTI'!$A$5:$A$204<>"")*(SUMIFS('13_VANZARI'!$H$5:$H$1004,'13_VANZARI'!$F$5:$F$1004,$A9,'13_VANZARI'!$D$5:$D$1004,'10_CLIENTI'!$A$5:$A$204,'13_VANZARI'!$A$5:$A$1004,">="&'09_PARAMETRI'!$B$5,'13_VANZARI'!$A$5:$A$1004,"<="&'09_PARAMETRI'!$B$6)<>0))) | L9: =IF($A9="","",IFERROR($F9/$E9,"")) | M9: =IF($A9="","",SUMIFS('14_TINTE'!$E$5:$E$304,'14_TINTE'!$A$5:$A$304,">="&'09_PARAMETRI'!$B$5,'14_TINTE'!$A$5:$A$304,"<="&'09_PARAMETRI'!$B$6,'14_TINTE'!$D$5:$D$304,"Venit",'14_TINTE'!$B$5:$B$304,"Persoană",'14_TINTE'!$C$5:$C$304,$A9)) | N9: =IF($A9="","",IFERROR(IF($M9=0,"",$F9/$M9),"")) | O9: =IF($A9="","",IF(AND($N9<>"",$N9<'09_PARAMETRI'!$B$18,$M9>0),"Sub țintă",IF(AND($H9<>"",$H9<='09_PARAMETRI'!$B$13),"Portofoliu în scădere",IF(AND($F9>0,$L9<>"",$L9<IFERROR(AVERAGE($L$5:$L$64),0)*0.7),"Productivitate sub medie",IF($F9=0,"Fără vânzări înregistrate","În parametri"))))) | P9: =IF($A9="","",IF($O9="Sub țintă","Gap față de țintă",IF($O9="Portofoliu în scădere","Productivitate vânzări",IF($O9="Productivitate sub medie","Dezvoltare oameni",IF($O9="Fără vânzări înregistrate","Proces / operațional","Productivitate vânzări"))))) | Q9: =IF($A9="","",IFERROR(IF($O9="Sub țintă",MAX(0,$M9-$F9),IF($O9="Portofoliu în scădere",MAX(0,$G9-$F9),$F9*0.15)),""))
A10: =IF('12_OAMENI'!$A10="","",'12_OAMENI'!$A10) | B10: =IF($A10="","",IFERROR(INDEX('12_OAMENI'!$B$5:$B$64,MATCH($A10,'12_OAMENI'!$A$5:$A$64,0)),"")) | C10: =IF($A10="","",IFERROR(INDEX('12_OAMENI'!$C$5:$C$64,MATCH($A10,'12_OAMENI'!$A$5:$A$64,0)),"")) | D10: =IF($A10="","",IFERROR(INDEX('12_OAMENI'!$D$5:$D$64,MATCH($A10,'12_OAMENI'!$A$5:$A$64,0)),"")) | E10: =IF($A10="","",IFERROR(INDEX('12_OAMENI'!$E$5:$E$64,MATCH($A10,'12_OAMENI'!$A$5:$A$64,0)),"")) | F10: =IF($A10="","",SUMIFS('13_VANZARI'!$H$5:$H$1004,'13_VANZARI'!$F$5:$F$1004,$A10,'13_VANZARI'!$A$5:$A$1004,">="&'09_PARAMETRI'!$B$5,'13_VANZARI'!$A$5:$A$1004,"<="&'09_PARAMETRI'!$B$6)) | G10: =IF($A10="","",SUMIFS('13_VANZARI'!$H$5:$H$1004,'13_VANZARI'!$F$5:$F$1004,$A10,'13_VANZARI'!$A$5:$A$1004,">="&'09_PARAMETRI'!$B$7,'13_VANZARI'!$A$5:$A$1004,"<="&'09_PARAMETRI'!$B$8)) | H10: =IF($A10="","",IFERROR(IF($G10=0,"",($F10-$G10)/ABS($G10)),"")) | I10: =IF($A10="","",SUMIFS('13_VANZARI'!$K$5:$K$1004,'13_VANZARI'!$F$5:$F$1004,$A10,'13_VANZARI'!$A$5:$A$1004,">="&'09_PARAMETRI'!$B$5,'13_VANZARI'!$A$5:$A$1004,"<="&'09_PARAMETRI'!$B$6)) | J10: =IF($A10="","",IFERROR($I10/$F10,"")) | K10: =IF($A10="","",SUMPRODUCT(('10_CLIENTI'!$A$5:$A$204<>"")*(SUMIFS('13_VANZARI'!$H$5:$H$1004,'13_VANZARI'!$F$5:$F$1004,$A10,'13_VANZARI'!$D$5:$D$1004,'10_CLIENTI'!$A$5:$A$204,'13_VANZARI'!$A$5:$A$1004,">="&'09_PARAMETRI'!$B$5,'13_VANZARI'!$A$5:$A$1004,"<="&'09_PARAMETRI'!$B$6)<>0))) | L10: =IF($A10="","",IFERROR($F10/$E10,"")) | M10: =IF($A10="","",SUMIFS('14_TINTE'!$E$5:$E$304,'14_TINTE'!$A$5:$A$304,">="&'09_PARAMETRI'!$B$5,'14_TINTE'!$A$5:$A$304,"<="&'09_PARAMETRI'!$B$6,'14_TINTE'!$D$5:$D$304,"Venit",'14_TINTE'!$B$5:$B$304,"Persoană",'14_TINTE'!$C$5:$C$304,$A10)) | N10: =IF($A10="","",IFERROR(IF($M10=0,"",$F10/$M10),"")) | O10: =IF($A10="","",IF(AND($N10<>"",$N10<'09_PARAMETRI'!$B$18,$M10>0),"Sub țintă",IF(AND($H10<>"",$H10<='09_PARAMETRI'!$B$13),"Portofoliu în scădere",IF(AND($F10>0,$L10<>"",$L10<IFERROR(AVERAGE($L$5:$L$64),0)*0.7),"Productivitate sub medie",IF($F10=0,"Fără vânzări înregistrate","În parametri"))))) | P10: =IF($A10="","",IF($O10="Sub țintă","Gap față de țintă",IF($O10="Portofoliu în scădere","Productivitate vânzări",IF($O10="Productivitate sub medie","Dezvoltare oameni",IF($O10="Fără vânzări înregistrate","Proces / operațional","Productivitate vânzări"))))) | Q10: =IF($A10="","",IFERROR(IF($O10="Sub țintă",MAX(0,$M10-$F10),IF($O10="Portofoliu în scădere",MAX(0,$G10-$F10),$F10*0.15)),""))
A11: =IF('12_OAMENI'!$A11="","",'12_OAMENI'!$A11) | B11: =IF($A11="","",IFERROR(INDEX('12_OAMENI'!$B$5:$B$64,MATCH($A11,'12_OAMENI'!$A$5:$A$64,0)),"")) | C11: =IF($A11="","",IFERROR(INDEX('12_OAMENI'!$C$5:$C$64,MATCH($A11,'12_OAMENI'!$A$5:$A$64,0)),"")) | D11: =IF($A11="","",IFERROR(INDEX('12_OAMENI'!$D$5:$D$64,MATCH($A11,'12_OAMENI'!$A$5:$A$64,0)),"")) | E11: =IF($A11="","",IFERROR(INDEX('12_OAMENI'!$E$5:$E$64,MATCH($A11,'12_OAMENI'!$A$5:$A$64,0)),"")) | F11: =IF($A11="","",SUMIFS('13_VANZARI'!$H$5:$H$1004,'13_VANZARI'!$F$5:$F$1004,$A11,'13_VANZARI'!$A$5:$A$1004,">="&'09_PARAMETRI'!$B$5,'13_VANZARI'!$A$5:$A$1004,"<="&'09_PARAMETRI'!$B$6)) | G11: =IF($A11="","",SUMIFS('13_VANZARI'!$H$5:$H$1004,'13_VANZARI'!$F$5:$F$1004,$A11,'13_VANZARI'!$A$5:$A$1004,">="&'09_PARAMETRI'!$B$7,'13_VANZARI'!$A$5:$A$1004,"<="&'09_PARAMETRI'!$B$8)) | H11: =IF($A11="","",IFERROR(IF($G11=0,"",($F11-$G11)/ABS($G11)),"")) | I11: =IF($A11="","",SUMIFS('13_VANZARI'!$K$5:$K$1004,'13_VANZARI'!$F$5:$F$1004,$A11,'13_VANZARI'!$A$5:$A$1004,">="&'09_PARAMETRI'!$B$5,'13_VANZARI'!$A$5:$A$1004,"<="&'09_PARAMETRI'!$B$6)) | J11: =IF($A11="","",IFERROR($I11/$F11,"")) | K11: =IF($A11="","",SUMPRODUCT(('10_CLIENTI'!$A$5:$A$204<>"")*(SUMIFS('13_VANZARI'!$H$5:$H$1004,'13_VANZARI'!$F$5:$F$1004,$A11,'13_VANZARI'!$D$5:$D$1004,'10_CLIENTI'!$A$5:$A$204,'13_VANZARI'!$A$5:$A$1004,">="&'09_PARAMETRI'!$B$5,'13_VANZARI'!$A$5:$A$1004,"<="&'09_PARAMETRI'!$B$6)<>0))) | L11: =IF($A11="","",IFERROR($F11/$E11,"")) | M11: =IF($A11="","",SUMIFS('14_TINTE'!$E$5:$E$304,'14_TINTE'!$A$5:$A$304,">="&'09_PARAMETRI'!$B$5,'14_TINTE'!$A$5:$A$304,"<="&'09_PARAMETRI'!$B$6,'14_TINTE'!$D$5:$D$304,"Venit",'14_TINTE'!$B$5:$B$304,"Persoană",'14_TINTE'!$C$5:$C$304,$A11)) | N11: =IF($A11="","",IFERROR(IF($M11=0,"",$F11/$M11),"")) | O11: =IF($A11="","",IF(AND($N11<>"",$N11<'09_PARAMETRI'!$B$18,$M11>0),"Sub țintă",IF(AND($H11<>"",$H11<='09_PARAMETRI'!$B$13),"Portofoliu în scădere",IF(AND($F11>0,$L11<>"",$L11<IFERROR(AVERAGE($L$5:$L$64),0)*0.7),"Productivitate sub medie",IF($F11=0,"Fără vânzări înregistrate","În parametri"))))) | P11: =IF($A11="","",IF($O11="Sub țintă","Gap față de țintă",IF($O11="Portofoliu în scădere","Productivitate vânzări",IF($O11="Productivitate sub medie","Dezvoltare oameni",IF($O11="Fără vânzări înregistrate","Proces / operațional","Productivitate vânzări"))))) | Q11: =IF($A11="","",IFERROR(IF($O11="Sub țintă",MAX(0,$M11-$F11),IF($O11="Portofoliu în scădere",MAX(0,$G11-$F11),$F11*0.15)),""))
A12: =IF('12_OAMENI'!$A12="","",'12_OAMENI'!$A12) | B12: =IF($A12="","",IFERROR(INDEX('12_OAMENI'!$B$5:$B$64,MATCH($A12,'12_OAMENI'!$A$5:$A$64,0)),"")) | C12: =IF($A12="","",IFERROR(INDEX('12_OAMENI'!$C$5:$C$64,MATCH($A12,'12_OAMENI'!$A$5:$A$64,0)),"")) | D12: =IF($A12="","",IFERROR(INDEX('12_OAMENI'!$D$5:$D$64,MATCH($A12,'12_OAMENI'!$A$5:$A$64,0)),"")) | E12: =IF($A12="","",IFERROR(INDEX('12_OAMENI'!$E$5:$E$64,MATCH($A12,'12_OAMENI'!$A$5:$A$64,0)),"")) | F12: =IF($A12="","",SUMIFS('13_VANZARI'!$H$5:$H$1004,'13_VANZARI'!$F$5:$F$1004,$A12,'13_VANZARI'!$A$5:$A$1004,">="&'09_PARAMETRI'!$B$5,'13_VANZARI'!$A$5:$A$1004,"<="&'09_PARAMETRI'!$B$6)) | G12: =IF($A12="","",SUMIFS('13_VANZARI'!$H$5:$H$1004,'13_VANZARI'!$F$5:$F$1004,$A12,'13_VANZARI'!$A$5:$A$1004,">="&'09_PARAMETRI'!$B$7,'13_VANZARI'!$A$5:$A$1004,"<="&'09_PARAMETRI'!$B$8)) | H12: =IF($A12="","",IFERROR(IF($G12=0,"",($F12-$G12)/ABS($G12)),"")) | I12: =IF($A12="","",SUMIFS('13_VANZARI'!$K$5:$K$1004,'13_VANZARI'!$F$5:$F$1004,$A12,'13_VANZARI'!$A$5:$A$1004,">="&'09_PARAMETRI'!$B$5,'13_VANZARI'!$A$5:$A$1004,"<="&'09_PARAMETRI'!$B$6)) | J12: =IF($A12="","",IFERROR($I12/$F12,"")) | K12: =IF($A12="","",SUMPRODUCT(('10_CLIENTI'!$A$5:$A$204<>"")*(SUMIFS('13_VANZARI'!$H$5:$H$1004,'13_VANZARI'!$F$5:$F$1004,$A12,'13_VANZARI'!$D$5:$D$1004,'10_CLIENTI'!$A$5:$A$204,'13_VANZARI'!$A$5:$A$1004,">="&'09_PARAMETRI'!$B$5,'13_VANZARI'!$A$5:$A$1004,"<="&'09_PARAMETRI'!$B$6)<>0))) | L12: =IF($A12="","",IFERROR($F12/$E12,"")) | M12: =IF($A12="","",SUMIFS('14_TINTE'!$E$5:$E$304,'14_TINTE'!$A$5:$A$304,">="&'09_PARAMETRI'!$B$5,'14_TINTE'!$A$5:$A$304,"<="&'09_PARAMETRI'!$B$6,'14_TINTE'!$D$5:$D$304,"Venit",'14_TINTE'!$B$5:$B$304,"Persoană",'14_TINTE'!$C$5:$C$304,$A12)) | N12: =IF($A12="","",IFERROR(IF($M12=0,"",$F12/$M12),"")) | O12: =IF($A12="","",IF(AND($N12<>"",$N12<'09_PARAMETRI'!$B$18,$M12>0),"Sub țintă",IF(AND($H12<>"",$H12<='09_PARAMETRI'!$B$13),"Portofoliu în scădere",IF(AND($F12>0,$L12<>"",$L12<IFERROR(AVERAGE($L$5:$L$64),0)*0.7),"Productivitate sub medie",IF($F12=0,"Fără vânzări înregistrate","În parametri"))))) | P12: =IF($A12="","",IF($O12="Sub țintă","Gap față de țintă",IF($O12="Portofoliu în scădere","Productivitate vânzări",IF($O12="Productivitate sub medie","Dezvoltare oameni",IF($O12="Fără vânzări înregistrate","Proces / operațional","Productivitate vânzări"))))) | Q12: =IF($A12="","",IFERROR(IF($O12="Sub țintă",MAX(0,$M12-$F12),IF($O12="Portofoliu în scădere",MAX(0,$G12-$F12),$F12*0.15)),""))
A13: =IF('12_OAMENI'!$A13="","",'12_OAMENI'!$A13) | B13: =IF($A13="","",IFERROR(INDEX('12_OAMENI'!$B$5:$B$64,MATCH($A13,'12_OAMENI'!$A$5:$A$64,0)),"")) | C13: =IF($A13="","",IFERROR(INDEX('12_OAMENI'!$C$5:$C$64,MATCH($A13,'12_OAMENI'!$A$5:$A$64,0)),"")) | D13: =IF($A13="","",IFERROR(INDEX('12_OAMENI'!$D$5:$D$64,MATCH($A13,'12_OAMENI'!$A$5:$A$64,0)),"")) | E13: =IF($A13="","",IFERROR(INDEX('12_OAMENI'!$E$5:$E$64,MATCH($A13,'12_OAMENI'!$A$5:$A$64,0)),"")) | F13: =IF($A13="","",SUMIFS('13_VANZARI'!$H$5:$H$1004,'13_VANZARI'!$F$5:$F$1004,$A13,'13_VANZARI'!$A$5:$A$1004,">="&'09_PARAMETRI'!$B$5,'13_VANZARI'!$A$5:$A$1004,"<="&'09_PARAMETRI'!$B$6)) | G13: =IF($A13="","",SUMIFS('13_VANZARI'!$H$5:$H$1004,'13_VANZARI'!$F$5:$F$1004,$A13,'13_VANZARI'!$A$5:$A$1004,">="&'09_PARAMETRI'!$B$7,'13_VANZARI'!$A$5:$A$1004,"<="&'09_PARAMETRI'!$B$8)) | H13: =IF($A13="","",IFERROR(IF($G13=0,"",($F13-$G13)/ABS($G13)),"")) | I13: =IF($A13="","",SUMIFS('13_VANZARI'!$K$5:$K$1004,'13_VANZARI'!$F$5:$F$1004,$A13,'13_VANZARI'!$A$5:$A$1004,">="&'09_PARAMETRI'!$B$5,'13_VANZARI'!$A$5:$A$1004,"<="&'09_PARAMETRI'!$B$6)) | J13: =IF($A13="","",IFERROR($I13/$F13,"")) | K13: =IF($A13="","",SUMPRODUCT(('10_CLIENTI'!$A$5:$A$204<>"")*(SUMIFS('13_VANZARI'!$H$5:$H$1004,'13_VANZARI'!$F$5:$F$1004,$A13,'13_VANZARI'!$D$5:$D$1004,'10_CLIENTI'!$A$5:$A$204,'13_VANZARI'!$A$5:$A$1004,">="&'09_PARAMETRI'!$B$5,'13_VANZARI'!$A$5:$A$1004,"<="&'09_PARAMETRI'!$B$6)<>0))) | L13: =IF($A13="","",IFERROR($F13/$E13,"")) | M13: =IF($A13="","",SUMIFS('14_TINTE'!$E$5:$E$304,'14_TINTE'!$A$5:$A$304,">="&'09_PARAMETRI'!$B$5,'14_TINTE'!$A$5:$A$304,"<="&'09_PARAMETRI'!$B$6,'14_TINTE'!$D$5:$D$304,"Venit",'14_TINTE'!$B$5:$B$304,"Persoană",'14_TINTE'!$C$5:$C$304,$A13)) | N13: =IF($A13="","",IFERROR(IF($M13=0,"",$F13/$M13),"")) | O13: =IF($A13="","",IF(AND($N13<>"",$N13<'09_PARAMETRI'!$B$18,$M13>0),"Sub țintă",IF(AND($H13<>"",$H13<='09_PARAMETRI'!$B$13),"Portofoliu în scădere",IF(AND($F13>0,$L13<>"",$L13<IFERROR(AVERAGE($L$5:$L$64),0)*0.7),"Productivitate sub medie",IF($F13=0,"Fără vânzări înregistrate","În parametri"))))) | P13: =IF($A13="","",IF($O13="Sub țintă","Gap față de țintă",IF($O13="Portofoliu în scădere","Productivitate vânzări",IF($O13="Productivitate sub medie","Dezvoltare oameni",IF($O13="Fără vânzări înregistrate","Proces / operațional","Productivitate vânzări"))))) | Q13: =IF($A13="","",IFERROR(IF($O13="Sub țintă",MAX(0,$M13-$F13),IF($O13="Portofoliu în scădere",MAX(0,$G13-$F13),$F13*0.15)),""))
A14: =IF('12_OAMENI'!$A14="","",'12_OAMENI'!$A14) | B14: =IF($A14="","",IFERROR(INDEX('12_OAMENI'!$B$5:$B$64,MATCH($A14,'12_OAMENI'!$A$5:$A$64,0)),"")) | C14: =IF($A14="","",IFERROR(INDEX('12_OAMENI'!$C$5:$C$64,MATCH($A14,'12_OAMENI'!$A$5:$A$64,0)),"")) | D14: =IF($A14="","",IFERROR(INDEX('12_OAMENI'!$D$5:$D$64,MATCH($A14,'12_OAMENI'!$A$5:$A$64,0)),"")) | E14: =IF($A14="","",IFERROR(INDEX('12_OAMENI'!$E$5:$E$64,MATCH($A14,'12_OAMENI'!$A$5:$A$64,0)),"")) | F14: =IF($A14="","",SUMIFS('13_VANZARI'!$H$5:$H$1004,'13_VANZARI'!$F$5:$F$1004,$A14,'13_VANZARI'!$A$5:$A$1004,">="&'09_PARAMETRI'!$B$5,'13_VANZARI'!$A$5:$A$1004,"<="&'09_PARAMETRI'!$B$6)) | G14: =IF($A14="","",SUMIFS('13_VANZARI'!$H$5:$H$1004,'13_VANZARI'!$F$5:$F$1004,$A14,'13_VANZARI'!$A$5:$A$1004,">="&'09_PARAMETRI'!$B$7,'13_VANZARI'!$A$5:$A$1004,"<="&'09_PARAMETRI'!$B$8)) | H14: =IF($A14="","",IFERROR(IF($G14=0,"",($F14-$G14)/ABS($G14)),"")) | I14: =IF($A14="","",SUMIFS('13_VANZARI'!$K$5:$K$1004,'13_VANZARI'!$F$5:$F$1004,$A14,'13_VANZARI'!$A$5:$A$1004,">="&'09_PARAMETRI'!$B$5,'13_VANZARI'!$A$5:$A$1004,"<="&'09_PARAMETRI'!$B$6)) | J14: =IF($A14="","",IFERROR($I14/$F14,"")) | K14: =IF($A14="","",SUMPRODUCT(('10_CLIENTI'!$A$5:$A$204<>"")*(SUMIFS('13_VANZARI'!$H$5:$H$1004,'13_VANZARI'!$F$5:$F$1004,$A14,'13_VANZARI'!$D$5:$D$1004,'10_CLIENTI'!$A$5:$A$204,'13_VANZARI'!$A$5:$A$1004,">="&'09_PARAMETRI'!$B$5,'13_VANZARI'!$A$5:$A$1004,"<="&'09_PARAMETRI'!$B$6)<>0))) | L14: =IF($A14="","",IFERROR($F14/$E14,"")) | M14: =IF($A14="","",SUMIFS('14_TINTE'!$E$5:$E$304,'14_TINTE'!$A$5:$A$304,">="&'09_PARAMETRI'!$B$5,'14_TINTE'!$A$5:$A$304,"<="&'09_PARAMETRI'!$B$6,'14_TINTE'!$D$5:$D$304,"Venit",'14_TINTE'!$B$5:$B$304,"Persoană",'14_TINTE'!$C$5:$C$304,$A14)) | N14: =IF($A14="","",IFERROR(IF($M14=0,"",$F14/$M14),"")) | O14: =IF($A14="","",IF(AND($N14<>"",$N14<'09_PARAMETRI'!$B$18,$M14>0),"Sub țintă",IF(AND($H14<>"",$H14<='09_PARAMETRI'!$B$13),"Portofoliu în scădere",IF(AND($F14>0,$L14<>"",$L14<IFERROR(AVERAGE($L$5:$L$64),0)*0.7),"Productivitate sub medie",IF($F14=0,"Fără vânzări înregistrate","În parametri"))))) | P14: =IF($A14="","",IF($O14="Sub țintă","Gap față de țintă",IF($O14="Portofoliu în scădere","Productivitate vânzări",IF($O14="Productivitate sub medie","Dezvoltare oameni",IF($O14="Fără vânzări înregistrate","Proces / operațional","Productivitate vânzări"))))) | Q14: =IF($A14="","",IFERROR(IF($O14="Sub țintă",MAX(0,$M14-$F14),IF($O14="Portofoliu în scădere",MAX(0,$G14-$F14),$F14*0.15)),""))
A15: =IF('12_OAMENI'!$A15="","",'12_OAMENI'!$A15) | B15: =IF($A15="","",IFERROR(INDEX('12_OAMENI'!$B$5:$B$64,MATCH($A15,'12_OAMENI'!$A$5:$A$64,0)),"")) | C15: =IF($A15="","",IFERROR(INDEX('12_OAMENI'!$C$5:$C$64,MATCH($A15,'12_OAMENI'!$A$5:$A$64,0)),"")) | D15: =IF($A15="","",IFERROR(INDEX('12_OAMENI'!$D$5:$D$64,MATCH($A15,'12_OAMENI'!$A$5:$A$64,0)),"")) | E15: =IF($A15="","",IFERROR(INDEX('12_OAMENI'!$E$5:$E$64,MATCH($A15,'12_OAMENI'!$A$5:$A$64,0)),"")) | F15: =IF($A15="","",SUMIFS('13_VANZARI'!$H$5:$H$1004,'13_VANZARI'!$F$5:$F$1004,$A15,'13_VANZARI'!$A$5:$A$1004,">="&'09_PARAMETRI'!$B$5,'13_VANZARI'!$A$5:$A$1004,"<="&'09_PARAMETRI'!$B$6)) | G15: =IF($A15="","",SUMIFS('13_VANZARI'!$H$5:$H$1004,'13_VANZARI'!$F$5:$F$1004,$A15,'13_VANZARI'!$A$5:$A$1004,">="&'09_PARAMETRI'!$B$7,'13_VANZARI'!$A$5:$A$1004,"<="&'09_PARAMETRI'!$B$8)) | H15: =IF($A15="","",IFERROR(IF($G15=0,"",($F15-$G15)/ABS($G15)),"")) | I15: =IF($A15="","",SUMIFS('13_VANZARI'!$K$5:$K$1004,'13_VANZARI'!$F$5:$F$1004,$A15,'13_VANZARI'!$A$5:$A$1004,">="&'09_PARAMETRI'!$B$5,'13_VANZARI'!$A$5:$A$1004,"<="&'09_PARAMETRI'!$B$6)) | J15: =IF($A15="","",IFERROR($I15/$F15,"")) | K15: =IF($A15="","",SUMPRODUCT(('10_CLIENTI'!$A$5:$A$204<>"")*(SUMIFS('13_VANZARI'!$H$5:$H$1004,'13_VANZARI'!$F$5:$F$1004,$A15,'13_VANZARI'!$D$5:$D$1004,'10_CLIENTI'!$A$5:$A$204,'13_VANZARI'!$A$5:$A$1004,">="&'09_PARAMETRI'!$B$5,'13_VANZARI'!$A$5:$A$1004,"<="&'09_PARAMETRI'!$B$6)<>0))) | L15: =IF($A15="","",IFERROR($F15/$E15,"")) | M15: =IF($A15="","",SUMIFS('14_TINTE'!$E$5:$E$304,'14_TINTE'!$A$5:$A$304,">="&'09_PARAMETRI'!$B$5,'14_TINTE'!$A$5:$A$304,"<="&'09_PARAMETRI'!$B$6,'14_TINTE'!$D$5:$D$304,"Venit",'14_TINTE'!$B$5:$B$304,"Persoană",'14_TINTE'!$C$5:$C$304,$A15)) | N15: =IF($A15="","",IFERROR(IF($M15=0,"",$F15/$M15),"")) | O15: =IF($A15="","",IF(AND($N15<>"",$N15<'09_PARAMETRI'!$B$18,$M15>0),"Sub țintă",IF(AND($H15<>"",$H15<='09_PARAMETRI'!$B$13),"Portofoliu în scădere",IF(AND($F15>0,$L15<>"",$L15<IFERROR(AVERAGE($L$5:$L$64),0)*0.7),"Productivitate sub medie",IF($F15=0,"Fără vânzări înregistrate","În parametri"))))) | P15: =IF($A15="","",IF($O15="Sub țintă","Gap față de țintă",IF($O15="Portofoliu în scădere","Productivitate vânzări",IF($O15="Productivitate sub medie","Dezvoltare oameni",IF($O15="Fără vânzări înregistrate","Proces / operațional","Productivitate vânzări"))))) | Q15: =IF($A15="","",IFERROR(IF($O15="Sub țintă",MAX(0,$M15-$F15),IF($O15="Portofoliu în scădere",MAX(0,$G15-$F15),$F15*0.15)),""))
A16: =IF('12_OAMENI'!$A16="","",'12_OAMENI'!$A16) | B16: =IF($A16="","",IFERROR(INDEX('12_OAMENI'!$B$5:$B$64,MATCH($A16,'12_OAMENI'!$A$5:$A$64,0)),"")) | C16: =IF($A16="","",IFERROR(INDEX('12_OAMENI'!$C$5:$C$64,MATCH($A16,'12_OAMENI'!$A$5:$A$64,0)),"")) | D16: =IF($A16="","",IFERROR(INDEX('12_OAMENI'!$D$5:$D$64,MATCH($A16,'12_OAMENI'!$A$5:$A$64,0)),"")) | E16: =IF($A16="","",IFERROR(INDEX('12_OAMENI'!$E$5:$E$64,MATCH($A16,'12_OAMENI'!$A$5:$A$64,0)),"")) | F16: =IF($A16="","",SUMIFS('13_VANZARI'!$H$5:$H$1004,'13_VANZARI'!$F$5:$F$1004,$A16,'13_VANZARI'!$A$5:$A$1004,">="&'09_PARAMETRI'!$B$5,'13_VANZARI'!$A$5:$A$1004,"<="&'09_PARAMETRI'!$B$6)) | G16: =IF($A16="","",SUMIFS('13_VANZARI'!$H$5:$H$1004,'13_VANZARI'!$F$5:$F$1004,$A16,'13_VANZARI'!$A$5:$A$1004,">="&'09_PARAMETRI'!$B$7,'13_VANZARI'!$A$5:$A$1004,"<="&'09_PARAMETRI'!$B$8)) | H16: =IF($A16="","",IFERROR(IF($G16=0,"",($F16-$G16)/ABS($G16)),"")) | I16: =IF($A16="","",SUMIFS('13_VANZARI'!$K$5:$K$1004,'13_VANZARI'!$F$5:$F$1004,$A16,'13_VANZARI'!$A$5:$A$1004,">="&'09_PARAMETRI'!$B$5,'13_VANZARI'!$A$5:$A$1004,"<="&'09_PARAMETRI'!$B$6)) | J16: =IF($A16="","",IFERROR($I16/$F16,"")) | K16: =IF($A16="","",SUMPRODUCT(('10_CLIENTI'!$A$5:$A$204<>"")*(SUMIFS('13_VANZARI'!$H$5:$H$1004,'13_VANZARI'!$F$5:$F$1004,$A16,'13_VANZARI'!$D$5:$D$1004,'10_CLIENTI'!$A$5:$A$204,'13_VANZARI'!$A$5:$A$1004,">="&'09_PARAMETRI'!$B$5,'13_VANZARI'!$A$5:$A$1004,"<="&'09_PARAMETRI'!$B$6)<>0))) | L16: =IF($A16="","",IFERROR($F16/$E16,"")) | M16: =IF($A16="","",SUMIFS('14_TINTE'!$E$5:$E$304,'14_TINTE'!$A$5:$A$304,">="&'09_PARAMETRI'!$B$5,'14_TINTE'!$A$5:$A$304,"<="&'09_PARAMETRI'!$B$6,'14_TINTE'!$D$5:$D$304,"Venit",'14_TINTE'!$B$5:$B$304,"Persoană",'14_TINTE'!$C$5:$C$304,$A16)) | N16: =IF($A16="","",IFERROR(IF($M16=0,"",$F16/$M16),"")) | O16: =IF($A16="","",IF(AND($N16<>"",$N16<'09_PARAMETRI'!$B$18,$M16>0),"Sub țintă",IF(AND($H16<>"",$H16<='09_PARAMETRI'!$B$13),"Portofoliu în scădere",IF(AND($F16>0,$L16<>"",$L16<IFERROR(AVERAGE($L$5:$L$64),0)*0.7),"Productivitate sub medie",IF($F16=0,"Fără vânzări înregistrate","În parametri"))))) | P16: =IF($A16="","",IF($O16="Sub țintă","Gap față de țintă",IF($O16="Portofoliu în scădere","Productivitate vânzări",IF($O16="Productivitate sub medie","Dezvoltare oameni",IF($O16="Fără vânzări înregistrate","Proces / operațional","Productivitate vânzări"))))) | Q16: =IF($A16="","",IFERROR(IF($O16="Sub țintă",MAX(0,$M16-$F16),IF($O16="Portofoliu în scădere",MAX(0,$G16-$F16),$F16*0.15)),""))
... A64: =IF('12_OAMENI'!$A64="","",'12_OAMENI'!$A64) | B64: =IF($A64="","",IFERROR(INDEX('12_OAMENI'!$B$5:$B$64,MATCH($A64,'12_OAMENI'!$A$5:$A$64,0)),"")) | C64: =IF($A64="","",IFERROR(INDEX('12_OAMENI'!$C$5:$C$64,MATCH($A64,'12_OAMENI'!$A$5:$A$64,0)),"")) | D64: =IF($A64="","",IFERROR(INDEX('12_OAMENI'!$D$5:$D$64,MATCH($A64,'12_OAMENI'!$A$5:$A$64,0)),"")) | E64: =IF($A64="","",IFERROR(INDEX('12_OAMENI'!$E$5:$E$64,MATCH($A64,'12_OAMENI'!$A$5:$A$64,0)),"")) | F64: =IF($A64="","",SUMIFS('13_VANZARI'!$H$5:$H$1004,'13_VANZARI'!$F$5:$F$1004,$A64,'13_VANZARI'!$A$5:$A$1004,">="&'09_PARAMETRI'!$B$5,'13_VANZARI'!$A$5:$A$1004,"<="&'09_PARAMETRI'!$B$6)) | G64: =IF($A64="","",SUMIFS('13_VANZARI'!$H$5:$H$1004,'13_VANZARI'!$F$5:$F$1004,$A64,'13_VANZARI'!$A$5:$A$1004,">="&'09_PARAMETRI'!$B$7,'13_VANZARI'!$A$5:$A$1004,"<="&'09_PARAMETRI'!$B$8)) | H64: =IF($A64="","",IFERROR(IF($G64=0,"",($F64-$G64)/ABS($G64)),"")) | I64: =IF($A64="","",SUMIFS('13_VANZARI'!$K$5:$K$1004,'13_VANZARI'!$F$5:$F$1004,$A64,'13_VANZARI'!$A$5:$A$1004,">="&'09_PARAMETRI'!$B$5,'13_VANZARI'!$A$5:$A$1004,"<="&'09_PARAMETRI'!$B$6)) | J64: =IF($A64="","",IFERROR($I64/$F64,"")) | K64: =IF($A64="","",SUMPRODUCT(('10_CLIENTI'!$A$5:$A$204<>"")*(SUMIFS('13_VANZARI'!$H$5:$H$1004,'13_VANZARI'!$F$5:$F$1004,$A64,'13_VANZARI'!$D$5:$D$1004,'10_CLIENTI'!$A$5:$A$204,'13_VANZARI'!$A$5:$A$1004,">="&'09_PARAMETRI'!$B$5,'13_VANZARI'!$A$5:$A$1004,"<="&'09_PARAMETRI'!$B$6)<>0))) | L64: =IF($A64="","",IFERROR($F64/$E64,"")) | M64: =IF($A64="","",SUMIFS('14_TINTE'!$E$5:$E$304,'14_TINTE'!$A$5:$A$304,">="&'09_PARAMETRI'!$B$5,'14_TINTE'!$A$5:$A$304,"<="&'09_PARAMETRI'!$B$6,'14_TINTE'!$D$5:$D$304,"Venit",'14_TINTE'!$B$5:$B$304,"Persoană",'14_TINTE'!$C$5:$C$304,$A64)) | N64: =IF($A64="","",IFERROR(IF($M64=0,"",$F64/$M64),"")) | O64: =IF($A64="","",IF(AND($N64<>"",$N64<'09_PARAMETRI'!$B$18,$M64>0),"Sub țintă",IF(AND($H64<>"",$H64<='09_PARAMETRI'!$B$13),"Portofoliu în scădere",IF(AND($F64>0,$L64<>"",$L64<IFERROR(AVERAGE($L$5:$L$64),0)*0.7),"Productivitate sub medie",IF($F64=0,"Fără vânzări înregistrate","În parametri"))))) | P64: =IF($A64="","",IF($O64="Sub țintă","Gap față de țintă",IF($O64="Portofoliu în scădere","Productivitate vânzări",IF($O64="Productivitate sub medie","Dezvoltare oameni",IF($O64="Fără vânzări înregistrate","Proces / operațional","Productivitate vânzări"))))) | Q64: =IF($A64="","",IFERROR(IF($O64="Sub țintă",MAX(0,$M64-$F64),IF($O64="Portofoliu în scădere",MAX(0,$G64-$F64),$F64*0.15)),""))

Sheet 30_OPORTUNITATI
A1: 30 — OPORTUNITĂȚI PRIORITIZATE
A2: Scor = Impact × Probabilitate × Ușurință. Prioritatea se calculează din pragurile din 09_PARAMETRI. Rândurile de mai jos sunt tipare; înlocuiește-le cu semnalele reale din foile 21-23.
A4: ID | B4: Sursă | C4: Tip oportunitate | D4: Țintă (client / produs / persoană) | E4: Declanșator / dovadă din date | F4: Impact estimat | G4: Probabilitate | H4: Ușurință | I4: Scor | J4: Prioritate | K4: Acțiune recomandată | L4: Responsabil EQUIL | M4: Responsabil client | N4: Termen | O4: Status | P4: Valoare realizată | Q4: Observații | S4: SUMAR PORTOFOLIU
A5: OPP001 | B5: Manual | C5: Recuperare client | E5: Venit în scădere cu peste pragul setat față de perioada comparativă (vezi 21, coloana Semnal) | F5: 42000 | G5: 0.8 | H5: 0.7 | I5: =IF($F5="","",N($F5)*N($G5)*N($H5)) | J5: =IF($I5="","",IF($I5>='09_PARAMETRI'!$B$23,"HIGH",IF($I5>='09_PARAMETRI'!$B$24,"MEDIUM","LOW"))) | K5: Contact direct cu decidentul, diagnostic al volumului pierdut, ofertă de revenire | O5: Identificată | S5: Oportunități identificate | T5: =COUNTA($A$5:$A$64)
A6: OPP002 | B6: Manual | C6: Cross-sell | E6: Client care cumpără produsul X, dar nu și produsul Y pe care îl iau clienți similari | F6: 30000 | G6: 0.7 | H6: 0.9 | I6: =IF($F6="","",N($F6)*N($G6)*N($H6)) | J6: =IF($I6="","",IF($I6>='09_PARAMETRI'!$B$23,"HIGH",IF($I6>='09_PARAMETRI'!$B$24,"MEDIUM","LOW"))) | K6: Propunere pachet, pe baza comportamentului clienților comparabili | O6: Identificată | S6: Valoare brută (impact) | T6: =SUM($F$5:$F$64)
A7: OPP003 | B7: Manual | C7: Marjă / preț | E7: Venit stabil sau în creștere, dar marjă sub referința din 09_PARAMETRI (vezi 22) | F7: 25000 | G7: 0.7 | H7: 0.5 | I7: =IF($F7="","",N($F7)*N($G7)*N($H7)) | J7: =IF($I7="","",IF($I7>='09_PARAMETRI'!$B$23,"HIGH",IF($I7>='09_PARAMETRI'!$B$24,"MEDIUM","LOW"))) | K7: Revizuire preț, mix și cost; renegociere discount pe volum | O7: Identificată | S7: Valoare ponderată (scor) | T7: =SUM($I$5:$I$64)
A8: OPP004 | B8: Manual | C8: Productivitate vânzări | E8: Venit per om semnificativ sub media echipei (vezi 23) | F8: 20000 | G8: 0.6 | H8: 0.8 | I8: =IF($F8="","",N($F8)*N($G8)*N($H8)) | J8: =IF($I8="","",IF($I8>='09_PARAMETRI'!$B$23,"HIGH",IF($I8>='09_PARAMETRI'!$B$24,"MEDIUM","LOW"))) | K8: Coaching pe pipeline, acoperire de cont și rată de conversie | O8: Identificată | S8: Din care HIGH | T8: =SUMIF($J$5:$J$64,"HIGH",$I$5:$I$64)
A9: OPP005 | B9: Manual | C9: Risc concentrare | E9: Un client depășește pragul de concentrare din venitul total | F9: 50000 | G9: 0.8 | H9: 0.5 | I9: =IF($F9="","",N($F9)*N($G9)*N($H9)) | J9: =IF($I9="","",IF($I9>='09_PARAMETRI'!$B$23,"HIGH",IF($I9>='09_PARAMETRI'!$B$24,"MEDIUM","LOW"))) | K9: Plan de retenție pe clientul mare + diversificare activă a bazei | O9: Identificată | S9: Din care MEDIUM | T9: =SUMIF($J$5:$J$64,"MEDIUM",$I$5:$I$64)
A10: OPP006 | B10: Manual | C10: Recuperare NPS | E10: Detractori identificați în 15_NPS, cu motive concrete | F10: 15000 | G10: 0.6 | H10: 0.8 | I10: =IF($F10="","",N($F10)*N($G10)*N($H10)) | J10: =IF($I10="","",IF($I10>='09_PARAMETRI'!$B$23,"HIGH",IF($I10>='09_PARAMETRI'!$B$24,"MEDIUM","LOW"))) | K10: Apel de recuperare în 10 zile, rezolvarea cauzei, remăsurare după 60 de zile | O10: Identificată | S10: Realizat până acum | T10: =SUM($P$5:$P$64)
A11: OPP007 | B11: Manual | C11: Creștere produs | E11: Produs în creștere, dar cu penetrare mică în baza de clienți (vezi 22) | F11: 35000 | G11: 0.7 | H11: 0.7 | I11: =IF($F11="","",N($F11)*N($G11)*N($H11)) | J11: =IF($I11="","",IF($I11>='09_PARAMETRI'!$B$23,"HIGH",IF($I11>='09_PARAMETRI'!$B$24,"MEDIUM","LOW"))) | K11: Campanie dedicată pe clienții care nu îl au încă | O11: Identificată | S11: Acoperire gap față de țintă | T11: =IFERROR(SUM($I$5:$I$64)/'20_KPI'!$B$31,"")
A12: OPP008 | B12: Manual | C12: Gap față de țintă | E12: Atingerea țintei sub pragul din 09_PARAMETRI | F12: 30000 | G12: 0.7 | H12: 0.7 | I12: =IF($F12="","",N($F12)*N($G12)*N($H12)) | J12: =IF($I12="","",IF($I12>='09_PARAMETRI'!$B$23,"HIGH",IF($I12>='09_PARAMETRI'!$B$24,"MEDIUM","LOW"))) | K12: Prioritizarea pipeline-ului pe oportunitățile cu probabilitate mare | O12: Identificată
A13: OPP009 | B13: Manual | C13: Reactivare client | E13: Client dormant: fără achiziții peste pragul de zile setat | F13: 18000 | G13: 0.6 | H13: 0.9 | I13: =IF($F13="","",N($F13)*N($G13)*N($H13)) | J13: =IF($I13="","",IF($I13>='09_PARAMETRI'!$B$23,"HIGH",IF($I13>='09_PARAMETRI'!$B$24,"MEDIUM","LOW"))) | K13: Campanie de reactivare cu ofertă de revenire și termen limitat | O13: Identificată
A14: OPP010 | B14: Manual | C14: Dezvoltare oameni | E14: Diferență de performanță față de colegii comparabili | F14: 22000 | G14: 0.6 | H14: 0.8 | I14: =IF($F14="","",N($F14)*N($G14)*N($H14)) | J14: =IF($I14="","",IF($I14>='09_PARAMETRI'!$B$23,"HIGH",IF($I14>='09_PARAMETRI'!$B$24,"MEDIUM","LOW"))) | K14: Plan de training și shadowing pe cele mai slabe două etape din proces | O14: Identificată
I15: =IF($F15="","",N($F15)*N($G15)*N($H15)) | J15: =IF($I15="","",IF($I15>='09_PARAMETRI'!$B$23,"HIGH",IF($I15>='09_PARAMETRI'!$B$24,"MEDIUM","LOW")))
I16: =IF($F16="","",N($F16)*N($G16)*N($H16)) | J16: =IF($I16="","",IF($I16>='09_PARAMETRI'!$B$23,"HIGH",IF($I16>='09_PARAMETRI'!$B$24,"MEDIUM","LOW")))
I17: =IF($F17="","",N($F17)*N($G17)*N($H17)) | J17: =IF($I17="","",IF($I17>='09_PARAMETRI'!$B$23,"HIGH",IF($I17>='09_PARAMETRI'!$B$24,"MEDIUM","LOW")))
I18: =IF($F18="","",N($F18)*N($G18)*N($H18)) | J18: =IF($I18="","",IF($I18>='09_PARAMETRI'!$B$23,"HIGH",IF($I18>='09_PARAMETRI'!$B$24,"MEDIUM","LOW")))
I19: =IF($F19="","",N($F19)*N($G19)*N($H19)) | J19: =IF($I19="","",IF($I19>='09_PARAMETRI'!$B$23,"HIGH",IF($I19>='09_PARAMETRI'!$B$24,"MEDIUM","LOW")))
I20: =IF($F20="","",N($F20)*N($G20)*N($H20)) | J20: =IF($I20="","",IF($I20>='09_PARAMETRI'!$B$23,"HIGH",IF($I20>='09_PARAMETRI'!$B$24,"MEDIUM","LOW")))
I21: =IF($F21="","",N($F21)*N($G21)*N($H21)) | J21: =IF($I21="","",IF($I21>='09_PARAMETRI'!$B$23,"HIGH",IF($I21>='09_PARAMETRI'!$B$24,"MEDIUM","LOW")))
I22: =IF($F22="","",N($F22)*N($G22)*N($H22)) | J22: =IF($I22="","",IF($I22>='09_PARAMETRI'!$B$23,"HIGH",IF($I22>='09_PARAMETRI'!$B$24,"MEDIUM","LOW")))
I23: =IF($F23="","",N($F23)*N($G23)*N($H23)) | J23: =IF($I23="","",IF($I23>='09_PARAMETRI'!$B$23,"HIGH",IF($I23>='09_PARAMETRI'!$B$24,"MEDIUM","LOW")))
I24: =IF($F24="","",N($F24)*N($G24)*N($H24)) | J24: =IF($I24="","",IF($I24>='09_PARAMETRI'!$B$23,"HIGH",IF($I24>='09_PARAMETRI'!$B$24,"MEDIUM","LOW")))
I25: =IF($F25="","",N($F25)*N($G25)*N($H25)) | J25: =IF($I25="","",IF($I25>='09_PARAMETRI'!$B$23,"HIGH",IF($I25>='09_PARAMETRI'!$B$24,"MEDIUM","LOW")))
I26: =IF($F26="","",N($F26)*N($G26)*N($H26)) | J26: =IF($I26="","",IF($I26>='09_PARAMETRI'!$B$23,"HIGH",IF($I26>='09_PARAMETRI'!$B$24,"MEDIUM","LOW")))
... I64: =IF($F64="","",N($F64)*N($G64)*N($H64)) | J64: =IF($I64="","",IF($I64>='09_PARAMETRI'!$B$23,"HIGH",IF($I64>='09_PARAMETRI'!$B$24,"MEDIUM","LOW")))

Sheet 40_RAPORT
A1: EQUIL GROWTH INTELLIGENCE — RAPORT
A4: IDENTIFICARE
A5: Client | B5: ='09_PARAMETRI'!$B$27 | D5: Se preia din 01_FIRMA.
A6: Perioada analizată | B6: =YEAR('09_PARAMETRI'!$B$5)&"-"&RIGHT("0"&MONTH('09_PARAMETRI'!$B$5),2)&"-"&RIGHT("0"&DAY('09_PARAMETRI'!$B$5),2)&" — "&YEAR('09_PARAMETRI'!$B$6)&"-"&RIGHT("0"&MONTH('09_PARAMETRI'!$B$6),2)&"-"&RIGHT("0"&DAY('09_PARAMETRI'!$B$6),2)
A7: Comparat cu | B7: =YEAR('09_PARAMETRI'!$B$7)&"-"&RIGHT("0"&MONTH('09_PARAMETRI'!$B$7),2)&"-"&RIGHT("0"&DAY('09_PARAMETRI'!$B$7),2)&" — "&YEAR('09_PARAMETRI'!$B$8)&"-"&RIGHT("0"&MONTH('09_PARAMETRI'!$B$8),2)&"-"&RIGHT("0"&DAY('09_PARAMETRI'!$B$8),2)
A8: Monedă | B8: ='09_PARAMETRI'!$B$10
A9: Consultant EQUIL | B9: ='09_PARAMETRI'!$B$28
A11: CONCLUZII AUTOMATE (generate din date)
A12: Venit | B12: =IF('20_KPI'!$B$6=0,"Nu există date de vânzări în perioada selectată. Verifică 13_VANZARI și perioada din 09_PARAMETRI.","Venitul net al perioadei este "&FIXED('20_KPI'!$B$6,0)&" "&'09_PARAMETRI'!$B$10&IF(OR('20_KPI'!$E$6="",'20_KPI'!$E$6=0),", fără perioadă de comparație completată.",", "&IF('20_KPI'!$E$6>=0,"în creștere cu ","în scădere cu ")&FIXED((ABS('20_KPI'!$E$6))*100,1)&"%"&" față de perioada comparativă."))
A13: Marjă | B13: =IF('20_KPI'!$B$6=0,"—","Marja brută este "&FIXED(('20_KPI'!$B$8)*100,1)&"%"&", "&IF('20_KPI'!$B$8>='09_PARAMETRI'!$B$15,"peste","sub")&" referința de "&FIXED(('09_PARAMETRI'!$B$15)*100,1)&"%"&IF('20_KPI'!$B$8>='09_PARAMETRI'!$B$15,". Marja se menține.",". Un singur punct procentual de marjă recuperat înseamnă "&FIXED('20_KPI'!$B$6*0.01,0)&" "&'09_PARAMETRI'!$B$10&"."))
A14: Clienți | B14: =IF('20_KPI'!$B$13=0,"—","Au cumpărat "&FIXED('20_KPI'!$B$13,0)&" clienți, din care "&FIXED('20_KPI'!$B$14,0)&" noi. Venitul mediu pe client este "&FIXED('20_KPI'!$B$15,0)&" "&'09_PARAMETRI'!$B$10&".")
A15: Concentrare | B15: =IF('20_KPI'!$B$6=0,"—","Cel mai mare client aduce "&FIXED(('20_KPI'!$B$18)*100,1)&"%"&" din venit, "&IF('20_KPI'!$B$18>'09_PARAMETRI'!$B$19,"peste pragul de risc de "&FIXED(('09_PARAMETRI'!$B$19)*100,1)&"%"&". Retenția lui este prioritate, nu opțiune.","sub pragul de risc. Baza de clienți este echilibrată."))
A16: Productivitate | B16: =IF('20_KPI'!$B$21=0,"—","Fiecare normă întreagă din echipă aduce "&FIXED('20_KPI'!$B$21,0)&" "&'09_PARAMETRI'!$B$10&" venit în perioada analizată.")
A17: NPS | B17: =IF('20_KPI'!$B$25=0,"Nu există răspunsuri NPS în perioadă. Fără ele, nemulțumirea clienților se vede abia când scad comenzile.","NPS-ul este "&FIXED('20_KPI'!$B$24,0)&", din "&FIXED('20_KPI'!$B$25,0)&" răspunsuri, cu "&FIXED(('20_KPI'!$B$27)*100,0)&"%"&" detractori. "&IF('20_KPI'!$B$24<'09_PARAMETRI'!$B$17,"Este sub pragul agreat de "&FIXED('09_PARAMETRI'!$B$17,0)&"; detractorii intră în planul de acțiuni.","Este peste pragul agreat.")&IF('20_KPI'!$B$25<20," Atenție: sub 20 de răspunsuri, cifra este orientativă, nu concluzivă.",""))
A18: Țintă | B18: =IF('20_KPI'!$B$29=0,"Nu este completată o țintă de venit pentru perioadă (14_TINTE, nivel „Companie”). Fără ea nu se poate măsura gap-ul.","Atingerea țintei este "&FIXED(('20_KPI'!$B$30)*100,1)&"%"&IF('20_KPI'!$B$31>0,", mai lipsesc "&FIXED('20_KPI'!$B$31,0)&" "&'09_PARAMETRI'!$B$10&" până la plan.",", ținta este depășită."))
A19: Oportunități | B19: =IF('30_OPORTUNITATI'!$T$5=0,"Nu sunt încă oportunități completate în 30_OPORTUNITATI.","Sunt "&FIXED('30_OPORTUNITATI'!$T$5,0)&" oportunități identificate, cu valoare ponderată de "&FIXED('30_OPORTUNITATI'!$T$7,0)&" "&'09_PARAMETRI'!$B$10&IF(AND('20_KPI'!$B$31>0,'30_OPORTUNITATI'!$T$11<>""),IF('30_OPORTUNITATI'!$T$11>=1,", mai mult decât suficient cât să acopere gap-ul față de țintă ("&FIXED(('30_OPORTUNITATI'!$T$11)*100,0)&"%"&" din el).",", adică "&FIXED(('30_OPORTUNITATI'!$T$11)*100,0)&"%"&" din gap-ul față de țintă."),"."))
A20: Cum se folosesc | B20: Sunt materie primă, nu text final: le citești, le verifici și scrii mai jos sinteza în limbajul clientului.
A22: SINTEZA EXECUTIVĂ
A23: Concluzii (se scriu manual) | B23: [3-5 concluzii, formulate în limbajul clientului, sprijinite de cifrele de mai jos] | D23: Regula: fiecare concluzie trebuie să aibă o cifră în spate și o acțiune în față.
A25: INDICATORI CHEIE
A26: Indicator | B26: Perioada curentă | C26: Δ % vs. comparativ | D26: Comentariu
A27: Venit net | B27: ='20_KPI'!$B$6 | C27: ='20_KPI'!$E$6
A28: Profit brut | B28: ='20_KPI'!$B$7 | C28: ='20_KPI'!$E$7
A29: Marjă brută % | B29: ='20_KPI'!$B$8 | C29: ='20_KPI'!$E$8
A30: Clienți activi | B30: ='20_KPI'!$B$13 | C30: ='20_KPI'!$E$13
A31: Venit mediu / client | B31: ='20_KPI'!$B$15 | C31: ='20_KPI'!$E$15
A32: Venit / FTE | B32: ='20_KPI'!$B$21 | C32: ='20_KPI'!$E$21
A33: NPS | B33: ='20_KPI'!$B$24 | C33: ='20_KPI'!$E$24
A34: Atingere țintă % | B34: ='20_KPI'!$B$30 | C34: ='20_KPI'!$E$30
A35: Gap față de țintă | B35: ='20_KPI'!$B$31 | C35: ='20_KPI'!$E$31
A36: Concentrare — cel mai mare client | B36: ='20_KPI'!$B$18 | C36: ='20_KPI'!$E$18
A38: TOP 5 OPORTUNITĂȚI (ordonate după scor)
A39: # | B39: Oportunitate | C39: Scor | D39: Acțiune recomandată
A40: 1 | B40: =IFERROR(INDEX('30_OPORTUNITATI'!$C$5:$C$64,MATCH(LARGE('30_OPORTUNITATI'!$I$5:$I$64,1),'30_OPORTUNITATI'!$I$5:$I$64,0))&IF(INDEX('30_OPORTUNITATI'!$D$5:$D$64,MATCH(LARGE('30_OPORTUNITATI'!$I$5:$I$64,1),'30_OPORTUNITATI'!$I$5:$I$64,0))="",""," — "&INDEX('30_OPORTUNITATI'!$D$5:$D$64,MATCH(LARGE('30_OPORTUNITATI'!$I$5:$I$64,1),'30_OPORTUNITATI'!$I$5:$I$64,0))),"") | C40: =IFERROR(LARGE('30_OPORTUNITATI'!$I$5:$I$64,1),"") | D40: =IFERROR(INDEX('30_OPORTUNITATI'!$K$5:$K$64,MATCH(LARGE('30_OPORTUNITATI'!$I$5:$I$64,1),'30_OPORTUNITATI'!$I$5:$I$64,0)),"")
A41: 2 | B41: =IFERROR(INDEX('30_OPORTUNITATI'!$C$5:$C$64,MATCH(LARGE('30_OPORTUNITATI'!$I$5:$I$64,2),'30_OPORTUNITATI'!$I$5:$I$64,0))&IF(INDEX('30_OPORTUNITATI'!$D$5:$D$64,MATCH(LARGE('30_OPORTUNITATI'!$I$5:$I$64,2),'30_OPORTUNITATI'!$I$5:$I$64,0))="",""," — "&INDEX('30_OPORTUNITATI'!$D$5:$D$64,MATCH(LARGE('30_OPORTUNITATI'!$I$5:$I$64,2),'30_OPORTUNITATI'!$I$5:$I$64,0))),"") | C41: =IFERROR(LARGE('30_OPORTUNITATI'!$I$5:$I$64,2),"") | D41: =IFERROR(INDEX('30_OPORTUNITATI'!$K$5:$K$64,MATCH(LARGE('30_OPORTUNITATI'!$I$5:$I$64,2),'30_OPORTUNITATI'!$I$5:$I$64,0)),"")
A42: 3 | B42: =IFERROR(INDEX('30_OPORTUNITATI'!$C$5:$C$64,MATCH(LARGE('30_OPORTUNITATI'!$I$5:$I$64,3),'30_OPORTUNITATI'!$I$5:$I$64,0))&IF(INDEX('30_OPORTUNITATI'!$D$5:$D$64,MATCH(LARGE('30_OPORTUNITATI'!$I$5:$I$64,3),'30_OPORTUNITATI'!$I$5:$I$64,0))="",""," — "&INDEX('30_OPORTUNITATI'!$D$5:$D$64,MATCH(LARGE('30_OPORTUNITATI'!$I$5:$I$64,3),'30_OPORTUNITATI'!$I$5:$I$64,0))),"") | C42: =IFERROR(LARGE('30_OPORTUNITATI'!$I$5:$I$64,3),"") | D42: =IFERROR(INDEX('30_OPORTUNITATI'!$K$5:$K$64,MATCH(LARGE('30_OPORTUNITATI'!$I$5:$I$64,3),'30_OPORTUNITATI'!$I$5:$I$64,0)),"")
A43: 4 | B43: =IFERROR(INDEX('30_OPORTUNITATI'!$C$5:$C$64,MATCH(LARGE('30_OPORTUNITATI'!$I$5:$I$64,4),'30_OPORTUNITATI'!$I$5:$I$64,0))&IF(INDEX('30_OPORTUNITATI'!$D$5:$D$64,MATCH(LARGE('30_OPORTUNITATI'!$I$5:$I$64,4),'30_OPORTUNITATI'!$I$5:$I$64,0))="",""," — "&INDEX('30_OPORTUNITATI'!$D$5:$D$64,MATCH(LARGE('30_OPORTUNITATI'!$I$5:$I$64,4),'30_OPORTUNITATI'!$I$5:$I$64,0))),"") | C43: =IFERROR(LARGE('30_OPORTUNITATI'!$I$5:$I$64,4),"") | D43: =IFERROR(INDEX('30_OPORTUNITATI'!$K$5:$K$64,MATCH(LARGE('30_OPORTUNITATI'!$I$5:$I$64,4),'30_OPORTUNITATI'!$I$5:$I$64,0)),"")
A44: 5 | B44: =IFERROR(INDEX('30_OPORTUNITATI'!$C$5:$C$64,MATCH(LARGE('30_OPORTUNITATI'!$I$5:$I$64,5),'30_OPORTUNITATI'!$I$5:$I$64,0))&IF(INDEX('30_OPORTUNITATI'!$D$5:$D$64,MATCH(LARGE('30_OPORTUNITATI'!$I$5:$I$64,5),'30_OPORTUNITATI'!$I$5:$I$64,0))="",""," — "&INDEX('30_OPORTUNITATI'!$D$5:$D$64,MATCH(LARGE('30_OPORTUNITATI'!$I$5:$I$64,5),'30_OPORTUNITATI'!$I$5:$I$64,0))),"") | C44: =IFERROR(LARGE('30_OPORTUNITATI'!$I$5:$I$64,5),"") | D44: =IFERROR(INDEX('30_OPORTUNITATI'!$K$5:$K$64,MATCH(LARGE('30_OPORTUNITATI'!$I$5:$I$64,5),'30_OPORTUNITATI'!$I$5:$I$64,0)),"")
A46: VALOAREA TOTALĂ A PLANULUI
A47: Valoare ponderată a oportunităților | B47: ='30_OPORTUNITATI'!$T$7 | D47: Suma scorurilor: impact ajustat cu probabilitatea și ușurința.
A48: Gap față de țintă | B48: ='20_KPI'!$B$31 | D48: Cât lipsește până la țintă în perioada analizată.
A49: Acoperirea gapului | B49: ='30_OPORTUNITATI'!$T$11 | D49: Peste 100% înseamnă că planul acoperă integral deficitul, dacă se execută.
A51: PRIMELE 30 DE ZILE
A52: # | B52: Acțiune | C52: Responsabil | D52: Termen / rezultat așteptat
A53: 1
A54: 2
A55: 3
A56: 4
A57: 5
A59: Notă de metodă | B59: Cifrele provin exclusiv din datele furnizate de client în perioada indicată. Estimările de impact sunt scenarii, nu garanții, și se recalibrează după primele 30 de zile de execuție.

Sheet 41_GRAFICE
A1: 41 — GRAFICE
A2: Se desenează singure din datele introduse. Dacă par goale, apasă Ctrl+Alt+F9 (recalculare completă). Zona de calcul de sub grafice nu se editează.
A59: ZONA DE CALCUL PENTRU GRAFICE — nu se editează, nu se șterge.
A60: Lună | B60: Etichetă | C60: Venit net | D60: Profit brut | E60: Țintă | F60: Marjă % | H60: Top 10 clienți | I60: Venit net | K60: Top 10 produse | L60: Venit net | N60: Categorie NPS | O60: Răspunsuri | Q60: Prioritate | R60: Valoare ponderată
A61: =DATE(YEAR('09_PARAMETRI'!$B$6),MONTH('09_PARAMETRI'!$B$6)+1-12,1) | B61: =YEAR($A61)&"-"&RIGHT("0"&MONTH($A61),2) | C61: =SUMIFS('13_VANZARI'!$H$5:$H$1004,'13_VANZARI'!$A$5:$A$1004,">="&$A61,'13_VANZARI'!$A$5:$A$1004,"<="&DATE(YEAR($A61),MONTH($A61)+1,0)) | D61: =SUMIFS('13_VANZARI'!$K$5:$K$1004,'13_VANZARI'!$A$5:$A$1004,">="&$A61,'13_VANZARI'!$A$5:$A$1004,"<="&DATE(YEAR($A61),MONTH($A61)+1,0)) | E61: =SUMIFS('14_TINTE'!$E$5:$E$304,'14_TINTE'!$A$5:$A$304,">="&$A61,'14_TINTE'!$A$5:$A$304,"<="&DATE(YEAR($A61),MONTH($A61)+1,0),'14_TINTE'!$D$5:$D$304,"Venit",'14_TINTE'!$B$5:$B$304,"Companie") | F61: =IFERROR($D61/$C61,0) | H61: =IFERROR(INDEX('21_ANALIZA_CLIENTI'!$B$5:$B$204,MATCH(LARGE('21_ANALIZA_CLIENTI'!$R$5:$R$204,1),'21_ANALIZA_CLIENTI'!$R$5:$R$204,0)),"") | I61: =IFERROR(INDEX('21_ANALIZA_CLIENTI'!$E$5:$E$204,MATCH(LARGE('21_ANALIZA_CLIENTI'!$R$5:$R$204,1),'21_ANALIZA_CLIENTI'!$R$5:$R$204,0)),0) | K61: =IFERROR(INDEX('22_ANALIZA_PRODUSE'!$B$5:$B$104,MATCH(LARGE('22_ANALIZA_PRODUSE'!$P$5:$P$104,1),'22_ANALIZA_PRODUSE'!$P$5:$P$104,0)),"") | L61: =IFERROR(INDEX('22_ANALIZA_PRODUSE'!$D$5:$D$104,MATCH(LARGE('22_ANALIZA_PRODUSE'!$P$5:$P$104,1),'22_ANALIZA_PRODUSE'!$P$5:$P$104,0)),0) | N61: ="Promotori (9-10)" | O61: =SUMPRODUCT(('15_NPS'!$B$5:$B$504>='09_PARAMETRI'!$B$5)*('15_NPS'!$B$5:$B$504<='09_PARAMETRI'!$B$6)*('15_NPS'!$F$5:$F$504>=9)) | Q61: ="HIGH" | R61: =SUMIF('30_OPORTUNITATI'!$J$5:$J$64,"HIGH",'30_OPORTUNITATI'!$I$5:$I$64)
A62: =DATE(YEAR('09_PARAMETRI'!$B$6),MONTH('09_PARAMETRI'!$B$6)+2-12,1) | B62: =YEAR($A62)&"-"&RIGHT("0"&MONTH($A62),2) | C62: =SUMIFS('13_VANZARI'!$H$5:$H$1004,'13_VANZARI'!$A$5:$A$1004,">="&$A62,'13_VANZARI'!$A$5:$A$1004,"<="&DATE(YEAR($A62),MONTH($A62)+1,0)) | D62: =SUMIFS('13_VANZARI'!$K$5:$K$1004,'13_VANZARI'!$A$5:$A$1004,">="&$A62,'13_VANZARI'!$A$5:$A$1004,"<="&DATE(YEAR($A62),MONTH($A62)+1,0)) | E62: =SUMIFS('14_TINTE'!$E$5:$E$304,'14_TINTE'!$A$5:$A$304,">="&$A62,'14_TINTE'!$A$5:$A$304,"<="&DATE(YEAR($A62),MONTH($A62)+1,0),'14_TINTE'!$D$5:$D$304,"Venit",'14_TINTE'!$B$5:$B$304,"Companie") | F62: =IFERROR($D62/$C62,0) | H62: =IFERROR(INDEX('21_ANALIZA_CLIENTI'!$B$5:$B$204,MATCH(LARGE('21_ANALIZA_CLIENTI'!$R$5:$R$204,2),'21_ANALIZA_CLIENTI'!$R$5:$R$204,0)),"") | I62: =IFERROR(INDEX('21_ANALIZA_CLIENTI'!$E$5:$E$204,MATCH(LARGE('21_ANALIZA_CLIENTI'!$R$5:$R$204,2),'21_ANALIZA_CLIENTI'!$R$5:$R$204,0)),0) | K62: =IFERROR(INDEX('22_ANALIZA_PRODUSE'!$B$5:$B$104,MATCH(LARGE('22_ANALIZA_PRODUSE'!$P$5:$P$104,2),'22_ANALIZA_PRODUSE'!$P$5:$P$104,0)),"") | L62: =IFERROR(INDEX('22_ANALIZA_PRODUSE'!$D$5:$D$104,MATCH(LARGE('22_ANALIZA_PRODUSE'!$P$5:$P$104,2),'22_ANALIZA_PRODUSE'!$P$5:$P$104,0)),0) | N62: ="Pasivi (7-8)" | O62: =SUMPRODUCT(('15_NPS'!$B$5:$B$504>='09_PARAMETRI'!$B$5)*('15_NPS'!$B$5:$B$504<='09_PARAMETRI'!$B$6)*('15_NPS'!$F$5:$F$504>=7)*('15_NPS'!$F$5:$F$504<=8)) | Q62: ="MEDIUM" | R62: =SUMIF('30_OPORTUNITATI'!$J$5:$J$64,"MEDIUM",'30_OPORTUNITATI'!$I$5:$I$64)
A63: =DATE(YEAR('09_PARAMETRI'!$B$6),MONTH('09_PARAMETRI'!$B$6)+3-12,1) | B63: =YEAR($A63)&"-"&RIGHT("0"&MONTH($A63),2) | C63: =SUMIFS('13_VANZARI'!$H$5:$H$1004,'13_VANZARI'!$A$5:$A$1004,">="&$A63,'13_VANZARI'!$A$5:$A$1004,"<="&DATE(YEAR($A63),MONTH($A63)+1,0)) | D63: =SUMIFS('13_VANZARI'!$K$5:$K$1004,'13_VANZARI'!$A$5:$A$1004,">="&$A63,'13_VANZARI'!$A$5:$A$1004,"<="&DATE(YEAR($A63),MONTH($A63)+1,0)) | E63: =SUMIFS('14_TINTE'!$E$5:$E$304,'14_TINTE'!$A$5:$A$304,">="&$A63,'14_TINTE'!$A$5:$A$304,"<="&DATE(YEAR($A63),MONTH($A63)+1,0),'14_TINTE'!$D$5:$D$304,"Venit",'14_TINTE'!$B$5:$B$304,"Companie") | F63: =IFERROR($D63/$C63,0) | H63: =IFERROR(INDEX('21_ANALIZA_CLIENTI'!$B$5:$B$204,MATCH(LARGE('21_ANALIZA_CLIENTI'!$R$5:$R$204,3),'21_ANALIZA_CLIENTI'!$R$5:$R$204,0)),"") | I63: =IFERROR(INDEX('21_ANALIZA_CLIENTI'!$E$5:$E$204,MATCH(LARGE('21_ANALIZA_CLIENTI'!$R$5:$R$204,3),'21_ANALIZA_CLIENTI'!$R$5:$R$204,0)),0) | K63: =IFERROR(INDEX('22_ANALIZA_PRODUSE'!$B$5:$B$104,MATCH(LARGE('22_ANALIZA_PRODUSE'!$P$5:$P$104,3),'22_ANALIZA_PRODUSE'!$P$5:$P$104,0)),"") | L63: =IFERROR(INDEX('22_ANALIZA_PRODUSE'!$D$5:$D$104,MATCH(LARGE('22_ANALIZA_PRODUSE'!$P$5:$P$104,3),'22_ANALIZA_PRODUSE'!$P$5:$P$104,0)),0) | N63: ="Detractori (0-6)" | O63: =SUMPRODUCT(('15_NPS'!$B$5:$B$504>='09_PARAMETRI'!$B$5)*('15_NPS'!$B$5:$B$504<='09_PARAMETRI'!$B$6)*('15_NPS'!$F$5:$F$504<=6)*('15_NPS'!$F$5:$F$504<>"")) | Q63: ="LOW" | R63: =SUMIF('30_OPORTUNITATI'!$J$5:$J$64,"LOW",'30_OPORTUNITATI'!$I$5:$I$64)
A64: =DATE(YEAR('09_PARAMETRI'!$B$6),MONTH('09_PARAMETRI'!$B$6)+4-12,1) | B64: =YEAR($A64)&"-"&RIGHT("0"&MONTH($A64),2) | C64: =SUMIFS('13_VANZARI'!$H$5:$H$1004,'13_VANZARI'!$A$5:$A$1004,">="&$A64,'13_VANZARI'!$A$5:$A$1004,"<="&DATE(YEAR($A64),MONTH($A64)+1,0)) | D64: =SUMIFS('13_VANZARI'!$K$5:$K$1004,'13_VANZARI'!$A$5:$A$1004,">="&$A64,'13_VANZARI'!$A$5:$A$1004,"<="&DATE(YEAR($A64),MONTH($A64)+1,0)) | E64: =SUMIFS('14_TINTE'!$E$5:$E$304,'14_TINTE'!$A$5:$A$304,">="&$A64,'14_TINTE'!$A$5:$A$304,"<="&DATE(YEAR($A64),MONTH($A64)+1,0),'14_TINTE'!$D$5:$D$304,"Venit",'14_TINTE'!$B$5:$B$304,"Companie") | F64: =IFERROR($D64/$C64,0) | H64: =IFERROR(INDEX('21_ANALIZA_CLIENTI'!$B$5:$B$204,MATCH(LARGE('21_ANALIZA_CLIENTI'!$R$5:$R$204,4),'21_ANALIZA_CLIENTI'!$R$5:$R$204,0)),"") | I64: =IFERROR(INDEX('21_ANALIZA_CLIENTI'!$E$5:$E$204,MATCH(LARGE('21_ANALIZA_CLIENTI'!$R$5:$R$204,4),'21_ANALIZA_CLIENTI'!$R$5:$R$204,0)),0) | K64: =IFERROR(INDEX('22_ANALIZA_PRODUSE'!$B$5:$B$104,MATCH(LARGE('22_ANALIZA_PRODUSE'!$P$5:$P$104,4),'22_ANALIZA_PRODUSE'!$P$5:$P$104,0)),"") | L64: =IFERROR(INDEX('22_ANALIZA_PRODUSE'!$D$5:$D$104,MATCH(LARGE('22_ANALIZA_PRODUSE'!$P$5:$P$104,4),'22_ANALIZA_PRODUSE'!$P$5:$P$104,0)),0)
A65: =DATE(YEAR('09_PARAMETRI'!$B$6),MONTH('09_PARAMETRI'!$B$6)+5-12,1) | B65: =YEAR($A65)&"-"&RIGHT("0"&MONTH($A65),2) | C65: =SUMIFS('13_VANZARI'!$H$5:$H$1004,'13_VANZARI'!$A$5:$A$1004,">="&$A65,'13_VANZARI'!$A$5:$A$1004,"<="&DATE(YEAR($A65),MONTH($A65)+1,0)) | D65: =SUMIFS('13_VANZARI'!$K$5:$K$1004,'13_VANZARI'!$A$5:$A$1004,">="&$A65,'13_VANZARI'!$A$5:$A$1004,"<="&DATE(YEAR($A65),MONTH($A65)+1,0)) | E65: =SUMIFS('14_TINTE'!$E$5:$E$304,'14_TINTE'!$A$5:$A$304,">="&$A65,'14_TINTE'!$A$5:$A$304,"<="&DATE(YEAR($A65),MONTH($A65)+1,0),'14_TINTE'!$D$5:$D$304,"Venit",'14_TINTE'!$B$5:$B$304,"Companie") | F65: =IFERROR($D65/$C65,0) | H65: =IFERROR(INDEX('21_ANALIZA_CLIENTI'!$B$5:$B$204,MATCH(LARGE('21_ANALIZA_CLIENTI'!$R$5:$R$204,5),'21_ANALIZA_CLIENTI'!$R$5:$R$204,0)),"") | I65: =IFERROR(INDEX('21_ANALIZA_CLIENTI'!$E$5:$E$204,MATCH(LARGE('21_ANALIZA_CLIENTI'!$R$5:$R$204,5),'21_ANALIZA_CLIENTI'!$R$5:$R$204,0)),0) | K65: =IFERROR(INDEX('22_ANALIZA_PRODUSE'!$B$5:$B$104,MATCH(LARGE('22_ANALIZA_PRODUSE'!$P$5:$P$104,5),'22_ANALIZA_PRODUSE'!$P$5:$P$104,0)),"") | L65: =IFERROR(INDEX('22_ANALIZA_PRODUSE'!$D$5:$D$104,MATCH(LARGE('22_ANALIZA_PRODUSE'!$P$5:$P$104,5),'22_ANALIZA_PRODUSE'!$P$5:$P$104,0)),0)
A66: =DATE(YEAR('09_PARAMETRI'!$B$6),MONTH('09_PARAMETRI'!$B$6)+6-12,1) | B66: =YEAR($A66)&"-"&RIGHT("0"&MONTH($A66),2) | C66: =SUMIFS('13_VANZARI'!$H$5:$H$1004,'13_VANZARI'!$A$5:$A$1004,">="&$A66,'13_VANZARI'!$A$5:$A$1004,"<="&DATE(YEAR($A66),MONTH($A66)+1,0)) | D66: =SUMIFS('13_VANZARI'!$K$5:$K$1004,'13_VANZARI'!$A$5:$A$1004,">="&$A66,'13_VANZARI'!$A$5:$A$1004,"<="&DATE(YEAR($A66),MONTH($A66)+1,0)) | E66: =SUMIFS('14_TINTE'!$E$5:$E$304,'14_TINTE'!$A$5:$A$304,">="&$A66,'14_TINTE'!$A$5:$A$304,"<="&DATE(YEAR($A66),MONTH($A66)+1,0),'14_TINTE'!$D$5:$D$304,"Venit",'14_TINTE'!$B$5:$B$304,"Companie") | F66: =IFERROR($D66/$C66,0) | H66: =IFERROR(INDEX('21_ANALIZA_CLIENTI'!$B$5:$B$204,MATCH(LARGE('21_ANALIZA_CLIENTI'!$R$5:$R$204,6),'21_ANALIZA_CLIENTI'!$R$5:$R$204,0)),"") | I66: =IFERROR(INDEX('21_ANALIZA_CLIENTI'!$E$5:$E$204,MATCH(LARGE('21_ANALIZA_CLIENTI'!$R$5:$R$204,6),'21_ANALIZA_CLIENTI'!$R$5:$R$204,0)),0) | K66: =IFERROR(INDEX('22_ANALIZA_PRODUSE'!$B$5:$B$104,MATCH(LARGE('22_ANALIZA_PRODUSE'!$P$5:$P$104,6),'22_ANALIZA_PRODUSE'!$P$5:$P$104,0)),"") | L66: =IFERROR(INDEX('22_ANALIZA_PRODUSE'!$D$5:$D$104,MATCH(LARGE('22_ANALIZA_PRODUSE'!$P$5:$P$104,6),'22_ANALIZA_PRODUSE'!$P$5:$P$104,0)),0)
A67: =DATE(YEAR('09_PARAMETRI'!$B$6),MONTH('09_PARAMETRI'!$B$6)+7-12,1) | B67: =YEAR($A67)&"-"&RIGHT("0"&MONTH($A67),2) | C67: =SUMIFS('13_VANZARI'!$H$5:$H$1004,'13_VANZARI'!$A$5:$A$1004,">="&$A67,'13_VANZARI'!$A$5:$A$1004,"<="&DATE(YEAR($A67),MONTH($A67)+1,0)) | D67: =SUMIFS('13_VANZARI'!$K$5:$K$1004,'13_VANZARI'!$A$5:$A$1004,">="&$A67,'13_VANZARI'!$A$5:$A$1004,"<="&DATE(YEAR($A67),MONTH($A67)+1,0)) | E67: =SUMIFS('14_TINTE'!$E$5:$E$304,'14_TINTE'!$A$5:$A$304,">="&$A67,'14_TINTE'!$A$5:$A$304,"<="&DATE(YEAR($A67),MONTH($A67)+1,0),'14_TINTE'!$D$5:$D$304,"Venit",'14_TINTE'!$B$5:$B$304,"Companie") | F67: =IFERROR($D67/$C67,0) | H67: =IFERROR(INDEX('21_ANALIZA_CLIENTI'!$B$5:$B$204,MATCH(LARGE('21_ANALIZA_CLIENTI'!$R$5:$R$204,7),'21_ANALIZA_CLIENTI'!$R$5:$R$204,0)),"") | I67: =IFERROR(INDEX('21_ANALIZA_CLIENTI'!$E$5:$E$204,MATCH(LARGE('21_ANALIZA_CLIENTI'!$R$5:$R$204,7),'21_ANALIZA_CLIENTI'!$R$5:$R$204,0)),0) | K67: =IFERROR(INDEX('22_ANALIZA_PRODUSE'!$B$5:$B$104,MATCH(LARGE('22_ANALIZA_PRODUSE'!$P$5:$P$104,7),'22_ANALIZA_PRODUSE'!$P$5:$P$104,0)),"") | L67: =IFERROR(INDEX('22_ANALIZA_PRODUSE'!$D$5:$D$104,MATCH(LARGE('22_ANALIZA_PRODUSE'!$P$5:$P$104,7),'22_ANALIZA_PRODUSE'!$P$5:$P$104,0)),0)
A68: =DATE(YEAR('09_PARAMETRI'!$B$6),MONTH('09_PARAMETRI'!$B$6)+8-12,1) | B68: =YEAR($A68)&"-"&RIGHT("0"&MONTH($A68),2) | C68: =SUMIFS('13_VANZARI'!$H$5:$H$1004,'13_VANZARI'!$A$5:$A$1004,">="&$A68,'13_VANZARI'!$A$5:$A$1004,"<="&DATE(YEAR($A68),MONTH($A68)+1,0)) | D68: =SUMIFS('13_VANZARI'!$K$5:$K$1004,'13_VANZARI'!$A$5:$A$1004,">="&$A68,'13_VANZARI'!$A$5:$A$1004,"<="&DATE(YEAR($A68),MONTH($A68)+1,0)) | E68: =SUMIFS('14_TINTE'!$E$5:$E$304,'14_TINTE'!$A$5:$A$304,">="&$A68,'14_TINTE'!$A$5:$A$304,"<="&DATE(YEAR($A68),MONTH($A68)+1,0),'14_TINTE'!$D$5:$D$304,"Venit",'14_TINTE'!$B$5:$B$304,"Companie") | F68: =IFERROR($D68/$C68,0) | H68: =IFERROR(INDEX('21_ANALIZA_CLIENTI'!$B$5:$B$204,MATCH(LARGE('21_ANALIZA_CLIENTI'!$R$5:$R$204,8),'21_ANALIZA_CLIENTI'!$R$5:$R$204,0)),"") | I68: =IFERROR(INDEX('21_ANALIZA_CLIENTI'!$E$5:$E$204,MATCH(LARGE('21_ANALIZA_CLIENTI'!$R$5:$R$204,8),'21_ANALIZA_CLIENTI'!$R$5:$R$204,0)),0) | K68: =IFERROR(INDEX('22_ANALIZA_PRODUSE'!$B$5:$B$104,MATCH(LARGE('22_ANALIZA_PRODUSE'!$P$5:$P$104,8),'22_ANALIZA_PRODUSE'!$P$5:$P$104,0)),"") | L68: =IFERROR(INDEX('22_ANALIZA_PRODUSE'!$D$5:$D$104,MATCH(LARGE('22_ANALIZA_PRODUSE'!$P$5:$P$104,8),'22_ANALIZA_PRODUSE'!$P$5:$P$104,0)),0)
A69: =DATE(YEAR('09_PARAMETRI'!$B$6),MONTH('09_PARAMETRI'!$B$6)+9-12,1) | B69: =YEAR($A69)&"-"&RIGHT("0"&MONTH($A69),2) | C69: =SUMIFS('13_VANZARI'!$H$5:$H$1004,'13_VANZARI'!$A$5:$A$1004,">="&$A69,'13_VANZARI'!$A$5:$A$1004,"<="&DATE(YEAR($A69),MONTH($A69)+1,0)) | D69: =SUMIFS('13_VANZARI'!$K$5:$K$1004,'13_VANZARI'!$A$5:$A$1004,">="&$A69,'13_VANZARI'!$A$5:$A$1004,"<="&DATE(YEAR($A69),MONTH($A69)+1,0)) | E69: =SUMIFS('14_TINTE'!$E$5:$E$304,'14_TINTE'!$A$5:$A$304,">="&$A69,'14_TINTE'!$A$5:$A$304,"<="&DATE(YEAR($A69),MONTH($A69)+1,0),'14_TINTE'!$D$5:$D$304,"Venit",'14_TINTE'!$B$5:$B$304,"Companie") | F69: =IFERROR($D69/$C69,0) | H69: =IFERROR(INDEX('21_ANALIZA_CLIENTI'!$B$5:$B$204,MATCH(LARGE('21_ANALIZA_CLIENTI'!$R$5:$R$204,9),'21_ANALIZA_CLIENTI'!$R$5:$R$204,0)),"") | I69: =IFERROR(INDEX('21_ANALIZA_CLIENTI'!$E$5:$E$204,MATCH(LARGE('21_ANALIZA_CLIENTI'!$R$5:$R$204,9),'21_ANALIZA_CLIENTI'!$R$5:$R$204,0)),0) | K69: =IFERROR(INDEX('22_ANALIZA_PRODUSE'!$B$5:$B$104,MATCH(LARGE('22_ANALIZA_PRODUSE'!$P$5:$P$104,9),'22_ANALIZA_PRODUSE'!$P$5:$P$104,0)),"") | L69: =IFERROR(INDEX('22_ANALIZA_PRODUSE'!$D$5:$D$104,MATCH(LARGE('22_ANALIZA_PRODUSE'!$P$5:$P$104,9),'22_ANALIZA_PRODUSE'!$P$5:$P$104,0)),0)
A70: =DATE(YEAR('09_PARAMETRI'!$B$6),MONTH('09_PARAMETRI'!$B$6)+10-12,1) | B70: =YEAR($A70)&"-"&RIGHT("0"&MONTH($A70),2) | C70: =SUMIFS('13_VANZARI'!$H$5:$H$1004,'13_VANZARI'!$A$5:$A$1004,">="&$A70,'13_VANZARI'!$A$5:$A$1004,"<="&DATE(YEAR($A70),MONTH($A70)+1,0)) | D70: =SUMIFS('13_VANZARI'!$K$5:$K$1004,'13_VANZARI'!$A$5:$A$1004,">="&$A70,'13_VANZARI'!$A$5:$A$1004,"<="&DATE(YEAR($A70),MONTH($A70)+1,0)) | E70: =SUMIFS('14_TINTE'!$E$5:$E$304,'14_TINTE'!$A$5:$A$304,">="&$A70,'14_TINTE'!$A$5:$A$304,"<="&DATE(YEAR($A70),MONTH($A70)+1,0),'14_TINTE'!$D$5:$D$304,"Venit",'14_TINTE'!$B$5:$B$304,"Companie") | F70: =IFERROR($D70/$C70,0) | H70: =IFERROR(INDEX('21_ANALIZA_CLIENTI'!$B$5:$B$204,MATCH(LARGE('21_ANALIZA_CLIENTI'!$R$5:$R$204,10),'21_ANALIZA_CLIENTI'!$R$5:$R$204,0)),"") | I70: =IFERROR(INDEX('21_ANALIZA_CLIENTI'!$E$5:$E$204,MATCH(LARGE('21_ANALIZA_CLIENTI'!$R$5:$R$204,10),'21_ANALIZA_CLIENTI'!$R$5:$R$204,0)),0) | K70: =IFERROR(INDEX('22_ANALIZA_PRODUSE'!$B$5:$B$104,MATCH(LARGE('22_ANALIZA_PRODUSE'!$P$5:$P$104,10),'22_ANALIZA_PRODUSE'!$P$5:$P$104,0)),"") | L70: =IFERROR(INDEX('22_ANALIZA_PRODUSE'!$D$5:$D$104,MATCH(LARGE('22_ANALIZA_PRODUSE'!$P$5:$P$104,10),'22_ANALIZA_PRODUSE'!$P$5:$P$104,0)),0)
A71: =DATE(YEAR('09_PARAMETRI'!$B$6),MONTH('09_PARAMETRI'!$B$6)+11-12,1) | B71: =YEAR($A71)&"-"&RIGHT("0"&MONTH($A71),2) | C71: =SUMIFS('13_VANZARI'!$H$5:$H$1004,'13_VANZARI'!$A$5:$A$1004,">="&$A71,'13_VANZARI'!$A$5:$A$1004,"<="&DATE(YEAR($A71),MONTH($A71)+1,0)) | D71: =SUMIFS('13_VANZARI'!$K$5:$K$1004,'13_VANZARI'!$A$5:$A$1004,">="&$A71,'13_VANZARI'!$A$5:$A$1004,"<="&DATE(YEAR($A71),MONTH($A71)+1,0)) | E71: =SUMIFS('14_TINTE'!$E$5:$E$304,'14_TINTE'!$A$5:$A$304,">="&$A71,'14_TINTE'!$A$5:$A$304,"<="&DATE(YEAR($A71),MONTH($A71)+1,0),'14_TINTE'!$D$5:$D$304,"Venit",'14_TINTE'!$B$5:$B$304,"Companie") | F71: =IFERROR($D71/$C71,0)
A72: =DATE(YEAR('09_PARAMETRI'!$B$6),MONTH('09_PARAMETRI'!$B$6)+12-12,1) | B72: =YEAR($A72)&"-"&RIGHT("0"&MONTH($A72),2) | C72: =SUMIFS('13_VANZARI'!$H$5:$H$1004,'13_VANZARI'!$A$5:$A$1004,">="&$A72,'13_VANZARI'!$A$5:$A$1004,"<="&DATE(YEAR($A72),MONTH($A72)+1,0)) | D72: =SUMIFS('13_VANZARI'!$K$5:$K$1004,'13_VANZARI'!$A$5:$A$1004,">="&$A72,'13_VANZARI'!$A$5:$A$1004,"<="&DATE(YEAR($A72),MONTH($A72)+1,0)) | E72: =SUMIFS('14_TINTE'!$E$5:$E$304,'14_TINTE'!$A$5:$A$304,">="&$A72,'14_TINTE'!$A$5:$A$304,"<="&DATE(YEAR($A72),MONTH($A72)+1,0),'14_TINTE'!$D$5:$D$304,"Venit",'14_TINTE'!$B$5:$B$304,"Companie") | F72: =IFERROR($D72/$C72,0)

Sheet 90_LISTE
A1: Roluri | B1: Status_date | C1: Obligativitate | D1: Segment_client | E1: Canal | F1: Tip_oportunitate | G1: Prioritate | H1: Status_oportunitate | I1: Set_de_date | J1: Sursa_date | K1: Metrica_tinta | L1: Nivel_tinta | M1: Status_generic | N1: Da_Nu | O1: Categorie_NPS | P1: Tema_NPS | Q1: Tip_document | R1: Moneda | S1: Status_followup
A2: CEO / Administrator | B2: Nesolicitat | C2: Obligatoriu | D2: Key Account | E2: Retail | F2: Recuperare client | G2: HIGH | H2: Identificată | I2: Profil firmă | J2: ERP / Facturare | K2: Venit | L2: Companie | M2: Activ | N2: Da | O2: Promotor | P2: Preț | Q2: Factură | R2: RON | S2: Neînceput
A3: CFO / Contabilitate | B3: Solicitat | C3: Recomandat | D3: Mid-market | E3: Wholesale | F3: Cross-sell | G3: MEDIUM | H3: Validată cu clientul | I3: Clienți | J3: CRM | K3: Profit brut | L3: Persoană | M3: Inactiv | N3: Nu | O3: Pasiv | P3: Calitate | Q3: Storno | R3: EUR | S3: În lucru
A4: Director Vânzări | B4: Primit parțial | C4: Opțional | D4: Small | E4: Online | F4: Up-sell | G4: LOW | H4: În execuție | I4: Produse | J4: Excel intern | K4: Unități | L4: Produs | M4: Prospect | O4: Detractor | P4: Livrare | Q4: Avans | R4: USD | S4: Rezolvat
A5: Sales Ops / CRM | B5: Primit | C5: Auto | D5: Online | E5: Direct | F5: Marjă / preț | H5: Realizată | I5: Oameni | J5: Balanță / Contabilitate | L5: Client | M5: Pierdut | P5: Suport | Q5: Abonament | R5: GBP | S5: Escaladat
A6: Marketing | B6: Validat | D6: Distribuitor | E6: Partener | F6: Productivitate vânzări | H6: Respinsă | I6: Vânzări | J6: HR / State de plată | M6: În pilot | P6: Produs
A7: HR / Resurse Umane | B7: Blocat | D7: Altele | E7: Marketplace | F7: Risc concentrare | H7: Amânată | I7: Ținte / buget | J7: Chestionar NPS | M7: Retras | P7: Relație
A8: IT / ERP | B8: Nu există | F8: Recuperare NPS | I8: NPS / feedback | J8: Interviu / Workshop | P8: Proces comandă
A9: Operațiuni / Logistică | B9: Nu se aplică | F9: Creștere produs | I9: Financiar | J9: Site / public | P9: Altele
A10: Customer Service | F10: Gap față de țintă | I10: Documente / context | J10: Calculat automat
A11: Achiziții | F11: Reactivare client
A12: Consultant extern | F12: Dezvoltare oameni
A13: EQUIL (calculat) | F13: Proces / operațional
